Workbook
Name Emp_Data: Class_3_File!$A$1:$AF$101
Name Slicer_Dept_Name: #N/A
Name Slicer_Region: #N/A

Sheet HR_Data
A1: Emp_ID | B1: Date_of_Birth | C1: Age | D1: Hire_Date | E1: Hiring Source | F1: Dept_ID | G1: Job_Title | H1: Employment_Type | I1: Manager_ID | J1: Base_Salary | K1: Bonus | L1: Total_Salary | M1: Years_of_Experience | N1: Performance_Rating | O1: Attendance_Percentage | P1: Certifications | Q1: Promotion_Eligible | R1: Attrition_Risk | S1: Last_Promotion_Date | T1: Employee_Status | U1: First_Name | V1: Last_Name | W1: Full_Name | X1: ID_Card_Details | Y1: Dept_Name | Z1: Diwali_Month_Salary | AA1: Salary_Seg | AB1: Gender | AC1: Education_Level | AD1: Location | AE1: Region | AF1: Advanced_Cert_Bonus
A2: EMP075 | B2: 31339 | C2: 39 | D2: 41983 | E2: Referral | F2: D_006 | G2: VP Finance | H2: Full-Time | I2: MGR103 | J2: 1450000 | K2: 165000 | L2: =SUM(J2:K2) -> 1615000 | M2: 19 | N2: 4.8 | O2: 99.1 | P2: 4 | Q2: No | R2: Low | S2: 43819 | T2: Active | U2: =VLOOKUP(A2,Emp_Info!$B$1:$G$101,3,0) -> vinay | V2: =_xlfn.XLOOKUP(A2,Emp_Info!$B$2:$B$101,Emp_Info!$A$2:$A$101,,0) -> reddy | W2: =PROPER(_xlfn.CONCAT(U2," ",V2)) -> Vinay Reddy | X2: =UPPER(_xlfn.CONCAT(LEFT(U2),LEFT(V2),RIGHT(A2,3))) -> VR075 | Y2: =HLOOKUP(F2,Dept_Info!$A$2:$I$3,2,0) -> Finance | Z2: =IF(Y2="Sales",L2+(L2*$AG$6),L2) -> 1615000 | AA2: =IF(J2<700000,"Low",IF(AND(J2>700000,J2<900000),"Medium","High")) -> High | AB2: Male | AC2: =INDEX(Emp_Info!$B$1:$G$101,MATCH(HR_Data!$A18,Emp_Info!$B$2:$B$101,0),MATCH(HR_Data!AC$1,Emp_Info!$B$1:$G$1,0)) -> Bachelor | AD2: =INDEX(Emp_Info!$A$1:$G$101,MATCH(HR_Data!$A2,Emp_Info!$B$1:$B$101,0),MATCH(HR_Data!AD$1,Emp_Info!$A$1:$G$1,0)) -> Chennai | AE2: =INDEX(Emp_Info!$A$1:$G$101,MATCH(HR_Data!$A2,Emp_Info!$B$1:$B$101,0),MATCH(HR_Data!AE$1,Emp_Info!$A$1:$G$1,0)) -> South | AF2: =IF(AND(P2>=3,M2>6),"Eligible","Not Eligible") -> Eligible | AG2: HR
A3: EMP019 | B3: 31301 | C3: 39 | D3: 42070 | E3: Job Portal | F3: D_001 | G3: IT Manager | H3: Full-Time | I3: MGR101 | J3: 1450000 | K3: 165000 | L3: =SUM(J3:K3) -> 1615000 | M3: 17 | N3: 4.8 | O3: 99.2 | P3: 5 | Q3: No | R3: Low | S3: 43905 | T3: Active | U3: =VLOOKUP(A3,Emp_Info!$B$1:$G$101,3,0) -> anil | V3: =_xlfn.XLOOKUP(A3,Emp_Info!$B$2:$B$101,Emp_Info!$A$2:$A$101,,0) -> chopra | W3: =PROPER(_xlfn.CONCAT(U3," ",V3)) -> Anil Chopra | X3: =UPPER(_xlfn.CONCAT(LEFT(U3),LEFT(V3),RIGHT(A3,3))) -> AC019 | Y3: =HLOOKUP(F3,Dept_Info!$A$2:$I$3,2,0) -> IT | Z3: =IF(Y3="Sales",L3+(L3*$AG$6),L3) -> 1615000 | AA3: =IF(J3<700000,"Low",IF(AND(J3>700000,J3<900000),"Medium","High")) -> High | AB3: Male | AC3: =INDEX(Emp_Info!$B$1:$G$101,MATCH(HR_Data!$A49,Emp_Info!$B$2:$B$101,0),MATCH(HR_Data!AC$1,Emp_Info!$B$1:$G$1,0)) -> Master | AD3: =INDEX(Emp_Info!$A$1:$G$101,MATCH(HR_Data!$A3,Emp_Info!$B$1:$B$101,0),MATCH(HR_Data!AD$1,Emp_Info!$A$1:$G$1,0)) -> Noida | AE3: =INDEX(Emp_Info!$A$1:$G$101,MATCH(HR_Data!$A3,Emp_Info!$B$1:$B$101,0),MATCH(HR_Data!AE$1,Emp_Info!$A$1:$G$1,0)) -> North | AF3: =IF(AND(P3>=3,M3>6),"Eligible","Not Eligible") -> Eligible
A4: EMP097 | B4: 31462 | D4: 42137 | E4: Referral | F4: D_003 | G4: VP Sales | H4: Full-Time | I4: MGR106 | J4: 1380000 | K4: 158000 | L4: =SUM(J4:K4) -> 1538000 | M4: 18 | N4: 4.8 | O4: 99 | P4: 4 | Q4: No | R4: Low | S4: 43971 | T4: Active | U4: =VLOOKUP(A4,Emp_Info!$B$1:$G$101,3,0) -> rohit | V4: =_xlfn.XLOOKUP(A4,Emp_Info!$B$2:$B$101,Emp_Info!$A$2:$A$101,,0) -> agarwal | W4: =PROPER(_xlfn.CONCAT(U4," ",V4)) -> Rohit Agarwal | X4: =UPPER(_xlfn.CONCAT(LEFT(U4),LEFT(V4),RIGHT(A4,3))) -> RA097 | Y4: =HLOOKUP(F4,Dept_Info!$A$2:$I$3,2,0) -> Sales | Z4: =IF(Y4="Sales",L4+(L4*$AG$6),L4) -> 1768700 | AA4: =IF(J4<700000,"Low",IF(AND(J4>700000,J4<900000),"Medium","High")) -> High | AB4: Male | AC4: =INDEX(Emp_Info!$B$1:$G$101,MATCH(HR_Data!$A86,Emp_Info!$B$2:$B$101,0),MATCH(HR_Data!AC$1,Emp_Info!$B$1:$G$1,0)) -> Master | AD4: =INDEX(Emp_Info!$A$1:$G$101,MATCH(HR_Data!$A4,Emp_Info!$B$1:$B$101,0),MATCH(HR_Data!AD$1,Emp_Info!$A$1:$G$1,0)) -> Bangalore | AE4: =INDEX(Emp_Info!$A$1:$G$101,MATCH(HR_Data!$A4,Emp_Info!$B$1:$B$101,0),MATCH(HR_Data!AE$1,Emp_Info!$A$1:$G$1,0)) -> South | AF4: =IF(AND(P4>=3,M4>6),"Eligible","Not Eligible") -> Eligible
A5: EMP005 | B5: 32129 | C5: 37 | D5: 42559 | E5: Campus | F5: D_005 | G5: Operations Manager | H5: Full-Time | I5: MGR105 | J5: 1100000 | K5: 120000 | L5: =SUM(J5:K5) -> 1220000 | M5: 15 | N5: 4.7 | O5: 99 | P5: 4 | Q5: No | R5: Low | S5: 44397 | T5: Active | U5: =VLOOKUP(A5,Emp_Info!$B$1:$G$101,3,0) -> vikram | V5: =_xlfn.XLOOKUP(A5,Emp_Info!$B$2:$B$101,Emp_Info!$A$2:$A$101,,0) -> singh | W5: =PROPER(_xlfn.CONCAT(U5," ",V5)) -> Vikram Singh | X5: =UPPER(_xlfn.CONCAT(LEFT(U5),LEFT(V5),RIGHT(A5,3))) -> VS005 | Y5: =HLOOKUP(F5,Dept_Info!$A$2:$I$3,2,0) -> Marketing | Z5: =IF(Y5="Sales",L5+(L5*$AG$6),L5) -> 1220000 | AA5: =IF(J5<700000,"Low",IF(AND(J5>700000,J5<900000),"Medium","High")) -> High | AB5: Male | AC5: =INDEX(Emp_Info!$B$1:$G$101,MATCH(HR_Data!$A73,Emp_Info!$B$2:$B$101,0),MATCH(HR_Data!AC$1,Emp_Info!$B$1:$G$1,0)) -> Bachelor | AD5: =INDEX(Emp_Info!$A$1:$G$101,MATCH(HR_Data!$A5,Emp_Info!$B$1:$B$101,0),MATCH(HR_Data!AD$1,Emp_Info!$A$1:$G$1,0)) -> Pune | AE5: =INDEX(Emp_Info!$A$1:$G$101,MATCH(HR_Data!$A5,Emp_Info!$B$1:$B$101,0),MATCH(HR_Data!AE$1,Emp_Info!$A$1:$G$1,0)) -> West | AF5: =IF(AND(P5>=3,M5>6),"Eligible","Not Eligible") -> Eligible | AG5: Bonus
A6: EMP047 | B6: 31355 | C6: 39 | D6: 42115 | E6: LinkedIn | F6: D_005 | G6: Plant Manager | H6: Full-Time | I6: MGR105 | J6: 1080000 | K6: 115000 | L6: =SUM(J6:K6) -> 1195000 | M6: 18 | N6: 4.6 | O6: 98.6 | P6: 4 | Q6: No | R6: Low | S6: 43931 | T6: Active | U6: =VLOOKUP(A6,Emp_Info!$B$1:$G$101,3,0) -> rajeev | V6: =_xlfn.XLOOKUP(A6,Emp_Info!$B$2:$B$101,Emp_Info!$A$2:$A$101,,0) -> bose | W6: =PROPER(_xlfn.CONCAT(U6," ",V6)) -> Rajeev Bose | X6: =UPPER(_xlfn.CONCAT(LEFT(U6),LEFT(V6),RIGHT(A6,3))) -> RB047 | Y6: =HLOOKUP(F6,Dept_Info!$A$2:$I$3,2,0) -> Marketing | Z6: =IF(Y6="Sales",L6+(L6*$AG$6),L6) -> 1195000 | AA6: =IF(J6<700000,"Low",IF(AND(J6>700000,J6<900000),"Medium","High")) -> High | AB6: Male | AC6: =INDEX(Emp_Info!$B$1:$G$101,MATCH(HR_Data!$A70,Emp_Info!$B$2:$B$101,0),MATCH(HR_Data!AC$1,Emp_Info!$B$1:$G$1,0)) -> Bachelor | AD6: =INDEX(Emp_Info!$A$1:$G$101,MATCH(HR_Data!$A6,Emp_Info!$B$1:$B$101,0),MATCH(HR_Data!AD$1,Emp_Info!$A$1:$G$1,0)) -> Pune | AE6: =INDEX(Emp_Info!$A$1:$G$101,MATCH(HR_Data!$A6,Emp_Info!$B$1:$B$101,0),MATCH(HR_Data!AE$1,Emp_Info!$A$1:$G$1,0)) -> West | AF6: =IF(AND(P6>=3,M6>6),"Eligible","Not Eligible") -> Eligible | AG6: 0.15
A7: EMP041 | B7: 33015 | C7: 34 | D7: 43419 | E7: Freelance | F7: D_001 | G7: Cloud Architect | H7: Full-Time | I7: MGR101 | J7: 1050000 | K7: 110000 | L7: =SUM(J7:K7) -> 1160000 | M7: 11 | N7: 4.7 | O7: 98.9 | P7: 5 | Q7: Yes | R7: Low | S7: 44885 | T7: Active | U7: =VLOOKUP(A7,Emp_Info!$B$1:$G$101,3,0) -> varun | V7: =_xlfn.XLOOKUP(A7,Emp_Info!$B$2:$B$101,Emp_Info!$A$2:$A$101,,0) -> kapoor | W7: =PROPER(_xlfn.CONCAT(U7," ",V7)) -> Varun Kapoor | X7: =UPPER(_xlfn.CONCAT(LEFT(U7),LEFT(V7),RIGHT(A7,3))) -> VK041 | Y7: =HLOOKUP(F7,Dept_Info!$A$2:$I$3,2,0) -> IT | Z7: =IF(Y7="Sales",L7+(L7*$AG$6),L7) -> 1160000 | AA7: =IF(J7<700000,"Low",IF(AND(J7>700000,J7<900000),"Medium","High")) -> High | AB7: Male | AC7: =INDEX(Emp_Info!$B$1:$G$101,MATCH(HR_Data!$A55,Emp_Info!$B$2:$B$101,0),MATCH(HR_Data!AC$1,Emp_Info!$B$1:$G$1,0)) -> Bachelor | AD7: =INDEX(Emp_Info!$A$1:$G$101,MATCH(HR_Data!$A7,Emp_Info!$B$1:$B$101,0),MATCH(HR_Data!AD$1,Emp_Info!$A$1:$G$1,0)) -> Noida | AE7: =INDEX(Emp_Info!$A$1:$G$101,MATCH(HR_Data!$A7,Emp_Info!$B$1:$B$101,0),MATCH(HR_Data!AE$1,Emp_Info!$A$1:$G$1,0)) -> North | AF7: =IF(AND(P7>=3,M7>6),"Eligible","Not Eligible") -> Eligible
A8: EMP009 | B8: 31654 | C8: 38 | D8: 42040 | E8: Referral | F8: D_006 | G8: Finance Manager | H8: Full-Time | I8: MGR103 | J8: 1050000 | K8: 105000 | L8: =SUM(J8:K8) -> 1155000 | M8: 16 | N8: 4.6 | O8: 98.5 | P8: 3 | Q8: No | R8: Low | S8: 43871 | T8: Active | U8: =VLOOKUP(A8,Emp_Info!$B$1:$G$101,3,0) -> suresh | V8: =_xlfn.XLOOKUP(A8,Emp_Info!$B$2:$B$101,Emp_Info!$A$2:$A$101,,0) -> nair | W8: =PROPER(_xlfn.CONCAT(U8," ",V8)) -> Suresh Nair | X8: =UPPER(_xlfn.CONCAT(LEFT(U8),LEFT(V8),RIGHT(A8,3))) -> SN009 | Y8: =HLOOKUP(F8,Dept_Info!$A$2:$I$3,2,0) -> Finance | Z8: =IF(Y8="Sales",L8+(L8*$AG$6),L8) -> 1155000 | AA8: =IF(J8<700000,"Low",IF(AND(J8>700000,J8<900000),"Medium","High")) -> High | AB8: Male | AC8: =INDEX(Emp_Info!$B$1:$G$101,MATCH(HR_Data!$A20,Emp_Info!$B$2:$B$101,0),MATCH(HR_Data!AC$1,Emp_Info!$B$1:$G$1,0)) -> Master | AD8: =INDEX(Emp_Info!$A$1:$G$101,MATCH(HR_Data!$A8,Emp_Info!$B$1:$B$101,0),MATCH(HR_Data!AD$1,Emp_Info!$A$1:$G$1,0)) -> Chennai | AE8: =INDEX(Emp_Info!$A$1:$G$101,MATCH(HR_Data!$A8,Emp_Info!$B$1:$B$101,0),MATCH(HR_Data!AE$1,Emp_Info!$A$1:$G$1,0)) -> South | AF8: =IF(AND(P8>=3,M8>6),"Eligible","Not Eligible") -> Eligible
A9: EMP079 | B9: 32516 | C9: 35 | D9: 43329 | E9: Job Portal | F9: D_003 | G9: National Sales Manager | H9: Full-Time | I9: MGR106 | J9: 1020000 | K9: 125000 | L9: =SUM(J9:K9) -> 1145000 | M9: 12 | N9: 4.7 | O9: 98.6 | P9: 3 | Q9: Yes | R9: Low | S9: 45163 | T9: Active | U9: =VLOOKUP(A9,Emp_Info!$B$1:$G$101,3,0) -> nikhil | V9: =_xlfn.XLOOKUP(A9,Emp_Info!$B$2:$B$101,Emp_Info!$A$2:$A$101,,0) -> chopra | W9: =PROPER(_xlfn.CONCAT(U9," ",V9)) -> Nikhil Chopra | X9: =UPPER(_xlfn.CONCAT(LEFT(U9),LEFT(V9),RIGHT(A9,3))) -> NC079 | Y9: =HLOOKUP(F9,Dept_Info!$A$2:$I$3,2,0) -> Sales | Z9: =IF(Y9="Sales",L9+(L9*$AG$6),L9) -> 1316750 | AA9: =IF(J9<700000,"Low",IF(AND(J9>700000,J9<900000),"Medium","High")) -> High | AB9: Male | AC9: =INDEX(Emp_Info!$B$1:$G$101,MATCH(HR_Data!$A92,Emp_Info!$B$2:$B$101,0),MATCH(HR_Data!AC$1,Emp_Info!$B$1:$G$1,0)) -> Master | AD9: =INDEX(Emp_Info!$A$1:$G$101,MATCH(HR_Data!$A9,Emp_Info!$B$1:$B$101,0),MATCH(HR_Data!AD$1,Emp_Info!$A$1:$G$1,0)) -> Hyderabad | AE9: =INDEX(Emp_Info!$A$1:$G$101,MATCH(HR_Data!$A9,Emp_Info!$B$1:$B$101,0),MATCH(HR_Data!AE$1,Emp_Info!$A$1:$G$1,0)) -> South | AF9: =IF(AND(P9>=3,M9>6),"Eligible","Not Eligible") -> Eligible
A10: EMP051 | B10: 31537 | C10: 38 | D10: 42383 | E10: Freelance | F10: D_006 | G10: Controller | H10: Full-Time | I10: MGR103 | J10: 980000 | K10: 98000 | L10: =SUM(J10:K10) -> 1078000 | M10: 16 | N10: 4.5 | O10: 98.2 | P10: 3 | Q10: No | R10: Low | S10: 44216 | T10: Active | U10: =VLOOKUP(A10,Emp_Info!$B$1:$G$101,3,0) -> ramesh | V10: =_xlfn.XLOOKUP(A10,Emp_Info!$B$2:$B$101,Emp_Info!$A$2:$A$101,,0) -> pillai | W10: =PROPER(_xlfn.CONCAT(U10," ",V10)) -> Ramesh Pillai | X10: =UPPER(_xlfn.CONCAT(LEFT(U10),LEFT(V10),RIGHT(A10,3))) -> RP051 | Y10: =HLOOKUP(F10,Dept_Info!$A$2:$I$3,2,0) -> Finance | Z10: =IF(Y10="Sales",L10+(L10*$AG$6),L10) -> 1078000 | AA10: =IF(J10<700000,"Low",IF(AND(J10>700000,J10<900000),"Medium","High")) -> High | AB10: Male | AC10: =INDEX(Emp_Info!$B$1:$G$101,MATCH(HR_Data!$A21,Emp_Info!$B$2:$B$101,0),MATCH(HR_Data!AC$1,Emp_Info!$B$1:$G$1,0)) -> Master | AD10: =INDEX(Emp_Info!$A$1:$G$101,MATCH(HR_Data!$A10,Emp_Info!$B$1:$B$101,0),MATCH(HR_Data!AD$1,Emp_Info!$A$1:$G$1,0)) -> Chennai | AE10: =INDEX(Emp_Info!$A$1:$G$101,MATCH(HR_Data!$A10,Emp_Info!$B$1:$B$101,0),MATCH(HR_Data!AE$1,Emp_Info!$A$1:$G$1,0)) -> South | AF10: =IF(AND(P10>=3,M10>6),"Eligible","Not Eligible") -> Eligible
A11: EMP077 | B11: 32276 | C11: 36 | D11: 43053 | E11: LinkedIn | F11: D_001 | G11: Solutions Architect | H11: Full-Time | I11: MGR101 | J11: 980000 | K11: 98000 | L11: =SUM(J11:K11) -> 1078000 | M11: 13 | N11: 4.6 | O11: 98.4 | P11: 4 | Q11: Yes | R11: Low | S11: 44885 | T11: Active | U11: =VLOOKUP(A11,Emp_Info!$B$1:$G$101,3,0) -> rajat | V11: =_xlfn.XLOOKUP(A11,Emp_Info!$B$2:$B$101,Emp_Info!$A$2:$A$101,,0) -> verma | W11: =PROPER(_xlfn.CONCAT(U11," ",V11)) -> Rajat Verma | X11: =UPPER(_xlfn.CONCAT(LEFT(U11),LEFT(V11),RIGHT(A11,3))) -> RV077 | Y11: =HLOOKUP(F11,Dept_Info!$A$2:$I$3,2,0) -> IT | Z11: =IF(Y11="Sales",L11+(L11*$AG$6),L11) -> 1078000 | AA11: =IF(J11<700000,"Low",IF(AND(J11>700000,J11<900000),"Medium","High")) -> High | AB11: Male | AC11: =INDEX(Emp_Info!$B$1:$G$101,MATCH(HR_Data!$A53,Emp_Info!$B$2:$B$101,0),MATCH(HR_Data!AC$1,Emp_Info!$B$1:$G$1,0)) -> Master | AD11: =INDEX(Emp_Info!$A$1:$G$101,MATCH(HR_Data!$A11,Emp_Info!$B$1:$B$101,0),MATCH(HR_Data!AD$1,Emp_Info!$A$1:$G$1,0)) -> Delhi | AE11: =INDEX(Emp_Info!$A$1:$G$101,MATCH(HR_Data!$A11,Emp_Info!$B$1:$B$101,0),MATCH(HR_Data!AE$1,Emp_Info!$A$1:$G$1,0)) -> North | AF11: =IF(AND(P11>=3,M11>6),"Eligible","Not Eligible") -> Eligible
A12: EMP025 | B12: 33206 | C12: 34 | D12: 43544 | E12: Job Portal | F12: D_003 | G12: Regional Sales Manager | H12: Full-Time | I12: MGR106 | J12: 950000 | K12: 115000 | L12: =SUM(J12:K12) -> 1065000 | M12: 10 | N12: 4.5 | O12: 97.8 | P12: 2 | Q12: Yes | R12: Low | S12: 44995 | T12: Active | U12: =VLOOKUP(A12,Emp_Info!$B$1:$G$101,3,0) -> gaurav | V12: =_xlfn.XLOOKUP(A12,Emp_Info!$B$2:$B$101,Emp_Info!$A$2:$A$101,,0) -> pandey | W12: =PROPER(_xlfn.CONCAT(U12," ",V12)) -> Gaurav Pandey | X12: =UPPER(_xlfn.CONCAT(LEFT(U12),LEFT(V12),RIGHT(A12,3))) -> GP025 | Y12: =HLOOKUP(F12,Dept_Info!$A$2:$I$3,2,0) -> Sales | Z12: =IF(Y12="Sales",L12+(L12*$AG$6),L12) -> 1224750 | AA12: =IF(J12<700000,"Low",IF(AND(J12>700000,J12<900000),"Medium","High")) -> High | AB12: Male | AC12: =INDEX(Emp_Info!$B$1:$G$101,MATCH(HR_Data!$A95,Emp_Info!$B$2:$B$101,0),MATCH(HR_Data!AC$1,Emp_Info!$B$1:$G$1,0)) -> Master | AD12: =INDEX(Emp_Info!$A$1:$G$101,MATCH(HR_Data!$A12,Emp_Info!$B$1:$B$101,0),MATCH(HR_Data!AD$1,Emp_Info!$A$1:$G$1,0)) -> Hyderabad | AE12: =INDEX(Emp_Info!$A$1:$G$101,MATCH(HR_Data!$A12,Emp_Info!$B$1:$B$101,0),MATCH(HR_Data!AE$1,Emp_Info!$A$1:$G$1,0)) -> South | AF12: =IF(AND(P12>=3,M12>6),"Eligible","Not Eligible") -> Not Eligible
A13: EMP061 | B13: 32504 | C13: 36 | D13: 42954 | E13: Referral | F13: D_003 | G13: Enterprise Sales Manager | H13: Full-Time | I13: MGR106 | J13: 940000 | K13: 112000 | L13: =SUM(J13:K13) -> 1052000 | M13: 13 | N13: 4.5 | O13: 98.1 | P13: 3 | Q13: Yes | R13: Low | S13: 44788 | T13: Active | U13: =VLOOKUP(A13,Emp_Info!$B$1:$G$101,3,0) -> siddharth | V13: =_xlfn.XLOOKUP(A13,Emp_Info!$B$2:$B$101,Emp_Info!$A$2:$A$101,,0) -> mehta | W13: =PROPER(_xlfn.CONCAT(U13," ",V13)) -> Siddharth Mehta | X13: =UPPER(_xlfn.CONCAT(LEFT(U13),LEFT(V13),RIGHT(A13,3))) -> SM061 | Y13: =HLOOKUP(F13,Dept_Info!$A$2:$I$3,2,0) -> Sales | Z13: =IF(Y13="Sales",L13+(L13*$AG$6),L13) -> 1209800 | AA13: =IF(J13<700000,"Low",IF(AND(J13>700000,J13<900000),"Medium","High")) -> High | AB13: Male | AC13: =INDEX(Emp_Info!$B$1:$G$101,MATCH(HR_Data!$A91,Emp_Info!$B$2:$B$101,0),MATCH(HR_Data!AC$1,Emp_Info!$B$1:$G$1,0)) -> Bachelor | AD13: =INDEX(Emp_Info!$A$1:$G$101,MATCH(HR_Data!$A13,Emp_Info!$B$1:$B$101,0),MATCH(HR_Data!AD$1,Emp_Info!$A$1:$G$1,0)) -> Delhi | AE13: =INDEX(Emp_Info!$A$1:$G$101,MATCH(HR_Data!$A13,Emp_Info!$B$1:$B$101,0),MATCH(HR_Data!AE$1,Emp_Info!$A$1:$G$1,0)) -> North | AF13: =IF(AND(P13>=3,M13>6),"Eligible","Not Eligible") -> Eligible
A14: EMP002 | B14: 33076 | C14: 34 | D14: 43631 | E14: LinkedIn | F14: D_002 | G14: HR Manager | H14: Full-Time | I14: MGR102 | J14: 950000 | K14: 95000 | L14: =SUM(J14:K14) -> 1045000 | M14: 10 | N14: 4.3 | O14: 98.2 | P14: 2 | Q14: Yes | R14: Low | S14: 45087 | T14: Active | U14: =VLOOKUP(A14,Emp_Info!$B$1:$G$101,3,0) -> priya | V14: =_xlfn.XLOOKUP(A14,Emp_Info!$B$2:$B$101,Emp_Info!$A$2:$A$101,,0) -> sharma | W14: =PROPER(_xlfn.CONCAT(U14," ",V14)) -> Priya Sharma | X14: =UPPER(_xlfn.CONCAT(LEFT(U14),LEFT(V14),RIGHT(A14,3))) -> PS002 | Y14: =HLOOKUP(F14,Dept_Info!$A$2:$I$3,2,0) -> HR | Z14: =IF(Y14="Sales",L14+(L14*$AG$6),L14) -> 1045000 | AA14: =IF(J14<700000,"Low",IF(AND(J14>700000,J14<900000),"Medium","High")) -> High | AB14: Female | AC14: =INDEX(Emp_Info!$B$1:$G$101,MATCH(HR_Data!$A35,Emp_Info!$B$2:$B$101,0),MATCH(HR_Data!AC$1,Emp_Info!$B$1:$G$1,0)) -> Bachelor | AD14: =INDEX(Emp_Info!$A$1:$G$101,MATCH(HR_Data!$A14,Emp_Info!$B$1:$B$101,0),MATCH(HR_Data!AD$1,Emp_Info!$A$1:$G$1,0)) -> Delhi | AE14: =INDEX(Emp_Info!$A$1:$G$101,MATCH(HR_Data!$A14,Emp_Info!$B$1:$B$101,0),MATCH(HR_Data!AE$1,Emp_Info!$A$1:$G$1,0)) -> North | AF14: =IF(AND(P14>=3,M14>6),"Eligible","Not Eligible") -> Not Eligible
A15: EMP092 | B15: 34168 | C15: 31 | D15: 44462 | E15: Job Portal | F15: D_001 | G15: Machine Learning Engineer | H15: Full-Time | I15: MGR101 | J15: 950000 | K15: 95000 | L15: =SUM(J15:K15) -> 1045000 | M15: 6 | N15: 4.6 | O15: 98.3 | P15: 4 | Q15: Yes | R15: Low | S15: NA | T15: Active | U15: =VLOOKUP(A15,Emp_Info!$B$1:$G$101,3,0) -> kavita | V15: =_xlfn.XLOOKUP(A15,Emp_Info!$B$2:$B$101,Emp_Info!$A$2:$A$101,,0) -> pillai | W15: =PROPER(_xlfn.CONCAT(U15," ",V15)) -> Kavita Pillai | X15: =UPPER(_xlfn.CONCAT(LEFT(U15),LEFT(V15),RIGHT(A15,3))) -> KP092 | Y15: =HLOOKUP(F15,Dept_Info!$A$2:$I$3,2,0) -> IT | Z15: =IF(Y15="Sales",L15+(L15*$AG$6),L15) -> 1045000 | AA15: =IF(J15<700000,"Low",IF(AND(J15>700000,J15<900000),"Medium","High")) -> High | AB15: Female | AC15: =INDEX(Emp_Info!$B$1:$G$101,MATCH(HR_Data!$A61,Emp_Info!$B$2:$B$101,0),MATCH(HR_Data!AC$1,Emp_Info!$B$1:$G$1,0)) -> Bachelor | AD15: =INDEX(Emp_Info!$A$1:$G$101,MATCH(HR_Data!$A15,Emp_Info!$B$1:$B$101,0),MATCH(HR_Data!AD$1,Emp_Info!$A$1:$G$1,0)) -> Bangalore | AE15: =INDEX(Emp_Info!$A$1:$G$101,MATCH(HR_Data!$A15,Emp_Info!$B$1:$B$101,0),MATCH(HR_Data!AE$1,Emp_Info!$A$1:$G$1,0)) -> South | AF15: =IF(AND(P15>=3,M15>6),"Eligible","Not Eligible") -> Not Eligible
A16: EMP036 | B16: 33490 | C16: 33 | D16: 43851 | E16: Referral | F16: D_004 | G16: Product Manager | H16: Full-Time | I16: MGR104 | J16: 920000 | K16: 95000 | L16: =SUM(J16:K16) -> 1015000 | M16: 9 | N16: 4.6 | O16: 98.7 | P16: 3 | Q16: Yes | R16: Low | S16: NA | T16: Active | U16: =VLOOKUP(A16,Emp_Info!$B$1:$G$101,3,0) -> pallavi | V16: =_xlfn.XLOOKUP(A16,Emp_Info!$B$2:$B$101,Emp_Info!$A$2:$A$101,,0) -> nambiar | W16: =PROPER(_xlfn.CONCAT(U16," ",V16)) -> Pallavi Nambiar | X16: =UPPER(_xlfn.CONCAT(LEFT(U16),LEFT(V16),RIGHT(A16,3))) -> PN036 | Y16: =HLOOKUP(F16,Dept_Info!$A$2:$I$3,2,0) -> Admin | Z16: =IF(Y16="Sales",L16+(L16*$AG$6),L16) -> 1015000 | AA16: =IF(J16<700000,"Low",IF(AND(J16>700000,J16<900000),"Medium","High")) -> High | AB16: Female | AC16: =INDEX(Emp_Info!$B$1:$G$101,MATCH(HR_Data!$A3,Emp_Info!$B$2:$B$101,0),MATCH(HR_Data!AC$1,Emp_Info!$B$1:$G$1,0)) -> Bachelor | AD16: =INDEX(Emp_Info!$A$1:$G$101,MATCH(HR_Data!$A16,Emp_Info!$B$1:$B$101,0),MATCH(HR_Data!AD$1,Emp_Info!$A$1:$G$1,0)) -> Pune | AE16: =INDEX(Emp_Info!$A$1:$G$101,MATCH(HR_Data!$A16,Emp_Info!$B$1:$B$101,0),MATCH(HR_Data!AE$1,Emp_Info!$A$1:$G$1,0)) -> West | AF16: =IF(AND(P16>=3,M16>6),"Eligible","Not Eligible") -> Eligible
A17: EMP011 | B17: 30684 | C17: 40 | D17: 41988 | E17: Freelance | F17: D_001 | G17: Senior Developer | H17: Full-Time | I17: MGR101 | J17: 920000 | K17: 92000 | L17: =SUM(J17:K17) -> 1012000 | M17: 18 | N17: 4.4 | O17: 97.3 | P17: 4 | Q17: No | R17: Low | S17: 43819 | T17: Active | U17: =VLOOKUP(A17,Emp_Info!$B$1:$G$101,3,0) -> manoj | V17: =_xlfn.XLOOKUP(A17,Emp_Info!$B$2:$B$101,Emp_Info!$A$2:$A$101,,0) -> gupta | W17: =PROPER(_xlfn.CONCAT(U17," ",V17)) -> Manoj Gupta | X17: =UPPER(_xlfn.CONCAT(LEFT(U17),LEFT(V17),RIGHT(A17,3))) -> MG011 | Y17: =HLOOKUP(F17,Dept_Info!$A$2:$I$3,2,0) -> IT | Z17: =IF(Y17="Sales",L17+(L17*$AG$6),L17) -> 1012000 | AA17: =IF(J17<700000,"Low",IF(AND(J17>700000,J17<900000),"Medium","High")) -> High | AB17: Male | AC17: =INDEX(Emp_Info!$B$1:$G$101,MATCH(HR_Data!$A48,Emp_Info!$B$2:$B$101,0),MATCH(HR_Data!AC$1,Emp_Info!$B$1:$G$1,0)) -> Bachelor | AD17: =INDEX(Emp_Info!$A$1:$G$101,MATCH(HR_Data!$A17,Emp_Info!$B$1:$B$101,0),MATCH(HR_Data!AD$1,Emp_Info!$A$1:$G$1,0)) -> Noida | AE17: =INDEX(Emp_Info!$A$1:$G$101,MATCH(HR_Data!$A17,Emp_Info!$B$1:$B$101,0),MATCH(HR_Data!AE$1,Emp_Info!$A$1:$G$1,0)) -> North | AF17: =IF(AND(P17>=3,M17>6),"Eligible","Not Eligible") -> Eligible
A18: EMP059 | B18: 31479 | C18: 38 | D18: 42300 | E18: Job Portal | F18: D_005 | G18: Production Manager | H18: Full-Time | I18: MGR105 | J18: 920000 | K18: 92000 | L18: =SUM(J18:K18) -> 1012000 | M18: 17 | N18: 4.4 | O18: 97.9 | P18: 3 | Q18: No | R18: Low | S18: 44119 | T18: Active | U18: =VLOOKUP(A18,Emp_Info!$B$1:$G$101,3,0) -> alok | V18: =_xlfn.XLOOKUP(A18,Emp_Info!$B$2:$B$101,Emp_Info!$A$2:$A$101,,0) -> sinha | W18: =PROPER(_xlfn.CONCAT(U18," ",V18)) -> Alok Sinha | X18: =UPPER(_xlfn.CONCAT(LEFT(U18),LEFT(V18),RIGHT(A18,3))) -> AS059 | Y18: =HLOOKUP(F18,Dept_Info!$A$2:$I$3,2,0) -> Marketing | Z18: =IF(Y18="Sales",L18+(L18*$AG$6),L18) -> 1012000 | AA18: =IF(J18<700000,"Low",IF(AND(J18>700000,J18<900000),"Medium","High")) -> High | AB18: Male | AC18: =INDEX(Emp_Info!$B$1:$G$101,MATCH(HR_Data!$A71,Emp_Info!$B$2:$B$101,0),MATCH(HR_Data!AC$1,Emp_Info!$B$1:$G$1,0)) -> Master | AD18: =INDEX(Emp_Info!$A$1:$G$101,MATCH(HR_Data!$A18,Emp_Info!$B$1:$B$101,0),MATCH(HR_Data!AD$1,Emp_Info!$A$1:$G$1,0)) -> Chennai | AE18: =INDEX(Emp_Info!$A$1:$G$101,MATCH(HR_Data!$A18,Emp_Info!$B$1:$B$101,0),MATCH(HR_Data!AE$1,Emp_Info!$A$1:$G$1,0)) -> South | AF18: =IF(AND(P18>=3,M18>6),"Eligible","Not Eligible") -> Eligible
A19: EMP093 | B19: 32080 | C19: 37 | D19: 42531 | E19: Freelance | F19: D_006 | G19: Financial Planning Manager | H19: Full-Time | I19: MGR103 | J19: 920000 | K19: 92000 | L19: =SUM(J19:K19) -> 1012000 | M19: 15 | N19: 4.5 | O19: 98 | P19: 3 | Q19: Yes | R19: Low | S19: 44367 | T19: Active | U19: =VLOOKUP(A19,Emp_Info!$B$1:$G$101,3,0) -> dinesh | V19: =_xlfn.XLOOKUP(A19,Emp_Info!$B$2:$B$101,Emp_Info!$A$2:$A$101,,0) -> reddy | W19: =PROPER(_xlfn.CONCAT(U19," ",V19)) -> Dinesh Reddy | X19: =UPPER(_xlfn.CONCAT(LEFT(U19),LEFT(V19),RIGHT(A19,3))) -> DR093 | Y19: =HLOOKUP(F19,Dept_Info!$A$2:$I$3,2,0) -> Finance | Z19: =IF(Y19="Sales",L19+(L19*$AG$6),L19) -> 1012000 | AA19: =IF(J19<700000,"Low",IF(AND(J19>700000,J19<900000),"Medium","High")) -> High | AB19: Male | AC19: =INDEX(Emp_Info!$B$1:$G$101,MATCH(HR_Data!$A23,Emp_Info!$B$2:$B$101,0),MATCH(HR_Data!AC$1,Emp_Info!$B$1:$G$1,0)) -> Master | AD19: =INDEX(Emp_Info!$A$1:$G$101,MATCH(HR_Data!$A19,Emp_Info!$B$1:$B$101,0),MATCH(HR_Data!AD$1,Emp_Info!$A$1:$G$1,0)) -> Delhi | AE19: =INDEX(Emp_Info!$A$1:$G$101,MATCH(HR_Data!$A19,Emp_Info!$B$1:$B$101,0),MATCH(HR_Data!AE$1,Emp_Info!$A$1:$G$1,0)) -> North | AF19: =IF(AND(P19>=3,M19>6),"Eligible","Not Eligible") -> Eligible
A20: EMP096 | B20: 33579 | C20: 33 | D20: 43758 | E20: Freelance | F20: D_001 | G20: Technical Lead | H20: Full-Time | I20: MGR101 | J20: 920000 | K20: 92000 | L20: =SUM(J20:K20) -> 1012000 | M20: 9 | N20: 4.5 | O20: 98.1 | P20: 4 | Q20: Yes | R20: Low | S20: 45214 | T20: Active | U20: =VLOOKUP(A20,Emp_Info!$B$1:$G$101,3,0) -> anjana | V20: =_xlfn.XLOOKUP(A20,Emp_Info!$B$2:$B$101,Emp_Info!$A$2:$A$101,,0) -> nair | W20: =PROPER(_xlfn.CONCAT(U20," ",V20)) -> Anjana Nair | X20: =UPPER(_xlfn.CONCAT(LEFT(U20),LEFT(V20),RIGHT(A20,3))) -> AN096 | Y20: =HLOOKUP(F20,Dept_Info!$A$2:$I$3,2,0) -> IT | Z20: =IF(Y20="Sales",L20+(L20*$AG$6),L20) -> 1012000 | AA20: =IF(J20<700000,"Low",IF(AND(J20>700000,J20<900000),"Medium","High")) -> High | AB20: Female | AC20: =INDEX(Emp_Info!$B$1:$G$101,MATCH(HR_Data!$A56,Emp_Info!$B$2:$B$101,0),MATCH(HR_Data!AC$1,Emp_Info!$B$1:$G$1,0)) -> Master | AD20: =INDEX(Emp_Info!$A$1:$G$101,MATCH(HR_Data!$A20,Emp_Info!$B$1:$B$101,0),MATCH(HR_Data!AD$1,Emp_Info!$A$1:$G$1,0)) -> Noida | AE20: =INDEX(Emp_Info!$A$1:$G$101,MATCH(HR_Data!$A20,Emp_Info!$B$1:$B$101,0),MATCH(HR_Data!AE$1,Emp_Info!$A$1:$G$1,0)) -> North | AF20: =IF(AND(P20>=3,M20>6),"Eligible","Not Eligible") -> Eligible
A21: EMP082 | B21: 34530 | C21: 30 | D21: 44862 | E21: Job Portal | F21: D_001 | G21: Data Scientist | H21: Full-Time | I21: MGR101 | J21: 920000 | K21: 92000 | L21: =SUM(J21:K21) -> 1012000 | M21: 5 | N21: 4.5 | O21: 97.8 | P21: 3 | Q21: Yes | R21: Low | S21: NA | T21: Active | U21: =VLOOKUP(A21,Emp_Info!$B$1:$G$101,3,0) -> namita | V21: =_xlfn.XLOOKUP(A21,Emp_Info!$B$2:$B$101,Emp_Info!$A$2:$A$101,,0) -> rao | W21: =PROPER(_xlfn.CONCAT(U21," ",V21)) -> Namita Rao | X21: =UPPER(_xlfn.CONCAT(LEFT(U21),LEFT(V21),RIGHT(A21,3))) -> NR082 | Y21: =HLOOKUP(F21,Dept_Info!$A$2:$I$3,2,0) -> IT | Z21: =IF(Y21="Sales",L21+(L21*$AG$6),L21) -> 1012000 | AA21: =IF(J21<700000,"Low",IF(AND(J21>700000,J21<900000),"Medium","High")) -> High | AB21: Female | AC21: =INDEX(Emp_Info!$B$1:$G$101,MATCH(HR_Data!$A63,Emp_Info!$B$2:$B$101,0),MATCH(HR_Data!AC$1,Emp_Info!$B$1:$G$1,0)) -> Master | AD21: =INDEX(Emp_Info!$A$1:$G$101,MATCH(HR_Data!$A21,Emp_Info!$B$1:$B$101,0),MATCH(HR_Data!AD$1,Emp_Info!$A$1:$G$1,0)) -> Noida | AE21: =INDEX(Emp_Info!$A$1:$G$101,MATCH(HR_Data!$A21,Emp_Info!$B$1:$B$101,0),MATCH(HR_Data!AE$1,Emp_Info!$A$1:$G$1,0)) -> North | AF21: =IF(AND(P21>=3,M21>6),"Eligible","Not Eligible") -> Not Eligible
A22: EMP049 | B22: 32199 | C22: 36 | D22: 42622 | E22: Freelance | F22: D_003 | G22: Channel Sales Manager | H22: Full-Time | I22: MGR106 | J22: 890000 | K22: 105000 | L22: =SUM(J22:K22) -> 995000 | M22: 14 | N22: 4.4 | O22: 97.5 | P22: 3 | Q22: Yes | R22: Low | S22: 44459 | T22: Active | U22: =VLOOKUP(A22,Emp_Info!$B$1:$G$101,3,0) -> sunil | V22: =_xlfn.XLOOKUP(A22,Emp_Info!$B$2:$B$101,Emp_Info!$A$2:$A$101,,0) -> agarwal | W22: =PROPER(_xlfn.CONCAT(U22," ",V22)) -> Sunil Agarwal | X22: =UPPER(_xlfn.CONCAT(LEFT(U22),LEFT(V22),RIGHT(A22,3))) -> SA049 | Y22: =HLOOKUP(F22,Dept_Info!$A$2:$I$3,2,0) -> Sales | Z22: =IF(Y22="Sales",L22+(L22*$AG$6),L22) -> 1144250 | AA22: =IF(J22<700000,"Low",IF(AND(J22>700000,J22<900000),"Medium","High")) -> Medium | AB22: Male | AC22: =INDEX(Emp_Info!$B$1:$G$101,MATCH(HR_Data!$A90,Emp_Info!$B$2:$B$101,0),MATCH(HR_Data!AC$1,Emp_Info!$B$1:$G$1,0)) -> Bachelor | AD22: =INDEX(Emp_Info!$A$1:$G$101,MATCH(HR_Data!$A22,Emp_Info!$B$1:$B$101,0),MATCH(HR_Data!AD$1,Emp_Info!$A$1:$G$1,0)) -> Bangalore | AE22: =INDEX(Emp_Info!$A$1:$G$101,MATCH(HR_Data!$A22,Emp_Info!$B$1:$B$101,0),MATCH(HR_Data!AE$1,Emp_Info!$A$1:$G$1,0)) -> South | AF22: =IF(AND(P22>=3,M22>6),"Eligible","Not Eligible") -> Eligible
A23: EMP007 | B23: 32673 | C23: 35 | D23: 43434 | E23: Job Portal | F23: D_003 | G23: Sales Manager | H23: Full-Time | I23: MGR106 | J23: 880000 | K23: 110000 | L23: =SUM(J23:K23) -> 990000 | M23: 11 | N23: 4.3 | O23: 96.7 | P23: 1 | Q23: Yes | R23: Medium | S23: 44880 | T23: Active | U23: =VLOOKUP(A23,Emp_Info!$B$1:$G$101,3,0) -> rahul | V23: =_xlfn.XLOOKUP(A23,Emp_Info!$B$2:$B$101,Emp_Info!$A$2:$A$101,,0) -> mehta | W23: =PROPER(_xlfn.CONCAT(U23," ",V23)) -> Rahul Mehta | X23: =UPPER(_xlfn.CONCAT(LEFT(U23),LEFT(V23),RIGHT(A23,3))) -> RM007 | Y23: =HLOOKUP(F23,Dept_Info!$A$2:$I$3,2,0) -> Sales | Z23: =IF(Y23="Sales",L23+(L23*$AG$6),L23) -> 1138500 | AA23: =IF(J23<700000,"Low",IF(AND(J23>700000,J23<900000),"Medium","High")) -> Medium | AB23: Male | AC23: =INDEX(Emp_Info!$B$1:$G$101,MATCH(HR_Data!$A94,Emp_Info!$B$2:$B$101,0),MATCH(HR_Data!AC$1,Emp_Info!$B$1:$G$1,0)) -> Bachelor | AD23: =INDEX(Emp_Info!$A$1:$G$101,MATCH(HR_Data!$A23,Emp_Info!$B$1:$B$101,0),MATCH(HR_Data!AD$1,Emp_Info!$A$1:$G$1,0)) -> Delhi | AE23: =INDEX(Emp_Info!$A$1:$G$101,MATCH(HR_Data!$A23,Emp_Info!$B$1:$B$101,0),MATCH(HR_Data!AE$1,Emp_Info!$A$1:$G$1,0)) -> North | AF23: =IF(AND(P23>=3,M23>6),"Eligible","Not Eligible") -> Not Eligible
A24: EMP099 | B24: 32308 | C24: 36 | D24: 43048 | E24: Referral | F24: D_006 | G24: Mergers & Acquisitions Analyst | H24: Full-Time | I24: MGR103 | J24: 890000 | K24: 88000 | L24: =SUM(J24:K24) -> 978000 | M24: 13 | N24: 4.4 | O24: 97.6 | P24: 3 | Q24: Yes | R24: Low | S24: 44885 | T24: Active | U24: =VLOOKUP(A24,Emp_Info!$B$1:$G$101,3,0) -> vikas | V24: =_xlfn.XLOOKUP(A24,Emp_Info!$B$2:$B$101,Emp_Info!$A$2:$A$101,,0) -> sharma | W24: =PROPER(_xlfn.CONCAT(U24," ",V24)) -> Vikas Sharma | X24: =UPPER(_xlfn.CONCAT(LEFT(U24),LEFT(V24),RIGHT(A24,3))) -> VS099 | Y24: =HLOOKUP(F24,Dept_Info!$A$2:$I$3,2,0) -> Finance | Z24: =IF(Y24="Sales",L24+(L24*$AG$6),L24) -> 978000 | AA24: =IF(J24<700000,"Low",IF(AND(J24>700000,J24<900000),"Medium","High")) -> Medium | AB24: Male | AC24: =INDEX(Emp_Info!$B$1:$G$101,MATCH(HR_Data!$A27,Emp_Info!$B$2:$B$101,0),MATCH(HR_Data!AC$1,Emp_Info!$B$1:$G$1,0)) -> Master | AD24: =INDEX(Emp_Info!$A$1:$G$101,MATCH(HR_Data!$A24,Emp_Info!$B$1:$B$101,0),MATCH(HR_Data!AD$1,Emp_Info!$A$1:$G$1,0)) -> Pune | AE24: =INDEX(Emp_Info!$A$1:$G$101,MATCH(HR_Data!$A24,Emp_Info!$B$1:$B$101,0),MATCH(HR_Data!AE$1,Emp_Info!$A$1:$G$1,0)) -> West | AF24: =IF(AND(P24>=3,M24>6),"Eligible","Not Eligible") -> Eligible
A25: EMP029 | B25: 32485 | D25: 42903 | E25: LinkedIn | F25: D_005 | G25: Process Manager | H25: Full-Time | I25: MGR105 | J25: 890000 | K25: 88000 | L25: =SUM(J25:K25) -> 978000 | M25: 13 | N25: 4.3 | O25: 98 | P25: 3 | Q25: Yes | R25: Low | S25: 44732 | T25: Active | U25: =VLOOKUP(A25,Emp_Info!$B$1:$G$101,3,0) -> nitin | V25: =_xlfn.XLOOKUP(A25,Emp_Info!$B$2:$B$101,Emp_Info!$A$2:$A$101,,0) -> jain | W25: =PROPER(_xlfn.CONCAT(U25," ",V25)) -> Nitin Jain | X25: =UPPER(_xlfn.CONCAT(LEFT(U25),LEFT(V25),RIGHT(A25,3))) -> NJ029 | Y25: =HLOOKUP(F25,Dept_Info!$A$2:$I$3,2,0) -> Marketing | Z25: =IF(Y25="Sales",L25+(L25*$AG$6),L25) -> 978000 | AA25: =IF(J25<700000,"Low",IF(AND(J25>700000,J25<900000),"Medium","High")) -> Medium | AB25: Male | AC25: =INDEX(Emp_Info!$B$1:$G$101,MATCH(HR_Data!$A78,Emp_Info!$B$2:$B$101,0),MATCH(HR_Data!AC$1,Emp_Info!$B$1:$G$1,0)) -> Bachelor | AD25: =INDEX(Emp_Info!$A$1:$G$101,MATCH(HR_Data!$A25,Emp_Info!$B$1:$B$101,0),MATCH(HR_Data!AD$1,Emp_Info!$A$1:$G$1,0)) -> Pune | AE25: =INDEX(Emp_Info!$A$1:$G$101,MATCH(HR_Data!$A25,Emp_Info!$B$1:$B$101,0),MATCH(HR_Data!AE$1,Emp_Info!$A$1:$G$1,0)) -> West | AF25: =IF(AND(P25>=3,M25>6),"Eligible","Not Eligible") -> Eligible
A26: EMP091 | B26: 32514 | C26: 35 | D26: 43084 | E26: LinkedIn | F26: D_003 | G26: Direct Sales Manager | H26: Full-Time | I26: MGR106 | J26: 870000 | K26: 98000 | L26: =SUM(J26:K26) -> 968000 | M26: 12 | N26: 4.4 | O26: 97.4 | P26: 2 | Q26: Yes | R26: Low | S26: 44915 | T26: Active | U26: =VLOOKUP(A26,Emp_Info!$B$1:$G$101,3,0) -> sameer | V26: =_xlfn.XLOOKUP(A26,Emp_Info!$B$2:$B$101,Emp_Info!$A$2:$A$101,,0) -> bansal | W26: =PROPER(_xlfn.CONCAT(U26," ",V26)) -> Sameer Bansal | X26: =UPPER(_xlfn.CONCAT(LEFT(U26),LEFT(V26),RIGHT(A26,3))) -> SB091 | Y26: =HLOOKUP(F26,Dept_Info!$A$2:$I$3,2,0) -> Sales | Z26: =IF(Y26="Sales",L26+(L26*$AG$6),L26) -> 1113200 | AA26: =IF(J26<700000,"Low",IF(AND(J26>700000,J26<900000),"Medium","High")) -> Medium | AB26: Male | AC26: =INDEX(Emp_Info!$B$1:$G$101,MATCH(HR_Data!$A93,Emp_Info!$B$2:$B$101,0),MATCH(HR_Data!AC$1,Emp_Info!$B$1:$G$1,0)) -> Master | AD26: =INDEX(Emp_Info!$A$1:$G$101,MATCH(HR_Data!$A26,Emp_Info!$B$1:$B$101,0),MATCH(HR_Data!AD$1,Emp_Info!$A$1:$G$1,0)) -> Pune | AE26: =INDEX(Emp_Info!$A$1:$G$101,MATCH(HR_Data!$A26,Emp_Info!$B$1:$B$101,0),MATCH(HR_Data!AE$1,Emp_Info!$A$1:$G$1,0)) -> West | AF26: =IF(AND(P26>=3,M26>6),"Eligible","Not Eligible") -> Not Eligible
A27: EMP037 | B27: 31471 | C27: 38 | D27: 42342 | E27: Job Portal | F27: D_001 | G27: DevOps Engineer | H27: Full-Time | I27: MGR101 | J27: 880000 | K27: 85000 | L27: =SUM(J27:K27) -> 965000 | M27: 16 | N27: 4.4 | O27: 97.4 | P27: 4 | Q27: No | R27: Low | S27: 44180 | T27: Active | U27: =VLOOKUP(A27,Emp_Info!$B$1:$G$101,3,0) -> ajay | V27: =_xlfn.XLOOKUP(A27,Emp_Info!$B$2:$B$101,Emp_Info!$A$2:$A$101,,0) -> sharma | W27: =PROPER(_xlfn.CONCAT(U27," ",V27)) -> Ajay Sharma | X27: =UPPER(_xlfn.CONCAT(LEFT(U27),LEFT(V27),RIGHT(A27,3))) -> AS037 | Y27: =HLOOKUP(F27,Dept_Info!$A$2:$I$3,2,0) -> IT | Z27: =IF(Y27="Sales",L27+(L27*$AG$6),L27) -> 965000 | AA27: =IF(J27<700000,"Low",IF(AND(J27>700000,J27<900000),"Medium","High")) -> Medium | AB27: Male | AC27: =INDEX(Emp_Info!$B$1:$G$101,MATCH(HR_Data!$A50,Emp_Info!$B$2:$B$101,0),MATCH(HR_Data!AC$1,Emp_Info!$B$1:$G$1,0)) -> Bachelor | AD27: =INDEX(Emp_Info!$A$1:$G$101,MATCH(HR_Data!$A27,Emp_Info!$B$1:$B$101,0),MATCH(HR_Data!AD$1,Emp_Info!$A$1:$G$1,0)) -> Bangalore | AE27: =INDEX(Emp_Info!$A$1:$G$101,MATCH(HR_Data!$A27,Emp_Info!$B$1:$B$101,0),MATCH(HR_Data!AE$1,Emp_Info!$A$1:$G$1,0)) -> South | AF27: =IF(AND(P27>=3,M27>6),"Eligible","Not Eligible") -> Eligible
A28: EMP086 | B28: 33453 | C28: 33 | D28: 43795 | E28: Job Portal | F28: D_001 | G28: Product Owner | H28: Full-Time | I28: MGR101 | J28: 880000 | K28: 85000 | L28: =SUM(J28:K28) -> 965000 | M28: 9 | N28: 4.4 | O28: 97.6 | P28: 3 | Q28: Yes | R28: Low | S28: NA | T28: Active | U28: =VLOOKUP(A28,Emp_Info!$B$1:$G$101,3,0) -> preeti | V28: =_xlfn.XLOOKUP(A28,Emp_Info!$B$2:$B$101,Emp_Info!$A$2:$A$101,,0) -> menon | W28: =PROPER(_xlfn.CONCAT(U28," ",V28)) -> Preeti Menon | X28: =UPPER(_xlfn.CONCAT(LEFT(U28),LEFT(V28),RIGHT(A28,3))) -> PM086 | Y28: =HLOOKUP(F28,Dept_Info!$A$2:$I$3,2,0) -> IT | Z28: =IF(Y28="Sales",L28+(L28*$AG$6),L28) -> 965000 | AA28: =IF(J28<700000,"Low",IF(AND(J28>700000,J28<900000),"Medium","High")) -> Medium | AB28: Female | AC28: =INDEX(Emp_Info!$B$1:$G$101,MATCH(HR_Data!$A59,Emp_Info!$B$2:$B$101,0),MATCH(HR_Data!AC$1,Emp_Info!$B$1:$G$1,0)) -> Bachelor | AD28: =INDEX(Emp_Info!$A$1:$G$101,MATCH(HR_Data!$A28,Emp_Info!$B$1:$B$101,0),MATCH(HR_Data!AD$1,Emp_Info!$A$1:$G$1,0)) -> Bangalore | AE28: =INDEX(Emp_Info!$A$1:$G$101,MATCH(HR_Data!$A28,Emp_Info!$B$1:$B$101,0),MATCH(HR_Data!AE$1,Emp_Info!$A$1:$G$1,0)) -> South | AF28: =IF(AND(P28>=3,M28>6),"Eligible","Not Eligible") -> Eligible
A29: EMP031 | B29: 31837 | C29: 37 | D29: 42680 | E29: Job Portal | F29: D_003 | G29: Key Account Manager | H29: Full-Time | I29: MGR106 | J29: 860000 | K29: 98000 | L29: =SUM(J29:K29) -> 958000 | M29: 14 | N29: 4.4 | O29: 96.9 | P29: 2 | Q29: Yes | R29: Low | S29: 44515 | T29: Active | U29: =VLOOKUP(A29,Emp_Info!$B$1:$G$101,3,0) -> ravi | V29: =_xlfn.XLOOKUP(A29,Emp_Info!$B$2:$B$101,Emp_Info!$A$2:$A$101,,0) -> shetty | W29: =PROPER(_xlfn.CONCAT(U29," ",V29)) -> Ravi Shetty | X29: =UPPER(_xlfn.CONCAT(LEFT(U29),LEFT(V29),RIGHT(A29,3))) -> RS031 | Y29: =HLOOKUP(F29,Dept_Info!$A$2:$I$3,2,0) -> Sales | Z29: =IF(Y29="Sales",L29+(L29*$AG$6),L29) -> 1101700 | AA29: =IF(J29<700000,"Low",IF(AND(J29>700000,J29<900000),"Medium","High")) -> Medium | AB29: Male | AC29: =INDEX(Emp_Info!$B$1:$G$101,MATCH(HR_Data!$A89,Emp_Info!$B$2:$B$101,0),MATCH(HR_Data!AC$1,Emp_Info!$B$1:$G$1,0)) -> Bachelor | AD29: =INDEX(Emp_Info!$A$1:$G$101,MATCH(HR_Data!$A29,Emp_Info!$B$1:$B$101,0),MATCH(HR_Data!AD$1,Emp_Info!$A$1:$G$1,0)) -> Bangalore | AE29: =INDEX(Emp_Info!$A$1:$G$101,MATCH(HR_Data!$A29,Emp_Info!$B$1:$B$101,0),MATCH(HR_Data!AE$1,Emp_Info!$A$1:$G$1,0)) -> South | AF29: =IF(AND(P29>=3,M29>6),"Eligible","Not Eligible") -> Not Eligible
A30: EMP017 | B30: 31871 | C30: 37 | D30: 42655 | E30: Referral | F30: D_005 | G30: Logistics Manager | H30: Full-Time | I30: MGR105 | J30: 870000 | K30: 85000 | L30: =SUM(J30:K30) -> 955000 | M30: 14 | N30: 4.3 | O30: 98.1 | P30: 3 | Q30: Yes | R30: Low | S30: 44489 | T30: Active | U30: =VLOOKUP(A30,Emp_Info!$B$1:$G$101,3,0) -> sanjay | V30: =_xlfn.XLOOKUP(A30,Emp_Info!$B$2:$B$101,Emp_Info!$A$2:$A$101,,0) -> pillai | W30: =PROPER(_xlfn.CONCAT(U30," ",V30)) -> Sanjay Pillai | X30: =UPPER(_xlfn.CONCAT(LEFT(U30),LEFT(V30),RIGHT(A30,3))) -> SP017 | Y30: =HLOOKUP(F30,Dept_Info!$A$2:$I$3,2,0) -> Marketing | Z30: =IF(Y30="Sales",L30+(L30*$AG$6),L30) -> 955000 | AA30: =IF(J30<700000,"Low",IF(AND(J30>700000,J30<900000),"Medium","High")) -> Medium | AB30: Male | AC30: =INDEX(Emp_Info!$B$1:$G$101,MATCH(HR_Data!$A77,Emp_Info!$B$2:$B$101,0),MATCH(HR_Data!AC$1,Emp_Info!$B$1:$G$1,0)) -> Bachelor | AD30: =INDEX(Emp_Info!$A$1:$G$101,MATCH(HR_Data!$A30,Emp_Info!$B$1:$B$101,0),MATCH(HR_Data!AD$1,Emp_Info!$A$1:$G$1,0)) -> Chennai | AE30: =INDEX(Emp_Info!$A$1:$G$101,MATCH(HR_Data!$A30,Emp_Info!$B$1:$B$101,0),MATCH(HR_Data!AE$1,Emp_Info!$A$1:$G$1,0)) -> South | AF30: =IF(AND(P30>=3,M30>6),"Eligible","Not Eligible") -> Eligible
A31: EMP081 | B31: 31718 | C31: 38 | D31: 42515 | E31: LinkedIn | F31: D_006 | G31: Compliance Officer | H31: Full-Time | I31: MGR103 | J31: 860000 | K31: 82000 | L31: =SUM(J31:K31) -> 942000 | M31: 16 | N31: 4.3 | O31: 97.1 | P31: 3 | Q31: No | R31: Low | S31: 44326 | T31: Active | U31: =VLOOKUP(A31,Emp_Info!$B$1:$G$101,3,0) -> sachin | V31: =_xlfn.XLOOKUP(A31,Emp_Info!$B$2:$B$101,Emp_Info!$A$2:$A$101,,0) -> desai | W31: =PROPER(_xlfn.CONCAT(U31," ",V31)) -> Sachin Desai | X31: =UPPER(_xlfn.CONCAT(LEFT(U31),LEFT(V31),RIGHT(A31,3))) -> SD081 | Y31: =HLOOKUP(F31,Dept_Info!$A$2:$I$3,2,0) -> Finance | Z31: =IF(Y31="Sales",L31+(L31*$AG$6),L31) -> 942000 | AA31: =IF(J31<700000,"Low",IF(AND(J31>700000,J31<900000),"Medium","High")) -> Medium | AB31: Male | AC31: =INDEX(Emp_Info!$B$1:$G$101,MATCH(HR_Data!$A22,Emp_Info!$B$2:$B$101,0),MATCH(HR_Data!AC$1,Emp_Info!$B$1:$G$1,0)) -> Bachelor | AD31: =INDEX(Emp_Info!$A$1:$G$101,MATCH(HR_Data!$A31,Emp_Info!$B$1:$B$101,0),MATCH(HR_Data!AD$1,Emp_Info!$A$1:$G$1,0)) -> Mumbai | AE31: =INDEX(Emp_Info!$A$1:$G$101,MATCH(HR_Data!$A31,Emp_Info!$B$1:$B$101,0),MATCH(HR_Data!AE$1,Emp_Info!$A$1:$G$1,0)) -> West | AF31: =IF(AND(P31>=3,M31>6),"Eligible","Not Eligible") -> Eligible
A32: EMP001 | B32: 31121 | C32: 39 | D32: 43191 | E32: Job Portal | F32: D_001 | G32: Software Engineer | H32: Full-Time | I32: MGR101 | J32: 850000 | K32: 85000 | L32: =SUM(J32:K32) -> 935000 | M32: 12 | N32: 4.2 | O32: 96.5 | P32: 3 | Q32: Yes | R32: Low | S32: 44666 | T32: Active | U32: =VLOOKUP(A32,Emp_Info!$B$1:$G$101,3,0) -> rajesh | V32: =_xlfn.XLOOKUP(A32,Emp_Info!$B$2:$B$101,Emp_Info!$A$2:$A$101,,0) -> kumar | W32: =PROPER(_xlfn.CONCAT(U32," ",V32)) -> Rajesh Kumar | X32: =UPPER(_xlfn.CONCAT(LEFT(U32),LEFT(V32),RIGHT(A32,3))) -> RK001 | Y32: =HLOOKUP(F32,Dept_Info!$A$2:$I$3,2,0) -> IT | Z32: =IF(Y32="Sales",L32+(L32*$AG$6),L32) -> 935000 | AA32: =IF(J32<700000,"Low",IF(AND(J32>700000,J32<900000),"Medium","High")) -> Medium | AB32: Male | AC32: =INDEX(Emp_Info!$B$1:$G$101,MATCH(HR_Data!$A54,Emp_Info!$B$2:$B$101,0),MATCH(HR_Data!AC$1,Emp_Info!$B$1:$G$1,0)) -> Bachelor | AD32: =INDEX(Emp_Info!$A$1:$G$101,MATCH(HR_Data!$A32,Emp_Info!$B$1:$B$101,0),MATCH(HR_Data!AD$1,Emp_Info!$A$1:$G$1,0)) -> Mumbai | AE32: =INDEX(Emp_Info!$A$1:$G$101,MATCH(HR_Data!$A32,Emp_Info!$B$1:$B$101,0),MATCH(HR_Data!AE$1,Emp_Info!$A$1:$G$1,0)) -> West | AF32: =IF(AND(P32>=3,M32>6),"Eligible","Not Eligible") -> Eligible
A33: EMP089 | B33: 31727 | C33: 38 | D33: 42464 | E33: Job Portal | F33: D_005 | G33: Distribution Manager | H33: Full-Time | I33: MGR105 | J33: 850000 | K33: 82000 | L33: =SUM(J33:K33) -> 932000 | M33: 16 | N33: 4.3 | O33: 97.7 | P33: 3 | Q33: No | R33: Low | S33: 44301 | T33: Active | U33: =VLOOKUP(A33,Emp_Info!$B$1:$G$101,3,0) -> akash | V33: =_xlfn.XLOOKUP(A33,Emp_Info!$B$2:$B$101,Emp_Info!$A$2:$A$101,,0) -> yadav | W33: =PROPER(_xlfn.CONCAT(U33," ",V33)) -> Akash Yadav | X33: =UPPER(_xlfn.CONCAT(LEFT(U33),LEFT(V33),RIGHT(A33,3))) -> AY089 | Y33: =HLOOKUP(F33,Dept_Info!$A$2:$I$3,2,0) -> Marketing | Z33: =IF(Y33="Sales",L33+(L33*$AG$6),L33) -> 932000 | AA33: =IF(J33<700000,"Low",IF(AND(J33>700000,J33<900000),"Medium","High")) -> Medium | AB33: Male | AC33: =INDEX(Emp_Info!$B$1:$G$101,MATCH(HR_Data!$A72,Emp_Info!$B$2:$B$101,0),MATCH(HR_Data!AC$1,Emp_Info!$B$1:$G$1,0)) -> Bachelor | AD33: =INDEX(Emp_Info!$A$1:$G$101,MATCH(HR_Data!$A33,Emp_Info!$B$1:$B$101,0),MATCH(HR_Data!AD$1,Emp_Info!$A$1:$G$1,0)) -> Noida | AE33: =INDEX(Emp_Info!$A$1:$G$101,MATCH(HR_Data!$A33,Emp_Info!$B$1:$B$101,0),MATCH(HR_Data!AE$1,Emp_Info!$A$1:$G$1,0)) -> North | AF33: =IF(AND(P33>=3,M33>6),"Eligible","Not Eligible") -> Eligible
A34: EMP035 | B34: 32706 | C34: 35 | D34: 43233 | E34: LinkedIn | F34: D_005 | G34: Quality Manager | H34: Full-Time | I34: MGR105 | J34: 850000 | K34: 82000 | L34: =SUM(J34:K34) -> 932000 | M34: 12 | N34: 4.3 | O34: 97.6 | P34: 3 | Q34: Yes | R34: Low | S34: 45066 | T34: Active | U34: =VLOOKUP(A34,Emp_Info!$B$1:$G$101,3,0) -> manish | V34: =_xlfn.XLOOKUP(A34,Emp_Info!$B$2:$B$101,Emp_Info!$A$2:$A$101,,0) -> goyal | W34: =PROPER(_xlfn.CONCAT(U34," ",V34)) -> Manish Goyal | X34: =UPPER(_xlfn.CONCAT(LEFT(U34),LEFT(V34),RIGHT(A34,3))) -> MG035 | Y34: =HLOOKUP(F34,Dept_Info!$A$2:$I$3,2,0) -> Marketing | Z34: =IF(Y34="Sales",L34+(L34*$AG$6),L34) -> 932000 | AA34: =IF(J34<700000,"Low",IF(AND(J34>700000,J34<900000),"Medium","High")) -> Medium | AB34: Male | AC34: =INDEX(Emp_Info!$B$1:$G$101,MATCH(HR_Data!$A79,Emp_Info!$B$2:$B$101,0),MATCH(HR_Data!AC$1,Emp_Info!$B$1:$G$1,0)) -> Bachelor | AD34: =INDEX(Emp_Info!$A$1:$G$101,MATCH(HR_Data!$A34,Emp_Info!$B$1:$B$101,0),MATCH(HR_Data!AD$1,Emp_Info!$A$1:$G$1,0)) -> Chennai | AE34: =INDEX(Emp_Info!$A$1:$G$101,MATCH(HR_Data!$A34,Emp_Info!$B$1:$B$101,0),MATCH(HR_Data!AE$1,Emp_Info!$A$1:$G$1,0)) -> South | AF34: =IF(AND(P34>=3,M34>6),"Eligible","Not Eligible") -> Eligible
A35: EMP095 | B35: 33110 | C35: 34 | D35: 43538 | E35: Job Portal | F35: D_004 | G35: Growth Marketing Manager | H35: Full-Time | I35: MGR104 | J35: 850000 | K35: 82000 | L35: =SUM(J35:K35) -> 932000 | M35: 10 | N35: 4.4 | O35: 97.8 | P35: 3 | Q35: Yes | R35: Low | S35: NA | T35: Active | U35: =VLOOKUP(A35,Emp_Info!$B$1:$G$101,3,0) -> puneet | V35: =_xlfn.XLOOKUP(A35,Emp_Info!$B$2:$B$101,Emp_Info!$A$2:$A$101,,0) -> mehta | W35: =PROPER(_xlfn.CONCAT(U35," ",V35)) -> Puneet Mehta | X35: =UPPER(_xlfn.CONCAT(LEFT(U35),LEFT(V35),RIGHT(A35,3))) -> PM095 | Y35: =HLOOKUP(F35,Dept_Info!$A$2:$I$3,2,0) -> Admin | Z35: =IF(Y35="Sales",L35+(L35*$AG$6),L35) -> 932000 | AA35: =IF(J35<700000,"Low",IF(AND(J35>700000,J35<900000),"Medium","High")) -> Medium | AB35: Male | AC35: =INDEX(Emp_Info!$B$1:$G$101,MATCH(HR_Data!$A2,Emp_Info!$B$2:$B$101,0),MATCH(HR_Data!AC$1,Emp_Info!$B$1:$G$1,0)) -> Bachelor | AD35: =INDEX(Emp_Info!$A$1:$G$101,MATCH(HR_Data!$A35,Emp_Info!$B$1:$B$101,0),MATCH(HR_Data!AD$1,Emp_Info!$A$1:$G$1,0)) -> Hyderabad | AE35: =INDEX(Emp_Info!$A$1:$G$101,MATCH(HR_Data!$A35,Emp_Info!$B$1:$B$101,0),MATCH(HR_Data!AE$1,Emp_Info!$A$1:$G$1,0)) -> South | AF35: =IF(AND(P35>=3,M35>6),"Eligible","Not Eligible") -> Eligible
A36: EMP052 | B36: 33479 | C36: 33 | D36: 43636 | E36: Job Portal | F36: D_002 | G36: Talent Acquisition Manager | H36: Full-Time | I36: MGR102 | J36: 850000 | K36: 82000 | L36: =SUM(J36:K36) -> 932000 | M36: 9 | N36: 4.4 | O36: 97.8 | P36: 2 | Q36: Yes | R36: Low | S36: 45092 | T36: Active | U36: =VLOOKUP(A36,Emp_Info!$B$1:$G$101,3,0) -> aditi | V36: =_xlfn.XLOOKUP(A36,Emp_Info!$B$2:$B$101,Emp_Info!$A$2:$A$101,,0) -> malhotra | W36: =PROPER(_xlfn.CONCAT(U36," ",V36)) -> Aditi Malhotra | X36: =UPPER(_xlfn.CONCAT(LEFT(U36),LEFT(V36),RIGHT(A36,3))) -> AM052 | Y36: =HLOOKUP(F36,Dept_Info!$A$2:$I$3,2,0) -> HR | Z36: =IF(Y36="Sales",L36+(L36*$AG$6),L36) -> 932000 | AA36: =IF(J36<700000,"Low",IF(AND(J36>700000,J36<900000),"Medium","High")) -> Medium | AB36: Female | AC36: =INDEX(Emp_Info!$B$1:$G$101,MATCH(HR_Data!$A37,Emp_Info!$B$2:$B$101,0),MATCH(HR_Data!AC$1,Emp_Info!$B$1:$G$1,0)) -> Bachelor | AD36: =INDEX(Emp_Info!$A$1:$G$101,MATCH(HR_Data!$A36,Emp_Info!$B$1:$B$101,0),MATCH(HR_Data!AD$1,Emp_Info!$A$1:$G$1,0)) -> Mumbai | AE36: =INDEX(Emp_Info!$A$1:$G$101,MATCH(HR_Data!$A36,Emp_Info!$B$1:$B$101,0),MATCH(HR_Data!AE$1,Emp_Info!$A$1:$G$1,0)) -> West | AF36: =IF(AND(P36>=3,M36>6),"Eligible","Not Eligible") -> Not Eligible
A37: EMP068 | B37: 33441 | C37: 33 | D37: 43756 | E37: Job Portal | F37: D_001 | G37: Scrum Master | H37: Full-Time | I37: MGR101 | J37: 850000 | K37: 82000 | L37: =SUM(J37:K37) -> 932000 | M37: 9 | N37: 4.4 | O37: 97.7 | P37: 3 | Q37: Yes | R37: Low | S37: NA | T37: Active | U37: =VLOOKUP(A37,Emp_Info!$B$1:$G$101,3,0) -> rashmi | V37: =_xlfn.XLOOKUP(A37,Emp_Info!$B$2:$B$101,Emp_Info!$A$2:$A$101,,0) -> kapoor | W37: =PROPER(_xlfn.CONCAT(U37," ",V37)) -> Rashmi Kapoor | X37: =UPPER(_xlfn.CONCAT(LEFT(U37),LEFT(V37),RIGHT(A37,3))) -> RK068 | Y37: =HLOOKUP(F37,Dept_Info!$A$2:$I$3,2,0) -> IT | Z37: =IF(Y37="Sales",L37+(L37*$AG$6),L37) -> 932000 | AA37: =IF(J37<700000,"Low",IF(AND(J37>700000,J37<900000),"Medium","High")) -> Medium | AB37: Female | AC37: =INDEX(Emp_Info!$B$1:$G$101,MATCH(HR_Data!$A58,Emp_Info!$B$2:$B$101,0),MATCH(HR_Data!AC$1,Emp_Info!$B$1:$G$1,0)) -> Bachelor | AD37: =INDEX(Emp_Info!$A$1:$G$101,MATCH(HR_Data!$A37,Emp_Info!$B$1:$B$101,0),MATCH(HR_Data!AD$1,Emp_Info!$A$1:$G$1,0)) -> Bangalore | AE37: =INDEX(Emp_Info!$A$1:$G$101,MATCH(HR_Data!$A37,Emp_Info!$B$1:$B$101,0),MATCH(HR_Data!AE$1,Emp_Info!$A$1:$G$1,0)) -> South | AF37: =IF(AND(P37>=3,M37>6),"Eligible","Not Eligible") -> Eligible
A38: EMP085 | B38: 33045 | C38: 34 | D38: 43476 | E38: Job Portal | F38: D_003 | G38: Partner Manager | H38: Full-Time | I38: MGR106 | J38: 840000 | K38: 88000 | L38: =SUM(J38:K38) -> 928000 | M38: 10 | N38: 4.3 | O38: 97 | P38: 2 | Q38: Yes | R38: Low | S38: 44946 | T38: Active | U38: =VLOOKUP(A38,Emp_Info!$B$1:$G$101,3,0) -> anuj | V38: =_xlfn.XLOOKUP(A38,Emp_Info!$B$2:$B$101,Emp_Info!$A$2:$A$101,,0) -> sinha | W38: =PROPER(_xlfn.CONCAT(U38," ",V38)) -> Anuj Sinha | X38: =UPPER(_xlfn.CONCAT(LEFT(U38),LEFT(V38),RIGHT(A38,3))) -> AS085 | Y38: =HLOOKUP(F38,Dept_Info!$A$2:$I$3,2,0) -> Sales | Z38: =IF(Y38="Sales",L38+(L38*$AG$6),L38) -> 1067200 | AA38: =IF(J38<700000,"Low",IF(AND(J38>700000,J38<900000),"Medium","High")) -> Medium | AB38: Male | AC38: =INDEX(Emp_Info!$B$1:$G$101,MATCH(HR_Data!$A98,Emp_Info!$B$2:$B$101,0),MATCH(HR_Data!AC$1,Emp_Info!$B$1:$G$1,0)) -> Bachelor | AD38: =INDEX(Emp_Info!$A$1:$G$101,MATCH(HR_Data!$A38,Emp_Info!$B$1:$B$101,0),MATCH(HR_Data!AD$1,Emp_Info!$A$1:$G$1,0)) -> Delhi | AE38: =INDEX(Emp_Info!$A$1:$G$101,MATCH(HR_Data!$A38,Emp_Info!$B$1:$B$101,0),MATCH(HR_Data!AE$1,Emp_Info!$A$1:$G$1,0)) -> North | AF38: =IF(AND(P38>=3,M38>6),"Eligible","Not Eligible") -> Not Eligible
A39: EMP043 | B39: 31796 | C39: 37 | D39: 42408 | E39: LinkedIn | F39: D_003 | G39: Territory Manager | H39: Full-Time | I39: MGR106 | J39: 830000 | K39: 92000 | L39: =SUM(J39:K39) -> 922000 | M39: 15 | N39: 4.3 | O39: 97.1 | P39: 2 | Q39: Yes | R39: Low | S39: 44242 | T39: Active | U39: =VLOOKUP(A39,Emp_Info!$B$1:$G$101,3,0) -> harish | V39: =_xlfn.XLOOKUP(A39,Emp_Info!$B$2:$B$101,Emp_Info!$A$2:$A$101,,0) -> menon | W39: =PROPER(_xlfn.CONCAT(U39," ",V39)) -> Harish Menon | X39: =UPPER(_xlfn.CONCAT(LEFT(U39),LEFT(V39),RIGHT(A39,3))) -> HM043 | Y39: =HLOOKUP(F39,Dept_Info!$A$2:$I$3,2,0) -> Sales | Z39: =IF(Y39="Sales",L39+(L39*$AG$6),L39) -> 1060300 | AA39: =IF(J39<700000,"Low",IF(AND(J39>700000,J39<900000),"Medium","High")) -> Medium | AB39: Male | AC39: =INDEX(Emp_Info!$B$1:$G$101,MATCH(HR_Data!$A88,Emp_Info!$B$2:$B$101,0),MATCH(HR_Data!AC$1,Emp_Info!$B$1:$G$1,0)) -> Master | AD39: =INDEX(Emp_Info!$A$1:$G$101,MATCH(HR_Data!$A39,Emp_Info!$B$1:$B$101,0),MATCH(HR_Data!AD$1,Emp_Info!$A$1:$G$1,0)) -> Chennai | AE39: =INDEX(Emp_Info!$A$1:$G$101,MATCH(HR_Data!$A39,Emp_Info!$B$1:$B$101,0),MATCH(HR_Data!AE$1,Emp_Info!$A$1:$G$1,0)) -> South | AF39: =IF(AND(P39>=3,M39>6),"Eligible","Not Eligible") -> Not Eligible
A40: EMP013 | B40: 33204 | C40: 34 | D40: 43306 | E40: Job Portal | F40: D_003 | G40: Business Development Manager | H40: Full-Time | I40: MGR106 | J40: 810000 | K40: 95000 | L40: =SUM(J40:K40) -> 905000 | M40: 10 | N40: 4.2 | O40: 95.5 | P40: 2 | Q40: Yes | R40: Medium | S40: NA | T40: Active | U40: =VLOOKUP(A40,Emp_Info!$B$1:$G$101,3,0) -> arjun | V40: =_xlfn.XLOOKUP(A40,Emp_Info!$B$2:$B$101,Emp_Info!$A$2:$A$101,,0) -> rao | W40: =PROPER(_xlfn.CONCAT(U40," ",V40)) -> Arjun Rao | X40: =UPPER(_xlfn.CONCAT(LEFT(U40),LEFT(V40),RIGHT(A40,3))) -> AR013 | Y40: =HLOOKUP(F40,Dept_Info!$A$2:$I$3,2,0) -> Sales | Z40: =IF(Y40="Sales",L40+(L40*$AG$6),L40) -> 1040750 | AA40: =IF(J40<700000,"Low",IF(AND(J40>700000,J40<900000),"Medium","High")) -> Medium | AB40: Male | AC40: =INDEX(Emp_Info!$B$1:$G$101,MATCH(HR_Data!$A96,Emp_Info!$B$2:$B$101,0),MATCH(HR_Data!AC$1,Emp_Info!$B$1:$G$1,0)) -> Bachelor | AD40: =INDEX(Emp_Info!$A$1:$G$101,MATCH(HR_Data!$A40,Emp_Info!$B$1:$B$101,0),MATCH(HR_Data!AD$1,Emp_Info!$A$1:$G$1,0)) -> Hyderabad | AE40: =INDEX(Emp_Info!$A$1:$G$101,MATCH(HR_Data!$A40,Emp_Info!$B$1:$B$101,0),MATCH(HR_Data!AE$1,Emp_Info!$A$1:$G$1,0)) -> South | AF40: =IF(AND(P40>=3,M40>6),"Eligible","Not Eligible") -> Not Eligible
A41: EMP033 | B41: 31343 | C41: 39 | D41: 42277 | E41: Referral | F41: D_006 | G41: Senior Accountant | H41: Full-Time | I41: MGR103 | J41: 820000 | K41: 78000 | L41: =SUM(J41:K41) -> 898000 | M41: 17 | N41: 4.1 | O41: 96.1 | P41: 2 | Q41: No | R41: Low | S41: 44084 | T41: Active | U41: =VLOOKUP(A41,Emp_Info!$B$1:$G$101,3,0) -> prakash | V41: =_xlfn.XLOOKUP(A41,Emp_Info!$B$2:$B$101,Emp_Info!$A$2:$A$101,,0) -> reddy | W41: =PROPER(_xlfn.CONCAT(U41," ",V41)) -> Prakash Reddy | X41: =UPPER(_xlfn.CONCAT(LEFT(U41),LEFT(V41),RIGHT(A41,3))) -> PR033 | Y41: =HLOOKUP(F41,Dept_Info!$A$2:$I$3,2,0) -> Finance | Z41: =IF(Y41="Sales",L41+(L41*$AG$6),L41) -> 898000 | AA41: =IF(J41<700000,"Low",IF(AND(J41>700000,J41<900000),"Medium","High")) -> Medium | AB41: Male | AC41: =INDEX(Emp_Info!$B$1:$G$101,MATCH(HR_Data!$A19,Emp_Info!$B$2:$B$101,0),MATCH(HR_Data!AC$1,Emp_Info!$B$1:$G$1,0)) -> Master | AD41: =INDEX(Emp_Info!$A$1:$G$101,MATCH(HR_Data!$A41,Emp_Info!$B$1:$B$101,0),MATCH(HR_Data!AD$1,Emp_Info!$A$1:$G$1,0)) -> Hyderabad | AE41: =INDEX(Emp_Info!$A$1:$G$101,MATCH(HR_Data!$A41,Emp_Info!$B$1:$B$101,0),MATCH(HR_Data!AE$1,Emp_Info!$A$1:$G$1,0)) -> South | AF41: =IF(AND(P41>=3,M41>6),"Eligible","Not Eligible") -> Not Eligible
A42: EMP055 | B42: 31964 | C42: 37 | D42: 42686 | E42: Referral | F42: D_001 | G42: Database Administrator | H42: Full-Time | I42: MGR101 | J42: 820000 | K42: 78000 | L42: =SUM(J42:K42) -> 898000 | M42: 15 | N42: 4.2 | O42: 96.8 | P42: 3 | Q42: Yes | R42: Low | S42: 44525 | T42: Active | U42: =VLOOKUP(A42,Emp_Info!$B$1:$G$101,3,0) -> karthik | V42: =_xlfn.XLOOKUP(A42,Emp_Info!$B$2:$B$101,Emp_Info!$A$2:$A$101,,0) -> reddy | W42: =PROPER(_xlfn.CONCAT(U42," ",V42)) -> Karthik Reddy | X42: =UPPER(_xlfn.CONCAT(LEFT(U42),LEFT(V42),RIGHT(A42,3))) -> KR055 | Y42: =HLOOKUP(F42,Dept_Info!$A$2:$I$3,2,0) -> IT | Z42: =IF(Y42="Sales",L42+(L42*$AG$6),L42) -> 898000 | AA42: =IF(J42<700000,"Low",IF(AND(J42>700000,J42<900000),"Medium","High")) -> Medium | AB42: Male | AC42: =INDEX(Emp_Info!$B$1:$G$101,MATCH(HR_Data!$A51,Emp_Info!$B$2:$B$101,0),MATCH(HR_Data!AC$1,Emp_Info!$B$1:$G$1,0)) -> Bachelor | AD42: =INDEX(Emp_Info!$A$1:$G$101,MATCH(HR_Data!$A42,Emp_Info!$B$1:$B$101,0),MATCH(HR_Data!AD$1,Emp_Info!$A$1:$G$1,0)) -> Hyderabad | AE42: =INDEX(Emp_Info!$A$1:$G$101,MATCH(HR_Data!$A42,Emp_Info!$B$1:$B$101,0),MATCH(HR_Data!AE$1,Emp_Info!$A$1:$G$1,0)) -> South | AF42: =IF(AND(P42>=3,M42>6),"Eligible","Not Eligible") -> Eligible
A43: EMP023 | B43: 31419 | C43: 38 | D43: 42593 | E43: Campus | F43: D_005 | G43: Warehouse Manager | H43: Full-Time | I43: MGR105 | J43: 820000 | K43: 78000 | L43: =SUM(J43:K43) -> 898000 | M43: 15 | N43: 4.2 | O43: 97 | P43: 2 | Q43: Yes | R43: Low | S43: 44433 | T43: Active | U43: =VLOOKUP(A43,Emp_Info!$B$1:$G$101,3,0) -> vishal | V43: =_xlfn.XLOOKUP(A43,Emp_Info!$B$2:$B$101,Emp_Info!$A$2:$A$101,,0) -> tiwari | W43: =PROPER(_xlfn.CONCAT(U43," ",V43)) -> Vishal Tiwari | X43: =UPPER(_xlfn.CONCAT(LEFT(U43),LEFT(V43),RIGHT(A43,3))) -> VT023 | Y43: =HLOOKUP(F43,Dept_Info!$A$2:$I$3,2,0) -> Marketing | Z43: =IF(Y43="Sales",L43+(L43*$AG$6),L43) -> 898000 | AA43: =IF(J43<700000,"Low",IF(AND(J43>700000,J43<900000),"Medium","High")) -> Medium | AB43: Male | AC43: =INDEX(Emp_Info!$B$1:$G$101,MATCH(HR_Data!$A74,Emp_Info!$B$2:$B$101,0),MATCH(HR_Data!AC$1,Emp_Info!$B$1:$G$1,0)) -> Bachelor | AD43: =INDEX(Emp_Info!$A$1:$G$101,MATCH(HR_Data!$A43,Emp_Info!$B$1:$B$101,0),MATCH(HR_Data!AD$1,Emp_Info!$A$1:$G$1,0)) -> Delhi | AE43: =INDEX(Emp_Info!$A$1:$G$101,MATCH(HR_Data!$A43,Emp_Info!$B$1:$B$101,0),MATCH(HR_Data!AE$1,Emp_Info!$A$1:$G$1,0)) -> North | AF43: =IF(AND(P43>=3,M43>6),"Eligible","Not Eligible") -> Not Eligible
A44: EMP080 | B44: 33714 | C44: 32 | D44: 44267 | E44: Campus | F44: D_002 | G44: Diversity & Inclusion Manager | H44: Full-Time | I44: MGR102 | J44: 820000 | K44: 78000 | L44: =SUM(J44:K44) -> 898000 | M44: 8 | N44: 4.4 | O44: 97.9 | P44: 3 | Q44: Yes | R44: Low | S44: NA | T44: Active | U44: =VLOOKUP(A44,Emp_Info!$B$1:$G$101,3,0) -> shilpa | V44: =_xlfn.XLOOKUP(A44,Emp_Info!$B$2:$B$101,Emp_Info!$A$2:$A$101,,0) -> kulkarni | W44: =PROPER(_xlfn.CONCAT(U44," ",V44)) -> Shilpa Kulkarni | X44: =UPPER(_xlfn.CONCAT(LEFT(U44),LEFT(V44),RIGHT(A44,3))) -> SK080 | Y44: =HLOOKUP(F44,Dept_Info!$A$2:$I$3,2,0) -> HR | Z44: =IF(Y44="Sales",L44+(L44*$AG$6),L44) -> 898000 | AA44: =IF(J44<700000,"Low",IF(AND(J44>700000,J44<900000),"Medium","High")) -> Medium | AB44: Female | AC44: =INDEX(Emp_Info!$B$1:$G$101,MATCH(HR_Data!$A38,Emp_Info!$B$2:$B$101,0),MATCH(HR_Data!AC$1,Emp_Info!$B$1:$G$1,0)) -> Bachelor | AD44: =INDEX(Emp_Info!$A$1:$G$101,MATCH(HR_Data!$A44,Emp_Info!$B$1:$B$101,0),MATCH(HR_Data!AD$1,Emp_Info!$A$1:$G$1,0)) -> Bangalore | AE44: =INDEX(Emp_Info!$A$1:$G$101,MATCH(HR_Data!$A44,Emp_Info!$B$1:$B$101,0),MATCH(HR_Data!AE$1,Emp_Info!$A$1:$G$1,0)) -> South | AF44: =IF(AND(P44>=3,M44>6),"Eligible","Not Eligible") -> Eligible
A45: EMP067 | B45: 31726 | C45: 38 | D45: 42434 | E45: Referral | F45: D_003 | G45: Sales Trainer | H45: Full-Time | I45: MGR106 | J45: 810000 | K45: 78000 | L45: =SUM(J45:K45) -> 888000 | M45: 16 | N45: 4.3 | O45: 97.4 | P45: 2 | Q45: No | R45: Low | S45: 44270 | T45: Active | U45: =VLOOKUP(A45,Emp_Info!$B$1:$G$101,3,0) -> naveen | V45: =_xlfn.XLOOKUP(A45,Emp_Info!$B$2:$B$101,Emp_Info!$A$2:$A$101,,0) -> gupta | W45: =PROPER(_xlfn.CONCAT(U45," ",V45)) -> Naveen Gupta | X45: =UPPER(_xlfn.CONCAT(LEFT(U45),LEFT(V45),RIGHT(A45,3))) -> NG067 | Y45: =HLOOKUP(F45,Dept_Info!$A$2:$I$3,2,0) -> Sales | Z45: =IF(Y45="Sales",L45+(L45*$AG$6),L45) -> 1021200 | AA45: =IF(J45<700000,"Low",IF(AND(J45>700000,J45<900000),"Medium","High")) -> Medium | AB45: Male | AC45: =INDEX(Emp_Info!$B$1:$G$101,MATCH(HR_Data!$A87,Emp_Info!$B$2:$B$101,0),MATCH(HR_Data!AC$1,Emp_Info!$B$1:$G$1,0)) -> Master | AD45: =INDEX(Emp_Info!$A$1:$G$101,MATCH(HR_Data!$A45,Emp_Info!$B$1:$B$101,0),MATCH(HR_Data!AD$1,Emp_Info!$A$1:$G$1,0)) -> Pune | AE45: =INDEX(Emp_Info!$A$1:$G$101,MATCH(HR_Data!$A45,Emp_Info!$B$1:$B$101,0),MATCH(HR_Data!AE$1,Emp_Info!$A$1:$G$1,0)) -> West | AF45: =IF(AND(P45>=3,M45>6),"Eligible","Not Eligible") -> Not Eligible
A46: EMP060 | B46: 33403 | C46: 33 | D46: 43932 | E46: LinkedIn | F46: D_004 | G46: Communications Manager | H46: Full-Time | I46: MGR104 | J46: 810000 | K46: 78000 | L46: =SUM(J46:K46) -> 888000 | M46: 9 | N46: 4.3 | O46: 97.3 | P46: 2 | Q46: Yes | R46: Low | S46: NA | T46: Active | U46: =VLOOKUP(A46,Emp_Info!$B$1:$G$101,3,0) -> nidhi | V46: =_xlfn.XLOOKUP(A46,Emp_Info!$B$2:$B$101,Emp_Info!$A$2:$A$101,,0) -> kulkarni | W46: =PROPER(_xlfn.CONCAT(U46," ",V46)) -> Nidhi Kulkarni | X46: =UPPER(_xlfn.CONCAT(LEFT(U46),LEFT(V46),RIGHT(A46,3))) -> NK060 | Y46: =HLOOKUP(F46,Dept_Info!$A$2:$I$3,2,0) -> Admin | Z46: =IF(Y46="Sales",L46+(L46*$AG$6),L46) -> 888000 | AA46: =IF(J46<700000,"Low",IF(AND(J46>700000,J46<900000),"Medium","High")) -> Medium | AB46: Female | AC46: =INDEX(Emp_Info!$B$1:$G$101,MATCH(HR_Data!$A4,Emp_Info!$B$2:$B$101,0),MATCH(HR_Data!AC$1,Emp_Info!$B$1:$G$1,0)) -> Bachelor | AD46: =INDEX(Emp_Info!$A$1:$G$101,MATCH(HR_Data!$A46,Emp_Info!$B$1:$B$101,0),MATCH(HR_Data!AD$1,Emp_Info!$A$1:$G$1,0)) -> Pune | AE46: =INDEX(Emp_Info!$A$1:$G$101,MATCH(HR_Data!$A46,Emp_Info!$B$1:$B$101,0),MATCH(HR_Data!AE$1,Emp_Info!$A$1:$G$1,0)) -> West | AF46: =IF(AND(P46>=3,M46>6),"Eligible","Not Eligible") -> Not Eligible
A47: EMP071 | B47: 31865 | C47: 37 | D47: 42573 | E47: Job Portal | F47: D_005 | G47: Safety Manager | H47: Full-Time | I47: MGR105 | J47: 800000 | K47: 76000 | L47: =SUM(J47:K47) -> 876000 | M47: 15 | N47: 4.2 | O47: 97.2 | P47: 3 | Q47: Yes | R47: Low | S47: 44407 | T47: Active | U47: =VLOOKUP(A47,Emp_Info!$B$1:$G$101,3,0) -> tarun | V47: =_xlfn.XLOOKUP(A47,Emp_Info!$B$2:$B$101,Emp_Info!$A$2:$A$101,,0) -> shetty | W47: =PROPER(_xlfn.CONCAT(U47," ",V47)) -> Tarun Shetty | X47: =UPPER(_xlfn.CONCAT(LEFT(U47),LEFT(V47),RIGHT(A47,3))) -> TS071 | Y47: =HLOOKUP(F47,Dept_Info!$A$2:$I$3,2,0) -> Marketing | Z47: =IF(Y47="Sales",L47+(L47*$AG$6),L47) -> 876000 | AA47: =IF(J47<700000,"Low",IF(AND(J47>700000,J47<900000),"Medium","High")) -> Medium | AB47: Male | AC47: =INDEX(Emp_Info!$B$1:$G$101,MATCH(HR_Data!$A75,Emp_Info!$B$2:$B$101,0),MATCH(HR_Data!AC$1,Emp_Info!$B$1:$G$1,0)) -> Bachelor | AD47: =INDEX(Emp_Info!$A$1:$G$101,MATCH(HR_Data!$A47,Emp_Info!$B$1:$B$101,0),MATCH(HR_Data!AD$1,Emp_Info!$A$1:$G$1,0)) -> Hyderabad | AE47: =INDEX(Emp_Info!$A$1:$G$101,MATCH(HR_Data!$A47,Emp_Info!$B$1:$B$101,0),MATCH(HR_Data!AE$1,Emp_Info!$A$1:$G$1,0)) -> South | AF47: =IF(AND(P47>=3,M47>6),"Eligible","Not Eligible") -> Eligible
A48: EMP063 | B48: 32010 | C48: 37 | D48: 42537 | E48: Campus | F48: D_001 | G48: Network Engineer | H48: Full-Time | I48: MGR101 | J48: 790000 | K48: 75000 | L48: =SUM(J48:K48) -> 865000 | M48: 15 | N48: 4.2 | O48: 96.9 | P48: 3 | Q48: Yes | R48: Low | S48: 44367 | T48: Active | U48: =VLOOKUP(A48,Emp_Info!$B$1:$G$101,3,0) -> abhishek | V48: =_xlfn.XLOOKUP(A48,Emp_Info!$B$2:$B$101,Emp_Info!$A$2:$A$101,,0) -> pandey | W48: =PROPER(_xlfn.CONCAT(U48," ",V48)) -> Abhishek Pandey | X48: =UPPER(_xlfn.CONCAT(LEFT(U48),LEFT(V48),RIGHT(A48,3))) -> AP063 | Y48: =HLOOKUP(F48,Dept_Info!$A$2:$I$3,2,0) -> IT | Z48: =IF(Y48="Sales",L48+(L48*$AG$6),L48) -> 865000 | AA48: =IF(J48<700000,"Low",IF(AND(J48>700000,J48<900000),"Medium","High")) -> Medium | AB48: Male | AC48: =INDEX(Emp_Info!$B$1:$G$101,MATCH(HR_Data!$A52,Emp_Info!$B$2:$B$101,0),MATCH(HR_Data!AC$1,Emp_Info!$B$1:$G$1,0)) -> Master | AD48: =INDEX(Emp_Info!$A$1:$G$101,MATCH(HR_Data!$A48,Emp_Info!$B$1:$B$101,0),MATCH(HR_Data!AD$1,Emp_Info!$A$1:$G$1,0)) -> Mumbai | AE48: =INDEX(Emp_Info!$A$1:$G$101,MATCH(HR_Data!$A48,Emp_Info!$B$1:$B$101,0),MATCH(HR_Data!AE$1,Emp_Info!$A$1:$G$1,0)) -> West | AF48: =IF(AND(P48>=3,M48>6),"Eligible","Not Eligible") -> Eligible
A49: EMP083 | B49: 31835 | C49: 37 | D49: 42632 | E49: Freelance | F49: D_005 | G49: Maintenance Manager | H49: Full-Time | I49: MGR105 | J49: 790000 | K49: 75000 | L49: =SUM(J49:K49) -> 865000 | M49: 15 | N49: 4.1 | O49: 96.3 | P49: 2 | Q49: Yes | R49: Low | S49: 44464 | T49: Active | U49: =VLOOKUP(A49,Emp_Info!$B$1:$G$101,3,0) -> yogesh | V49: =_xlfn.XLOOKUP(A49,Emp_Info!$B$2:$B$101,Emp_Info!$A$2:$A$101,,0) -> pandey | W49: =PROPER(_xlfn.CONCAT(U49," ",V49)) -> Yogesh Pandey | X49: =UPPER(_xlfn.CONCAT(LEFT(U49),LEFT(V49),RIGHT(A49,3))) -> YP083 | Y49: =HLOOKUP(F49,Dept_Info!$A$2:$I$3,2,0) -> Marketing | Z49: =IF(Y49="Sales",L49+(L49*$AG$6),L49) -> 865000 | AA49: =IF(J49<700000,"Low",IF(AND(J49>700000,J49<900000),"Medium","High")) -> Medium | AB49: Male | AC49: =INDEX(Emp_Info!$B$1:$G$101,MATCH(HR_Data!$A76,Emp_Info!$B$2:$B$101,0),MATCH(HR_Data!AC$1,Emp_Info!$B$1:$G$1,0)) -> Master | AD49: =INDEX(Emp_Info!$A$1:$G$101,MATCH(HR_Data!$A49,Emp_Info!$B$1:$B$101,0),MATCH(HR_Data!AD$1,Emp_Info!$A$1:$G$1,0)) -> Chennai | AE49: =INDEX(Emp_Info!$A$1:$G$101,MATCH(HR_Data!$A49,Emp_Info!$B$1:$B$101,0),MATCH(HR_Data!AE$1,Emp_Info!$A$1:$G$1,0)) -> South | AF49: =IF(AND(P49>=3,M49>6),"Eligible","Not Eligible") -> Not Eligible
A50: EMP039 | B50: 32236 | C50: 36 | D50: 42942 | E50: LinkedIn | F50: D_006 | G50: Investment Analyst | H50: Full-Time | I50: MGR103 | J50: 790000 | K50: 72000 | L50: =SUM(J50:K50) -> 862000 | M50: 13 | N50: 4.2 | O50: 96.5 | P50: 2 | Q50: Yes | R50: Low | S50: 44752 | T50: Active | U50: =VLOOKUP(A50,Emp_Info!$B$1:$G$101,3,0) -> sandeep | V50: =_xlfn.XLOOKUP(A50,Emp_Info!$B$2:$B$101,Emp_Info!$A$2:$A$101,,0) -> rana | W50: =PROPER(_xlfn.CONCAT(U50," ",V50)) -> Sandeep Rana | X50: =UPPER(_xlfn.CONCAT(LEFT(U50),LEFT(V50),RIGHT(A50,3))) -> SR039 | Y50: =HLOOKUP(F50,Dept_Info!$A$2:$I$3,2,0) -> Finance | Z50: =IF(Y50="Sales",L50+(L50*$AG$6),L50) -> 862000 | AA50: =IF(J50<700000,"Low",IF(AND(J50>700000,J50<900000),"Medium","High")) -> Medium | AB50: Male | AC50: =INDEX(Emp_Info!$B$1:$G$101,MATCH(HR_Data!$A25,Emp_Info!$B$2:$B$101,0),MATCH(HR_Data!AC$1,Emp_Info!$B$1:$G$1,0)) -> Bachelor | AD50: =INDEX(Emp_Info!$A$1:$G$101,MATCH(HR_Data!$A50,Emp_Info!$B$1:$B$101,0),MATCH(HR_Data!AD$1,Emp_Info!$A$1:$G$1,0)) -> Delhi | AE50: =INDEX(Emp_Info!$A$1:$G$101,MATCH(HR_Data!$A50,Emp_Info!$B$1:$B$101,0),MATCH(HR_Data!AE$1,Emp_Info!$A$1:$G$1,0)) -> North | AF50: =IF(AND(P50>=3,M50>6),"Eligible","Not Eligible") -> Not Eligible
A51: EMP073 | B51: 33231 | C51: 34 | D51: 43512 | E51: Job Portal | F51: D_003 | G51: Customer Success Manager | H51: Full-Time | I51: MGR106 | J51: 780000 | K51: 75000 | L51: =SUM(J51:K51) -> 855000 | M51: 10 | N51: 4.2 | O51: 96.6 | P51: 2 | Q51: Yes | R51: Medium | S51: NA | T51: Active | U51: =VLOOKUP(A51,Emp_Info!$B$1:$G$101,3,0) -> ashish | V51: =_xlfn.XLOOKUP(A51,Emp_Info!$B$2:$B$101,Emp_Info!$A$2:$A$101,,0) -> pillai | W51: =PROPER(_xlfn.CONCAT(U51," ",V51)) -> Ashish Pillai | X51: =UPPER(_xlfn.CONCAT(LEFT(U51),LEFT(V51),RIGHT(A51,3))) -> AP073 | Y51: =HLOOKUP(F51,Dept_Info!$A$2:$I$3,2,0) -> Sales | Z51: =IF(Y51="Sales",L51+(L51*$AG$6),L51) -> 983250 | AA51: =IF(J51<700000,"Low",IF(AND(J51>700000,J51<900000),"Medium","High")) -> Medium | AB51: Male | AC51: =INDEX(Emp_Info!$B$1:$G$101,MATCH(HR_Data!$A97,Emp_Info!$B$2:$B$101,0),MATCH(HR_Data!AC$1,Emp_Info!$B$1:$G$1,0)) -> Master | AD51: =INDEX(Emp_Info!$A$1:$G$101,MATCH(HR_Data!$A51,Emp_Info!$B$1:$B$101,0),MATCH(HR_Data!AD$1,Emp_Info!$A$1:$G$1,0)) -> Bangalore | AE51: =INDEX(Emp_Info!$A$1:$G$101,MATCH(HR_Data!$A51,Emp_Info!$B$1:$B$101,0),MATCH(HR_Data!AE$1,Emp_Info!$A$1:$G$1,0)) -> South | AF51: =IF(AND(P51>=3,M51>6),"Eligible","Not Eligible") -> Not Eligible
A52: EMP027 | B52: 30940 | C52: 40 | D52: 42013 | E52: Referral | F52: D_001 | G52: System Administrator | H52: Full-Time | I52: MGR101 | J52: 780000 | K52: 72000 | L52: =SUM(J52:K52) -> 852000 | M52: 19 | N52: 4.1 | O52: 96.4 | P52: 3 | Q52: No | R52: Low | S52: 43845 | T52: Active | U52: =VLOOKUP(A52,Emp_Info!$B$1:$G$101,3,0) -> ashok | V52: =_xlfn.XLOOKUP(A52,Emp_Info!$B$2:$B$101,Emp_Info!$A$2:$A$101,,0) -> bansal | W52: =PROPER(_xlfn.CONCAT(U52," ",V52)) -> Ashok Bansal | X52: =UPPER(_xlfn.CONCAT(LEFT(U52),LEFT(V52),RIGHT(A52,3))) -> AB027 | Y52: =HLOOKUP(F52,Dept_Info!$A$2:$I$3,2,0) -> IT | Z52: =IF(Y52="Sales",L52+(L52*$AG$6),L52) -> 852000 | AA52: =IF(J52<700000,"Low",IF(AND(J52>700000,J52<900000),"Medium","High")) -> Medium | AB52: Male | AC52: =INDEX(Emp_Info!$B$1:$G$101,MATCH(HR_Data!$A47,Emp_Info!$B$2:$B$101,0),MATCH(HR_Data!AC$1,Emp_Info!$B$1:$G$1,0)) -> Bachelor | AD52: =INDEX(Emp_Info!$A$1:$G$101,MATCH(HR_Data!$A52,Emp_Info!$B$1:$B$101,0),MATCH(HR_Data!AD$1,Emp_Info!$A$1:$G$1,0)) -> Mumbai | AE52: =INDEX(Emp_Info!$A$1:$G$101,MATCH(HR_Data!$A52,Emp_Info!$B$1:$B$101,0),MATCH(HR_Data!AE$1,Emp_Info!$A$1:$G$1,0)) -> West | AF52: =IF(AND(P52>=3,M52>6),"Eligible","Not Eligible") -> Eligible
A53: EMP076 | B53: 33270 | C53: 33 | D53: 43735 | E53: Job Portal | F53: D_005 | G53: Customer Service Manager | H53: Full-Time | I53: MGR105 | J53: 780000 | K53: 72000 | L53: =SUM(J53:K53) -> 852000 | M53: 9 | N53: 4.3 | O53: 97.5 | P53: 2 | Q53: Yes | R53: Low | S53: 45184 | T53: Active | U53: =VLOOKUP(A53,Emp_Info!$B$1:$G$101,3,0) -> sunita | V53: =_xlfn.XLOOKUP(A53,Emp_Info!$B$2:$B$101,Emp_Info!$A$2:$A$101,,0) -> nair | W53: =PROPER(_xlfn.CONCAT(U53," ",V53)) -> Sunita Nair | X53: =UPPER(_xlfn.CONCAT(LEFT(U53),LEFT(V53),RIGHT(A53,3))) -> SN076 | Y53: =HLOOKUP(F53,Dept_Info!$A$2:$I$3,2,0) -> Marketing | Z53: =IF(Y53="Sales",L53+(L53*$AG$6),L53) -> 852000 | AA53: =IF(J53<700000,"Low",IF(AND(J53>700000,J53<900000),"Medium","High")) -> Medium | AB53: Female | AC53: =INDEX(Emp_Info!$B$1:$G$101,MATCH(HR_Data!$A83,Emp_Info!$B$2:$B$101,0),MATCH(HR_Data!AC$1,Emp_Info!$B$1:$G$1,0)) -> Bachelor | AD53: =INDEX(Emp_Info!$A$1:$G$101,MATCH(HR_Data!$A53,Emp_Info!$B$1:$B$101,0),MATCH(HR_Data!AD$1,Emp_Info!$A$1:$G$1,0)) -> Mumbai | AE53: =INDEX(Emp_Info!$A$1:$G$101,MATCH(HR_Data!$A53,Emp_Info!$B$1:$B$101,0),MATCH(HR_Data!AE$1,Emp_Info!$A$1:$G$1,0)) -> West | AF53: =IF(AND(P53>=3,M53>6),"Eligible","Not Eligible") -> Not Eligible
A54: EMP024 | B54: 33803 | C54: 32 | D54: 44170 | E54: LinkedIn | F54: D_004 | G54: Brand Manager | H54: Full-Time | I54: MGR104 | J54: 780000 | K54: 72000 | L54: =SUM(J54:K54) -> 852000 | M54: 8 | N54: 4.4 | O54: 98.3 | P54: 3 | Q54: Yes | R54: Low | S54: NA | T54: Active | U54: =VLOOKUP(A54,Emp_Info!$B$1:$G$101,3,0) -> anjali | V54: =_xlfn.XLOOKUP(A54,Emp_Info!$B$2:$B$101,Emp_Info!$A$2:$A$101,,0) -> sinha | W54: =PROPER(_xlfn.CONCAT(U54," ",V54)) -> Anjali Sinha | X54: =UPPER(_xlfn.CONCAT(LEFT(U54),LEFT(V54),RIGHT(A54,3))) -> AS024 | Y54: =HLOOKUP(F54,Dept_Info!$A$2:$I$3,2,0) -> Admin | Z54: =IF(Y54="Sales",L54+(L54*$AG$6),L54) -> 852000 | AA54: =IF(J54<700000,"Low",IF(AND(J54>700000,J54<900000),"Medium","High")) -> Medium | AB54: Female | AC54: =INDEX(Emp_Info!$B$1:$G$101,MATCH(HR_Data!$A6,Emp_Info!$B$2:$B$101,0),MATCH(HR_Data!AC$1,Emp_Info!$B$1:$G$1,0)) -> Bachelor | AD54: =INDEX(Emp_Info!$A$1:$G$101,MATCH(HR_Data!$A54,Emp_Info!$B$1:$B$101,0),MATCH(HR_Data!AD$1,Emp_Info!$A$1:$G$1,0)) -> Bangalore | AE54: =INDEX(Emp_Info!$A$1:$G$101,MATCH(HR_Data!$A54,Emp_Info!$B$1:$B$101,0),MATCH(HR_Data!AE$1,Emp_Info!$A$1:$G$1,0)) -> South | AF54: =IF(AND(P54>=3,M54>6),"Eligible","Not Eligible") -> Eligible
A55: EMP050 | B55: 34255 | C55: 31 | D55: 44338 | E55: Job Portal | F55: D_001 | G55: Cybersecurity Analyst | H55: Full-Time | I55: MGR101 | J55: 780000 | K55: 72000 | L55: =SUM(J55:K55) -> 852000 | M55: 6 | N55: 4.2 | O55: 96.7 | P55: 3 | Q55: Yes | R55: Low | S55: NA | T55: Active | U55: =VLOOKUP(A55,Emp_Info!$B$1:$G$101,3,0) -> kavya | V55: =_xlfn.XLOOKUP(A55,Emp_Info!$B$2:$B$101,Emp_Info!$A$2:$A$101,,0) -> iyer | W55: =PROPER(_xlfn.CONCAT(U55," ",V55)) -> Kavya Iyer | X55: =UPPER(_xlfn.CONCAT(LEFT(U55),LEFT(V55),RIGHT(A55,3))) -> KI050 | Y55: =HLOOKUP(F55,Dept_Info!$A$2:$I$3,2,0) -> IT | Z55: =IF(Y55="Sales",L55+(L55*$AG$6),L55) -> 852000 | AA55: =IF(J55<700000,"Low",IF(AND(J55>700000,J55<900000),"Medium","High")) -> Medium | AB55: Female | AC55: =INDEX(Emp_Info!$B$1:$G$101,MATCH(HR_Data!$A62,Emp_Info!$B$2:$B$101,0),MATCH(HR_Data!AC$1,Emp_Info!$B$1:$G$1,0)) -> Bachelor | AD55: =INDEX(Emp_Info!$A$1:$G$101,MATCH(HR_Data!$A55,Emp_Info!$B$1:$B$101,0),MATCH(HR_Data!AD$1,Emp_Info!$A$1:$G$1,0)) -> Noida | AE55: =INDEX(Emp_Info!$A$1:$G$101,MATCH(HR_Data!$A55,Emp_Info!$B$1:$B$101,0),MATCH(HR_Data!AE$1,Emp_Info!$A$1:$G$1,0)) -> North | AF55: =IF(AND(P55>=3,M55>6),"Eligible","Not Eligible") -> Not Eligible
A56: EMP003 | B56: 32457 | C56: 36 | D56: 42755 | E56: Referral | F56: D_006 | G56: Financial Analyst | H56: Full-Time | I56: MGR103 | J56: 780000 | K56: 70000 | L56: =SUM(J56:K56) -> 850000 | M56: 14 | N56: 3.8 | O56: 94.3 | P56: 1 | Q56: No | R56: Medium | S56: NA | T56: Active | U56: =VLOOKUP(A56,Emp_Info!$B$1:$G$101,3,0) -> amit | V56: =_xlfn.XLOOKUP(A56,Emp_Info!$B$2:$B$101,Emp_Info!$A$2:$A$101,,0) -> patel | W56: =PROPER(_xlfn.CONCAT(U56," ",V56)) -> Amit Patel | X56: =UPPER(_xlfn.CONCAT(LEFT(U56),LEFT(V56),RIGHT(A56,3))) -> AP003 | Y56: =HLOOKUP(F56,Dept_Info!$A$2:$I$3,2,0) -> Finance | Z56: =IF(Y56="Sales",L56+(L56*$AG$6),L56) -> 850000 | AA56: =IF(J56<700000,"Low",IF(AND(J56>700000,J56<900000),"Medium","High")) -> Medium | AB56: Male | AC56: =INDEX(Emp_Info!$B$1:$G$101,MATCH(HR_Data!$A24,Emp_Info!$B$2:$B$101,0),MATCH(HR_Data!AC$1,Emp_Info!$B$1:$G$1,0)) -> Master | AD56: =INDEX(Emp_Info!$A$1:$G$101,MATCH(HR_Data!$A56,Emp_Info!$B$1:$B$101,0),MATCH(HR_Data!AD$1,Emp_Info!$A$1:$G$1,0)) -> Bangalore | AE56: =INDEX(Emp_Info!$A$1:$G$101,MATCH(HR_Data!$A56,Emp_Info!$B$1:$B$101,0),MATCH(HR_Data!AE$1,Emp_Info!$A$1:$G$1,0)) -> South | AF56: =IF(AND(P56>=3,M56>6),"Eligible","Not Eligible") -> Not Eligible
A57: EMP087 | B57: 32218 | C57: 36 | D57: 42924 | E57: LinkedIn | F57: D_006 | G57: Internal Auditor | H57: Full-Time | I57: MGR103 | J57: 770000 | K57: 72000 | L57: =SUM(J57:K57) -> 842000 | M57: 13 | N57: 4.1 | O57: 96.5 | P57: 2 | Q57: Yes | R57: Low | S57: 44757 | T57: Active | U57: =VLOOKUP(A57,Emp_Info!$B$1:$G$101,3,0) -> hemant | V57: =_xlfn.XLOOKUP(A57,Emp_Info!$B$2:$B$101,Emp_Info!$A$2:$A$101,,0) -> gupta | W57: =PROPER(_xlfn.CONCAT(U57," ",V57)) -> Hemant Gupta | X57: =UPPER(_xlfn.CONCAT(LEFT(U57),LEFT(V57),RIGHT(A57,3))) -> HG087 | Y57: =HLOOKUP(F57,Dept_Info!$A$2:$I$3,2,0) -> Finance | Z57: =IF(Y57="Sales",L57+(L57*$AG$6),L57) -> 842000 | AA57: =IF(J57<700000,"Low",IF(AND(J57>700000,J57<900000),"Medium","High")) -> Medium | AB57: Male | AC57: =INDEX(Emp_Info!$B$1:$G$101,MATCH(HR_Data!$A26,Emp_Info!$B$2:$B$101,0),MATCH(HR_Data!AC$1,Emp_Info!$B$1:$G$1,0)) -> Bachelor | AD57: =INDEX(Emp_Info!$A$1:$G$101,MATCH(HR_Data!$A57,Emp_Info!$B$1:$B$101,0),MATCH(HR_Data!AD$1,Emp_Info!$A$1:$G$1,0)) -> Hyderabad | AE57: =INDEX(Emp_Info!$A$1:$G$101,MATCH(HR_Data!$A57,Emp_Info!$B$1:$B$101,0),MATCH(HR_Data!AE$1,Emp_Info!$A$1:$G$1,0)) -> South | AF57: =IF(AND(P57>=3,M57>6),"Eligible","Not Eligible") -> Not Eligible
A58: EMP057 | B58: 32753 | C58: 35 | D58: 43235 | E58: Referral | F58: D_006 | G58: Risk Analyst | H58: Full-Time | I58: MGR103 | J58: 770000 | K58: 71000 | L58: =SUM(J58:K58) -> 841000 | M58: 11 | N58: 4.1 | O58: 96.2 | P58: 2 | Q58: Yes | R58: Low | S58: 45066 | T58: Active | U58: =VLOOKUP(A58,Emp_Info!$B$1:$G$101,3,0) -> mohit | V58: =_xlfn.XLOOKUP(A58,Emp_Info!$B$2:$B$101,Emp_Info!$A$2:$A$101,,0) -> jain | W58: =PROPER(_xlfn.CONCAT(U58," ",V58)) -> Mohit Jain | X58: =UPPER(_xlfn.CONCAT(LEFT(U58),LEFT(V58),RIGHT(A58,3))) -> MJ057 | Y58: =HLOOKUP(F58,Dept_Info!$A$2:$I$3,2,0) -> Finance | Z58: =IF(Y58="Sales",L58+(L58*$AG$6),L58) -> 841000 | AA58: =IF(J58<700000,"Low",IF(AND(J58>700000,J58<900000),"Medium","High")) -> Medium | AB58: Male | AC58: =INDEX(Emp_Info!$B$1:$G$101,MATCH(HR_Data!$A32,Emp_Info!$B$2:$B$101,0),MATCH(HR_Data!AC$1,Emp_Info!$B$1:$G$1,0)) -> Bachelor | AD58: =INDEX(Emp_Info!$A$1:$G$101,MATCH(HR_Data!$A58,Emp_Info!$B$1:$B$101,0),MATCH(HR_Data!AD$1,Emp_Info!$A$1:$G$1,0)) -> Mumbai | AE58: =INDEX(Emp_Info!$A$1:$G$101,MATCH(HR_Data!$A58,Emp_Info!$B$1:$B$101,0),MATCH(HR_Data!AE$1,Emp_Info!$A$1:$G$1,0)) -> West | AF58: =IF(AND(P58>=3,M58>6),"Eligible","Not Eligible") -> Not Eligible
A59: EMP065 | B59: 32919 | C59: 34 | D59: 43356 | E59: Job Portal | F59: D_005 | G59: Inventory Manager | H59: Full-Time | I59: MGR105 | J59: 760000 | K59: 72000 | L59: =SUM(J59:K59) -> 832000 | M59: 11 | N59: 4.1 | O59: 96.4 | P59: 2 | Q59: Yes | R59: Low | S59: 45189 | T59: Active | U59: =VLOOKUP(A59,Emp_Info!$B$1:$G$101,3,0) -> pankaj | V59: =_xlfn.XLOOKUP(A59,Emp_Info!$B$2:$B$101,Emp_Info!$A$2:$A$101,,0) -> bansal | W59: =PROPER(_xlfn.CONCAT(U59," ",V59)) -> Pankaj Bansal | X59: =UPPER(_xlfn.CONCAT(LEFT(U59),LEFT(V59),RIGHT(A59,3))) -> PB065 | Y59: =HLOOKUP(F59,Dept_Info!$A$2:$I$3,2,0) -> Marketing | Z59: =IF(Y59="Sales",L59+(L59*$AG$6),L59) -> 832000 | AA59: =IF(J59<700000,"Low",IF(AND(J59>700000,J59<900000),"Medium","High")) -> Medium | AB59: Male | AC59: =INDEX(Emp_Info!$B$1:$G$101,MATCH(HR_Data!$A80,Emp_Info!$B$2:$B$101,0),MATCH(HR_Data!AC$1,Emp_Info!$B$1:$G$1,0)) -> Master | AD59: =INDEX(Emp_Info!$A$1:$G$101,MATCH(HR_Data!$A59,Emp_Info!$B$1:$B$101,0),MATCH(HR_Data!AD$1,Emp_Info!$A$1:$G$1,0)) -> Noida | AE59: =INDEX(Emp_Info!$A$1:$G$101,MATCH(HR_Data!$A59,Emp_Info!$B$1:$B$101,0),MATCH(HR_Data!AE$1,Emp_Info!$A$1:$G$1,0)) -> North | AF59: =IF(AND(P59>=3,M59>6),"Eligible","Not Eligible") -> Not Eligible
A60: EMP090 | B60: 33748 | C60: 32 | D60: 44062 | E60: Campus | F60: D_004 | G60: Partnership Manager | H60: Full-Time | I60: MGR104 | J60: 760000 | K60: 72000 | L60: =SUM(J60:K60) -> 832000 | M60: 8 | N60: 4.2 | O60: 96.9 | P60: 2 | Q60: Yes | R60: Low | S60: NA | T60: Active | U60: =VLOOKUP(A60,Emp_Info!$B$1:$G$101,3,0) -> naina | V60: =_xlfn.XLOOKUP(A60,Emp_Info!$B$2:$B$101,Emp_Info!$A$2:$A$101,,0) -> tiwari | W60: =PROPER(_xlfn.CONCAT(U60," ",V60)) -> Naina Tiwari | X60: =UPPER(_xlfn.CONCAT(LEFT(U60),LEFT(V60),RIGHT(A60,3))) -> NT090 | Y60: =HLOOKUP(F60,Dept_Info!$A$2:$I$3,2,0) -> Admin | Z60: =IF(Y60="Sales",L60+(L60*$AG$6),L60) -> 832000 | AA60: =IF(J60<700000,"Low",IF(AND(J60>700000,J60<900000),"Medium","High")) -> Medium | AB60: Female | AC60: =INDEX(Emp_Info!$B$1:$G$101,MATCH(HR_Data!$A7,Emp_Info!$B$2:$B$101,0),MATCH(HR_Data!AC$1,Emp_Info!$B$1:$G$1,0)) -> Bachelor | AD60: =INDEX(Emp_Info!$A$1:$G$101,MATCH(HR_Data!$A60,Emp_Info!$B$1:$B$101,0),MATCH(HR_Data!AD$1,Emp_Info!$A$1:$G$1,0)) -> Chennai | AE60: =INDEX(Emp_Info!$A$1:$G$101,MATCH(HR_Data!$A60,Emp_Info!$B$1:$B$101,0),MATCH(HR_Data!AE$1,Emp_Info!$A$1:$G$1,0)) -> South | AF60: =IF(AND(P60>=3,M60>6),"Eligible","Not Eligible") -> Not Eligible
A61: EMP045 | B61: 32579 | C61: 35 | D61: 42964 | E61: Job Portal | F61: D_006 | G61: Treasury Analyst | H61: Full-Time | I61: MGR103 | J61: 760000 | K61: 70000 | L61: =SUM(J61:K61) -> 830000 | M61: 12 | N61: 4 | O61: 95.8 | P61: 2 | Q61: Yes | R61: Low | S61: 44798 | T61: Active | U61: =VLOOKUP(A61,Emp_Info!$B$1:$G$101,3,0) -> aditya | V61: =_xlfn.XLOOKUP(A61,Emp_Info!$B$2:$B$101,Emp_Info!$A$2:$A$101,,0) -> verma | W61: =PROPER(_xlfn.CONCAT(U61," ",V61)) -> Aditya Verma | X61: =UPPER(_xlfn.CONCAT(LEFT(U61),LEFT(V61),RIGHT(A61,3))) -> AV045 | Y61: =HLOOKUP(F61,Dept_Info!$A$2:$I$3,2,0) -> Finance | Z61: =IF(Y61="Sales",L61+(L61*$AG$6),L61) -> 830000 | AA61: =IF(J61<700000,"Low",IF(AND(J61>700000,J61<900000),"Medium","High")) -> Medium | AB61: Male | AC61: =INDEX(Emp_Info!$B$1:$G$101,MATCH(HR_Data!$A29,Emp_Info!$B$2:$B$101,0),MATCH(HR_Data!AC$1,Emp_Info!$B$1:$G$1,0)) -> Bachelor | AD61: =INDEX(Emp_Info!$A$1:$G$101,MATCH(HR_Data!$A61,Emp_Info!$B$1:$B$101,0),MATCH(HR_Data!AD$1,Emp_Info!$A$1:$G$1,0)) -> Mumbai | AE61: =INDEX(Emp_Info!$A$1:$G$101,MATCH(HR_Data!$A61,Emp_Info!$B$1:$B$101,0),MATCH(HR_Data!AE$1,Emp_Info!$A$1:$G$1,0)) -> West | AF61: =IF(AND(P61>=3,M61>6),"Eligible","Not Eligible") -> Not Eligible
A62: EMP015 | B62: 32333 | C62: 36 | D62: 42981 | E62: Job Portal | F62: D_006 | G62: Tax Consultant | H62: Full-Time | I62: MGR103 | J62: 750000 | K62: 68000 | L62: =SUM(J62:K62) -> 818000 | M62: 12 | N62: 4 | O62: 96.8 | P62: 2 | Q62: Yes | R62: Low | S62: 44819 | T62: Active | U62: =VLOOKUP(A62,Emp_Info!$B$1:$G$101,3,0) -> karan | V62: =_xlfn.XLOOKUP(A62,Emp_Info!$B$2:$B$101,Emp_Info!$A$2:$A$101,,0) -> malhotra | W62: =PROPER(_xlfn.CONCAT(U62," ",V62)) -> Karan Malhotra | X62: =UPPER(_xlfn.CONCAT(LEFT(U62),LEFT(V62),RIGHT(A62,3))) -> KM015 | Y62: =HLOOKUP(F62,Dept_Info!$A$2:$I$3,2,0) -> Finance | Z62: =IF(Y62="Sales",L62+(L62*$AG$6),L62) -> 818000 | AA62: =IF(J62<700000,"Low",IF(AND(J62>700000,J62<900000),"Medium","High")) -> Medium | AB62: Male | AC62: =INDEX(Emp_Info!$B$1:$G$101,MATCH(HR_Data!$A28,Emp_Info!$B$2:$B$101,0),MATCH(HR_Data!AC$1,Emp_Info!$B$1:$G$1,0)) -> Bachelor | AD62: =INDEX(Emp_Info!$A$1:$G$101,MATCH(HR_Data!$A62,Emp_Info!$B$1:$B$101,0),MATCH(HR_Data!AD$1,Emp_Info!$A$1:$G$1,0)) -> Delhi | AE62: =INDEX(Emp_Info!$A$1:$G$101,MATCH(HR_Data!$A62,Emp_Info!$B$1:$B$101,0),MATCH(HR_Data!AE$1,Emp_Info!$A$1:$G$1,0)) -> North | AF62: =IF(AND(P62>=3,M62>6),"Eligible","Not Eligible") -> Not Eligible
A63: EMP069 | B63: 32512 | C63: 35 | D63: 43216 | E63: Freelance | F63: D_006 | G63: Credit Analyst | H63: Full-Time | I63: MGR103 | J63: 740000 | K63: 68000 | L63: =SUM(J63:K63) -> 808000 | M63: 12 | N63: 4 | O63: 95.6 | P63: 2 | Q63: Yes | R63: Low | S63: 45026 | T63: Active | U63: =VLOOKUP(A63,Emp_Info!$B$1:$G$101,3,0) -> deepak | V63: =_xlfn.XLOOKUP(A63,Emp_Info!$B$2:$B$101,Emp_Info!$A$2:$A$101,,0) -> yadav | W63: =PROPER(_xlfn.CONCAT(U63," ",V63)) -> Deepak Yadav | X63: =UPPER(_xlfn.CONCAT(LEFT(U63),LEFT(V63),RIGHT(A63,3))) -> DY069 | Y63: =HLOOKUP(F63,Dept_Info!$A$2:$I$3,2,0) -> Finance | Z63: =IF(Y63="Sales",L63+(L63*$AG$6),L63) -> 808000 | AA63: =IF(J63<700000,"Low",IF(AND(J63>700000,J63<900000),"Medium","High")) -> Medium | AB63: Male | AC63: =INDEX(Emp_Info!$B$1:$G$101,MATCH(HR_Data!$A30,Emp_Info!$B$2:$B$101,0),MATCH(HR_Data!AC$1,Emp_Info!$B$1:$G$1,0)) -> Bachelor | AD63: =INDEX(Emp_Info!$A$1:$G$101,MATCH(HR_Data!$A63,Emp_Info!$B$1:$B$101,0),MATCH(HR_Data!AD$1,Emp_Info!$A$1:$G$1,0)) -> Delhi | AE63: =INDEX(Emp_Info!$A$1:$G$101,MATCH(HR_Data!$A63,Emp_Info!$B$1:$B$101,0),MATCH(HR_Data!AE$1,Emp_Info!$A$1:$G$1,0)) -> North | AF63: =IF(AND(P63>=3,M63>6),"Eligible","Not Eligible") -> Not Eligible
A64: EMP032 | B64: 33769 | C64: 32 | D64: 43940 | E64: Linkedin | F64: D_001 | G64: Business Analyst | H64: Full-Time | I64: MGR101 | J64: 740000 | K64: 68000 | L64: =SUM(J64:K64) -> 808000 | M64: 8 | N64: 4.2 | O64: 97.2 | P64: 2 | Q64: Yes | R64: Low | S64: NA | T64: Active | U64: =VLOOKUP(A64,Emp_Info!$B$1:$G$101,3,0) -> tanvi | V64: =_xlfn.XLOOKUP(A64,Emp_Info!$B$2:$B$101,Emp_Info!$A$2:$A$101,,0) -> deshpande | W64: =PROPER(_xlfn.CONCAT(U64," ",V64)) -> Tanvi Deshpande | X64: =UPPER(_xlfn.CONCAT(LEFT(U64),LEFT(V64),RIGHT(A64,3))) -> TD032 | Y64: =HLOOKUP(F64,Dept_Info!$A$2:$I$3,2,0) -> IT | Z64: =IF(Y64="Sales",L64+(L64*$AG$6),L64) -> 808000 | AA64: =IF(J64<700000,"Low",IF(AND(J64>700000,J64<900000),"Medium","High")) -> Medium | AB64: Female | AC64: =INDEX(Emp_Info!$B$1:$G$101,MATCH(HR_Data!$A60,Emp_Info!$B$2:$B$101,0),MATCH(HR_Data!AC$1,Emp_Info!$B$1:$G$1,0)) -> Bachelor | AD64: =INDEX(Emp_Info!$A$1:$G$101,MATCH(HR_Data!$A64,Emp_Info!$B$1:$B$101,0),MATCH(HR_Data!AD$1,Emp_Info!$A$1:$G$1,0)) -> Mumbai | AE64: =INDEX(Emp_Info!$A$1:$G$101,MATCH(HR_Data!$A64,Emp_Info!$B$1:$B$101,0),MATCH(HR_Data!AE$1,Emp_Info!$A$1:$G$1,0)) -> West | AF64: =IF(AND(P64>=3,M64>6),"Eligible","Not Eligible") -> Not Eligible
A65: EMP064 | B65: 33880 | C65: 32 | D65: 44164 | E65: LinkedIn | F65: D_006 | G65: Payroll Manager | H65: Full-Time | I65: MGR103 | J65: 730000 | K65: 68000 | L65: =SUM(J65:K65) -> 798000 | M65: 8 | N65: 4 | O65: 95.9 | P65: 2 | Q65: Yes | R65: Low | S65: NA | T65: Active | U65: =VLOOKUP(A65,Emp_Info!$B$1:$G$101,3,0) -> megha | V65: =_xlfn.XLOOKUP(A65,Emp_Info!$B$2:$B$101,Emp_Info!$A$2:$A$101,,0) -> tiwari | W65: =PROPER(_xlfn.CONCAT(U65," ",V65)) -> Megha Tiwari | X65: =UPPER(_xlfn.CONCAT(LEFT(U65),LEFT(V65),RIGHT(A65,3))) -> MT064 | Y65: =HLOOKUP(F65,Dept_Info!$A$2:$I$3,2,0) -> Finance | Z65: =IF(Y65="Sales",L65+(L65*$AG$6),L65) -> 798000 | AA65: =IF(J65<700000,"Low",IF(AND(J65>700000,J65<900000),"Medium","High")) -> Medium | AB65: Female | AC65: =INDEX(Emp_Info!$B$1:$G$101,MATCH(HR_Data!$A34,Emp_Info!$B$2:$B$101,0),MATCH(HR_Data!AC$1,Emp_Info!$B$1:$G$1,0)) -> Bachelor | AD65: =INDEX(Emp_Info!$A$1:$G$101,MATCH(HR_Data!$A65,Emp_Info!$B$1:$B$101,0),MATCH(HR_Data!AD$1,Emp_Info!$A$1:$G$1,0)) -> Hyderabad | AE65: =INDEX(Emp_Info!$A$1:$G$101,MATCH(HR_Data!$A65,Emp_Info!$B$1:$B$101,0),MATCH(HR_Data!AE$1,Emp_Info!$A$1:$G$1,0)) -> South | AF65: =IF(AND(P65>=3,M65>6),"Eligible","Not Eligible") -> Not Eligible
A66: EMP053 | B66: 33218 | C66: 34 | D66: 43542 | E66: LinkedIn | F66: D_005 | G66: Facilities Manager | H66: Full-Time | I66: MGR105 | J66: 720000 | K66: 68000 | L66: =SUM(J66:K66) -> 788000 | M66: 10 | N66: 4 | O66: 95.4 | P66: 2 | Q66: Yes | R66: Medium | S66: NA | T66: Active | U66: =VLOOKUP(A66,Emp_Info!$B$1:$G$101,3,0) -> vivek | V66: =_xlfn.XLOOKUP(A66,Emp_Info!$B$2:$B$101,Emp_Info!$A$2:$A$101,,0) -> nair | W66: =PROPER(_xlfn.CONCAT(U66," ",V66)) -> Vivek Nair | X66: =UPPER(_xlfn.CONCAT(LEFT(U66),LEFT(V66),RIGHT(A66,3))) -> VN053 | Y66: =HLOOKUP(F66,Dept_Info!$A$2:$I$3,2,0) -> Marketing | Z66: =IF(Y66="Sales",L66+(L66*$AG$6),L66) -> 788000 | AA66: =IF(J66<700000,"Low",IF(AND(J66>700000,J66<900000),"Medium","High")) -> Medium | AB66: Male | AC66: =INDEX(Emp_Info!$B$1:$G$101,MATCH(HR_Data!$A81,Emp_Info!$B$2:$B$101,0),MATCH(HR_Data!AC$1,Emp_Info!$B$1:$G$1,0)) -> Bachelor | AD66: =INDEX(Emp_Info!$A$1:$G$101,MATCH(HR_Data!$A66,Emp_Info!$B$1:$B$101,0),MATCH(HR_Data!AD$1,Emp_Info!$A$1:$G$1,0)) -> Delhi | AE66: =INDEX(Emp_Info!$A$1:$G$101,MATCH(HR_Data!$A66,Emp_Info!$B$1:$B$101,0),MATCH(HR_Data!AE$1,Emp_Info!$A$1:$G$1,0)) -> North | AF66: =IF(AND(P66>=3,M66>6),"Eligible","Not Eligible") -> Not Eligible
A67: EMP078 | B67: 34238 | C67: 31 | D67: 44367 | E67: Referral | F67: D_004 | G67: Influencer Marketing Manager | H67: Full-Time | I67: MGR104 | J67: 720000 | K67: 68000 | L67: =SUM(J67:K67) -> 788000 | M67: 6 | N67: 4.2 | O67: 96.8 | P67: 2 | Q67: Yes | R67: Low | S67: NA | T67: Active | U67: =VLOOKUP(A67,Emp_Info!$B$1:$G$101,3,0) -> archana | V67: =_xlfn.XLOOKUP(A67,Emp_Info!$B$2:$B$101,Emp_Info!$A$2:$A$101,,0) -> bhatt | W67: =PROPER(_xlfn.CONCAT(U67," ",V67)) -> Archana Bhatt | X67: =UPPER(_xlfn.CONCAT(LEFT(U67),LEFT(V67),RIGHT(A67,3))) -> AB078 | Y67: =HLOOKUP(F67,Dept_Info!$A$2:$I$3,2,0) -> Admin | Z67: =IF(Y67="Sales",L67+(L67*$AG$6),L67) -> 788000 | AA67: =IF(J67<700000,"Low",IF(AND(J67>700000,J67<900000),"Medium","High")) -> Medium | AB67: Female | AC67: =INDEX(Emp_Info!$B$1:$G$101,MATCH(HR_Data!$A11,Emp_Info!$B$2:$B$101,0),MATCH(HR_Data!AC$1,Emp_Info!$B$1:$G$1,0)) -> Bachelor | AD67: =INDEX(Emp_Info!$A$1:$G$101,MATCH(HR_Data!$A67,Emp_Info!$B$1:$B$101,0),MATCH(HR_Data!AD$1,Emp_Info!$A$1:$G$1,0)) -> Pune | AE67: =INDEX(Emp_Info!$A$1:$G$101,MATCH(HR_Data!$A67,Emp_Info!$B$1:$B$101,0),MATCH(HR_Data!AE$1,Emp_Info!$A$1:$G$1,0)) -> West | AF67: =IF(AND(P67>=3,M67>6),"Eligible","Not Eligible") -> Not Eligible
A68: EMP094 | B68: 34436 | C68: 30 | D68: 44892 | E68: Referral | F68: D_005 | G68: Quality Assurance Manager | H68: Full-Time | I68: MGR105 | J68: 720000 | K68: 68000 | L68: =SUM(J68:K68) -> 788000 | M68: 5 | N68: 4 | O68: 95.7 | P68: 2 | Q68: Yes | R68: Medium | S68: NA | T68: Active | U68: =VLOOKUP(A68,Emp_Info!$B$1:$G$101,3,0) -> shraddha | V68: =_xlfn.XLOOKUP(A68,Emp_Info!$B$2:$B$101,Emp_Info!$A$2:$A$101,,0) -> joshi | W68: =PROPER(_xlfn.CONCAT(U68," ",V68)) -> Shraddha Joshi | X68: =UPPER(_xlfn.CONCAT(LEFT(U68),LEFT(V68),RIGHT(A68,3))) -> SJ094 | Y68: =HLOOKUP(F68,Dept_Info!$A$2:$I$3,2,0) -> Marketing | Z68: =IF(Y68="Sales",L68+(L68*$AG$6),L68) -> 788000 | AA68: =IF(J68<700000,"Low",IF(AND(J68>700000,J68<900000),"Medium","High")) -> Medium | AB68: Female | AC68: =INDEX(Emp_Info!$B$1:$G$101,MATCH(HR_Data!$A85,Emp_Info!$B$2:$B$101,0),MATCH(HR_Data!AC$1,Emp_Info!$B$1:$G$1,0)) -> Bachelor | AD68: =INDEX(Emp_Info!$A$1:$G$101,MATCH(HR_Data!$A68,Emp_Info!$B$1:$B$101,0),MATCH(HR_Data!AD$1,Emp_Info!$A$1:$G$1,0)) -> Mumbai | AE68: =INDEX(Emp_Info!$A$1:$G$101,MATCH(HR_Data!$A68,Emp_Info!$B$1:$B$101,0),MATCH(HR_Data!AE$1,Emp_Info!$A$1:$G$1,0)) -> West | AF68: =IF(AND(P68>=3,M68>6),"Eligible","Not Eligible") -> Not Eligible
A69: EMP006 | B69: 33353 | C69: 33 | D69: 43730 | E69: LinkedIn | F69: D_001 | G69: Data Analyst | H69: Full-Time | I69: MGR101 | J69: 720000 | K69: 65000 | L69: =SUM(J69:K69) -> 785000 | M69: 9 | N69: 4.1 | O69: 95.8 | P69: 2 | Q69: Yes | R69: Low | S69: NA | T69: Active | U69: =VLOOKUP(A69,Emp_Info!$B$1:$G$101,3,0) -> anita | V69: =_xlfn.XLOOKUP(A69,Emp_Info!$B$2:$B$101,Emp_Info!$A$2:$A$101,,0) -> desai | W69: =PROPER(_xlfn.CONCAT(U69," ",V69)) -> Anita Desai | X69: =UPPER(_xlfn.CONCAT(LEFT(U69),LEFT(V69),RIGHT(A69,3))) -> AD006 | Y69: =HLOOKUP(F69,Dept_Info!$A$2:$I$3,2,0) -> IT | Z69: =IF(Y69="Sales",L69+(L69*$AG$6),L69) -> 785000 | AA69: =IF(J69<700000,"Low",IF(AND(J69>700000,J69<900000),"Medium","High")) -> Medium | AB69: Female | AC69: =INDEX(Emp_Info!$B$1:$G$101,MATCH(HR_Data!$A57,Emp_Info!$B$2:$B$101,0),MATCH(HR_Data!AC$1,Emp_Info!$B$1:$G$1,0)) -> Bachelor | AD69: =INDEX(Emp_Info!$A$1:$G$101,MATCH(HR_Data!$A69,Emp_Info!$B$1:$B$101,0),MATCH(HR_Data!AD$1,Emp_Info!$A$1:$G$1,0)) -> Mumbai | AE69: =INDEX(Emp_Info!$A$1:$G$101,MATCH(HR_Data!$A69,Emp_Info!$B$1:$B$101,0),MATCH(HR_Data!AE$1,Emp_Info!$A$1:$G$1,0)) -> West | AF69: =IF(AND(P69>=3,M69>6),"Eligible","Not Eligible") -> Not Eligible
A70: EMP028 | B70: 33354 | C70: 33 | D70: 43761 | E70: Job Portal | F70: D_006 | G70: Budget Analyst | H70: Full-Time | I70: MGR103 | J70: 710000 | K70: 65000 | L70: =SUM(J70:K70) -> 775000 | M70: 9 | N70: 4 | O70: 95.7 | P70: 2 | Q70: Yes | R70: Low | S70: NA | T70: Active | U70: =VLOOKUP(A70,Emp_Info!$B$1:$G$101,3,0) -> preeti | V70: =_xlfn.XLOOKUP(A70,Emp_Info!$B$2:$B$101,Emp_Info!$A$2:$A$101,,0) -> mishra | W70: =PROPER(_xlfn.CONCAT(U70," ",V70)) -> Preeti Mishra | X70: =UPPER(_xlfn.CONCAT(LEFT(U70),LEFT(V70),RIGHT(A70,3))) -> PM028 | Y70: =HLOOKUP(F70,Dept_Info!$A$2:$I$3,2,0) -> Finance | Z70: =IF(Y70="Sales",L70+(L70*$AG$6),L70) -> 775000 | AA70: =IF(J70<700000,"Low",IF(AND(J70>700000,J70<900000),"Medium","High")) -> Medium | AB70: Female | AC70: =INDEX(Emp_Info!$B$1:$G$101,MATCH(HR_Data!$A33,Emp_Info!$B$2:$B$101,0),MATCH(HR_Data!AC$1,Emp_Info!$B$1:$G$1,0)) -> Bachelor | AD70: =INDEX(Emp_Info!$A$1:$G$101,MATCH(HR_Data!$A70,Emp_Info!$B$1:$B$101,0),MATCH(HR_Data!AD$1,Emp_Info!$A$1:$G$1,0)) -> Chennai | AE70: =INDEX(Emp_Info!$A$1:$G$101,MATCH(HR_Data!$A70,Emp_Info!$B$1:$B$101,0),MATCH(HR_Data!AE$1,Emp_Info!$A$1:$G$1,0)) -> South | AF70: =IF(AND(P70>=3,M70>6),"Eligible","Not Eligible") -> Not Eligible
A71: EMP098 | B71: 34213 | C71: 31 | D71: 44393 | E71: Job Portal | F71: D_002 | G71: Organizational Development Specialist | H71: Full-Time | I71: MGR102 | J71: 690000 | K71: 64000 | L71: =SUM(J71:K71) -> 754000 | M71: 6 | N71: 4.1 | O71: 96.4 | P71: 2 | Q71: Yes | R71: Low | S71: NA | T71: Active | U71: =VLOOKUP(A71,Emp_Info!$B$1:$G$101,3,0) -> tara | V71: =_xlfn.XLOOKUP(A71,Emp_Info!$B$2:$B$101,Emp_Info!$A$2:$A$101,,0) -> desai | W71: =PROPER(_xlfn.CONCAT(U71," ",V71)) -> Tara Desai | X71: =UPPER(_xlfn.CONCAT(LEFT(U71),LEFT(V71),RIGHT(A71,3))) -> TD098 | Y71: =HLOOKUP(F71,Dept_Info!$A$2:$I$3,2,0) -> HR | Z71: =IF(Y71="Sales",L71+(L71*$AG$6),L71) -> 754000 | AA71: =IF(J71<700000,"Low",IF(AND(J71>700000,J71<900000),"Medium","High")) -> Low | AB71: Female | AC71: =INDEX(Emp_Info!$B$1:$G$101,MATCH(HR_Data!$A44,Emp_Info!$B$2:$B$101,0),MATCH(HR_Data!AC$1,Emp_Info!$B$1:$G$1,0)) -> Master | AD71: =INDEX(Emp_Info!$A$1:$G$101,MATCH(HR_Data!$A71,Emp_Info!$B$1:$B$101,0),MATCH(HR_Data!AD$1,Emp_Info!$A$1:$G$1,0)) -> Chennai | AE71: =INDEX(Emp_Info!$A$1:$G$101,MATCH(HR_Data!$A71,Emp_Info!$B$1:$B$101,0),MATCH(HR_Data!AE$1,Emp_Info!$A$1:$G$1,0)) -> South | AF71: =IF(AND(P71>=3,M71>6),"Eligible","Not Eligible") -> Not Eligible
A72: EMP044 | B72: 33511 | C72: 33 | D72: 43762 | E72: Referral | F72: D_002 | G72: HRIS Specialist | H72: Full-Time | I72: MGR102 | J72: 690000 | K72: 62000 | L72: =SUM(J72:K72) -> 752000 | M72: 9 | N72: 4.1 | O72: 96.3 | P72: 2 | Q72: Yes | R72: Low | S72: NA | T72: Active | U72: =VLOOKUP(A72,Emp_Info!$B$1:$G$101,3,0) -> priyanka | V72: =_xlfn.XLOOKUP(A72,Emp_Info!$B$2:$B$101,Emp_Info!$A$2:$A$101,,0) -> gupta | W72: =PROPER(_xlfn.CONCAT(U72," ",V72)) -> Priyanka Gupta | X72: =UPPER(_xlfn.CONCAT(LEFT(U72),LEFT(V72),RIGHT(A72,3))) -> PG044 | Y72: =HLOOKUP(F72,Dept_Info!$A$2:$I$3,2,0) -> HR | Z72: =IF(Y72="Sales",L72+(L72*$AG$6),L72) -> 752000 | AA72: =IF(J72<700000,"Low",IF(AND(J72>700000,J72<900000),"Medium","High")) -> Low | AB72: Female | AC72: =INDEX(Emp_Info!$B$1:$G$101,MATCH(HR_Data!$A36,Emp_Info!$B$2:$B$101,0),MATCH(HR_Data!AC$1,Emp_Info!$B$1:$G$1,0)) -> Master | AD72: =INDEX(Emp_Info!$A$1:$G$101,MATCH(HR_Data!$A72,Emp_Info!$B$1:$B$101,0),MATCH(HR_Data!AD$1,Emp_Info!$A$1:$G$1,0)) -> Bangalore | AE72: =INDEX(Emp_Info!$A$1:$G$101,MATCH(HR_Data!$A72,Emp_Info!$B$1:$B$101,0),MATCH(HR_Data!AE$1,Emp_Info!$A$1:$G$1,0)) -> South | AF72: =IF(AND(P72>=3,M72>6),"Eligible","Not Eligible") -> Not Eligible
A73: EMP012 | B73: 33377 | C73: 33 | D73: 43565 | E73: Referral | F73: D_005 | G73: Supply Chain Analyst | H73: Full-Time | I73: MGR105 | J73: 690000 | K73: 62000 | L73: =SUM(J73:K73) -> 752000 | M73: 9 | N73: 3.7 | O73: 92.8 | P73: 1 | Q73: No | R73: High | S73: NA | T73: Active | U73: =VLOOKUP(A73,Emp_Info!$B$1:$G$101,3,0) -> pooja | V73: =_xlfn.XLOOKUP(A73,Emp_Info!$B$2:$B$101,Emp_Info!$A$2:$A$101,,0) -> kapoor | W73: =PROPER(_xlfn.CONCAT(U73," ",V73)) -> Pooja Kapoor | X73: =UPPER(_xlfn.CONCAT(LEFT(U73),LEFT(V73),RIGHT(A73,3))) -> PK012 | Y73: =HLOOKUP(F73,Dept_Info!$A$2:$I$3,2,0) -> Marketing | Z73: =IF(Y73="Sales",L73+(L73*$AG$6),L73) -> 752000 | AA73: =IF(J73<700000,"Low",IF(AND(J73>700000,J73<900000),"Medium","High")) -> Low | AB73: Female | AC73: =INDEX(Emp_Info!$B$1:$G$101,MATCH(HR_Data!$A82,Emp_Info!$B$2:$B$101,0),MATCH(HR_Data!AC$1,Emp_Info!$B$1:$G$1,0)) -> Master | AD73: =INDEX(Emp_Info!$A$1:$G$101,MATCH(HR_Data!$A73,Emp_Info!$B$1:$B$101,0),MATCH(HR_Data!AD$1,Emp_Info!$A$1:$G$1,0)) -> Pune | AE73: =INDEX(Emp_Info!$A$1:$G$101,MATCH(HR_Data!$A73,Emp_Info!$B$1:$B$101,0),MATCH(HR_Data!AE$1,Emp_Info!$A$1:$G$1,0)) -> West | AF73: =IF(AND(P73>=3,M73>6),"Eligible","Not Eligible") -> Not Eligible
A74: EMP074 | B74: 34492 | C74: 30 | D74: 44796 | E74: Freelance | F74: D_001 | G74: Mobile App Developer | H74: Full-Time | I74: MGR101 | J74: 680000 | K74: 62000 | L74: =SUM(J74:K74) -> 742000 | M74: 5 | N74: 4 | O74: 95.2 | P74: 2 | Q74: Yes | R74: Low | S74: NA | T74: Active | U74: =VLOOKUP(A74,Emp_Info!$B$1:$G$101,3,0) -> jyoti | V74: =_xlfn.XLOOKUP(A74,Emp_Info!$B$2:$B$101,Emp_Info!$A$2:$A$101,,0) -> agarwal | W74: =PROPER(_xlfn.CONCAT(U74," ",V74)) -> Jyoti Agarwal | X74: =UPPER(_xlfn.CONCAT(LEFT(U74),LEFT(V74),RIGHT(A74,3))) -> JA074 | Y74: =HLOOKUP(F74,Dept_Info!$A$2:$I$3,2,0) -> IT | Z74: =IF(Y74="Sales",L74+(L74*$AG$6),L74) -> 742000 | AA74: =IF(J74<700000,"Low",IF(AND(J74>700000,J74<900000),"Medium","High")) -> Low | AB74: Female | AC74: =INDEX(Emp_Info!$B$1:$G$101,MATCH(HR_Data!$A65,Emp_Info!$B$2:$B$101,0),MATCH(HR_Data!AC$1,Emp_Info!$B$1:$G$1,0)) -> Bachelor | AD74: =INDEX(Emp_Info!$A$1:$G$101,MATCH(HR_Data!$A74,Emp_Info!$B$1:$B$101,0),MATCH(HR_Data!AD$1,Emp_Info!$A$1:$G$1,0)) -> Noida | AE74: =INDEX(Emp_Info!$A$1:$G$101,MATCH(HR_Data!$A74,Emp_Info!$B$1:$B$101,0),MATCH(HR_Data!AE$1,Emp_Info!$A$1:$G$1,0)) -> North | AF74: =IF(AND(P74>=3,M74>6),"Eligible","Not Eligible") -> Not Eligible
A75: EMP021 | B75: 32552 | C75: 35 | D75: 43248 | E75: Referral | F75: D_006 | G75: Accountant | H75: Full-Time | I75: MGR103 | J75: 680000 | K75: 60000 | L75: =SUM(J75:K75) -> 740000 | M75: 11 | N75: 3.8 | O75: 93.9 | P75: 1 | Q75: No | R75: Medium | S75: NA | T75: Active | U75: =VLOOKUP(A75,Emp_Info!$B$1:$G$101,3,0) -> rohit | V75: =_xlfn.XLOOKUP(A75,Emp_Info!$B$2:$B$101,Emp_Info!$A$2:$A$101,,0) -> agarwal | W75: =PROPER(_xlfn.CONCAT(U75," ",V75)) -> Rohit Agarwal | X75: =UPPER(_xlfn.CONCAT(LEFT(U75),LEFT(V75),RIGHT(A75,3))) -> RA021 | Y75: =HLOOKUP(F75,Dept_Info!$A$2:$I$3,2,0) -> Finance | Z75: =IF(Y75="Sales",L75+(L75*$AG$6),L75) -> 740000 | AA75: =IF(J75<700000,"Low",IF(AND(J75>700000,J75<900000),"Medium","High")) -> Low | AB75: Male | AC75: =INDEX(Emp_Info!$B$1:$G$101,MATCH(HR_Data!$A31,Emp_Info!$B$2:$B$101,0),MATCH(HR_Data!AC$1,Emp_Info!$B$1:$G$1,0)) -> Master | AD75: =INDEX(Emp_Info!$A$1:$G$101,MATCH(HR_Data!$A75,Emp_Info!$B$1:$B$101,0),MATCH(HR_Data!AD$1,Emp_Info!$A$1:$G$1,0)) -> Mumbai | AE75: =INDEX(Emp_Info!$A$1:$G$101,MATCH(HR_Data!$A75,Emp_Info!$B$1:$B$101,0),MATCH(HR_Data!AE$1,Emp_Info!$A$1:$G$1,0)) -> West | AF75: =IF(AND(P75>=3,M75>6),"Eligible","Not Eligible") -> Not Eligible
A76: EMP040 | B76: 33954 | C76: 32 | D76: 44265 | E76: Job Portal | F76: D_005 | G76: Procurement Specialist | H76: Full-Time | I76: MGR105 | J76: 670000 | K76: 60000 | L76: =SUM(J76:K76) -> 730000 | M76: 7 | N76: 3.9 | O76: 95 | P76: 1 | Q76: Yes | R76: Medium | S76: NA | T76: Active | U76: =VLOOKUP(A76,Emp_Info!$B$1:$G$101,3,0) -> madhuri | V76: =_xlfn.XLOOKUP(A76,Emp_Info!$B$2:$B$101,Emp_Info!$A$2:$A$101,,0) -> joshi | W76: =PROPER(_xlfn.CONCAT(U76," ",V76)) -> Madhuri Joshi | X76: =UPPER(_xlfn.CONCAT(LEFT(U76),LEFT(V76),RIGHT(A76,3))) -> MJ040 | Y76: =HLOOKUP(F76,Dept_Info!$A$2:$I$3,2,0) -> Marketing | Z76: =IF(Y76="Sales",L76+(L76*$AG$6),L76) -> 730000 | AA76: =IF(J76<700000,"Low",IF(AND(J76>700000,J76<900000),"Medium","High")) -> Low | AB76: Female | AC76: =INDEX(Emp_Info!$B$1:$G$101,MATCH(HR_Data!$A84,Emp_Info!$B$2:$B$101,0),MATCH(HR_Data!AC$1,Emp_Info!$B$1:$G$1,0)) -> Bachelor | AD76: =INDEX(Emp_Info!$A$1:$G$101,MATCH(HR_Data!$A76,Emp_Info!$B$1:$B$101,0),MATCH(HR_Data!AD$1,Emp_Info!$A$1:$G$1,0)) -> Hyderabad | AE76: =INDEX(Emp_Info!$A$1:$G$101,MATCH(HR_Data!$A76,Emp_Info!$B$1:$B$101,0),MATCH(HR_Data!AE$1,Emp_Info!$A$1:$G$1,0)) -> South | AF76: =IF(AND(P76>=3,M76>6),"Eligible","Not Eligible") -> Not Eligible
A77: EMP084 | B77: 34312 | C77: 31 | D77: 44666 | E77: Referral | F77: D_004 | G77: Affiliate Marketing Manager | H77: Full-Time | I77: MGR104 | J77: 650000 | K77: 58000 | L77: =SUM(J77:K77) -> 708000 | M77: 6 | N77: 3.9 | O77: 94.9 | P77: 1 | Q77: Yes | R77: Medium | S77: NA | T77: Active | U77: =VLOOKUP(A77,Emp_Info!$B$1:$G$101,3,0) -> riya | V77: =_xlfn.XLOOKUP(A77,Emp_Info!$B$2:$B$101,Emp_Info!$A$2:$A$101,,0) -> jain | W77: =PROPER(_xlfn.CONCAT(U77," ",V77)) -> Riya Jain | X77: =UPPER(_xlfn.CONCAT(LEFT(U77),LEFT(V77),RIGHT(A77,3))) -> RJ084 | Y77: =HLOOKUP(F77,Dept_Info!$A$2:$I$3,2,0) -> Admin | Z77: =IF(Y77="Sales",L77+(L77*$AG$6),L77) -> 708000 | AA77: =IF(J77<700000,"Low",IF(AND(J77>700000,J77<900000),"Medium","High")) -> Low | AB77: Female | AC77: =INDEX(Emp_Info!$B$1:$G$101,MATCH(HR_Data!$A12,Emp_Info!$B$2:$B$101,0),MATCH(HR_Data!AC$1,Emp_Info!$B$1:$G$1,0)) -> Master | AD77: =INDEX(Emp_Info!$A$1:$G$101,MATCH(HR_Data!$A77,Emp_Info!$B$1:$B$101,0),MATCH(HR_Data!AD$1,Emp_Info!$A$1:$G$1,0)) -> Pune | AE77: =INDEX(Emp_Info!$A$1:$G$101,MATCH(HR_Data!$A77,Emp_Info!$B$1:$B$101,0),MATCH(HR_Data!AE$1,Emp_Info!$A$1:$G$1,0)) -> West | AF77: =IF(AND(P77>=3,M77>6),"Eligible","Not Eligible") -> Not Eligible
A78: EMP004 | B78: 33852 | C78: 32 | D78: 43902 | E78: Job Portal | F78: D_004 | G78: Marketing Executive | H78: Full-Time | I78: MGR104 | J78: 650000 | K78: 55000 | L78: =SUM(J78:K78) -> 705000 | M78: 8 | N78: 4 | O78: 97.1 | P78: 2 | Q78: Yes | R78: Low | S78: NA | T78: Active | U78: =VLOOKUP(A78,Emp_Info!$B$1:$G$101,3,0) -> sneha | V78: =_xlfn.XLOOKUP(A78,Emp_Info!$B$2:$B$101,Emp_Info!$A$2:$A$101,,0) -> reddy | W78: =PROPER(_xlfn.CONCAT(U78," ",V78)) -> Sneha Reddy | X78: =UPPER(_xlfn.CONCAT(LEFT(U78),LEFT(V78),RIGHT(A78,3))) -> SR004 | Y78: =HLOOKUP(F78,Dept_Info!$A$2:$I$3,2,0) -> Admin | Z78: =IF(Y78="Sales",L78+(L78*$AG$6),L78) -> 705000 | AA78: =IF(J78<700000,"Low",IF(AND(J78>700000,J78<900000),"Medium","High")) -> Low | AB78: Female | AC78: =INDEX(Emp_Info!$B$1:$G$101,MATCH(HR_Data!$A5,Emp_Info!$B$2:$B$101,0),MATCH(HR_Data!AC$1,Emp_Info!$B$1:$G$1,0)) -> Bachelor | AD78: =INDEX(Emp_Info!$A$1:$G$101,MATCH(HR_Data!$A78,Emp_Info!$B$1:$B$101,0),MATCH(HR_Data!AD$1,Emp_Info!$A$1:$G$1,0)) -> Hyderabad | AE78: =INDEX(Emp_Info!$A$1:$G$101,MATCH(HR_Data!$A78,Emp_Info!$B$1:$B$101,0),MATCH(HR_Data!AE$1,Emp_Info!$A$1:$G$1,0)) -> South | AF78: =IF(AND(P78>=3,M78>6),"Eligible","Not Eligible") -> Not Eligible
A79: EMP070 | B79: 34228 | C79: 31 | D79: 44544 | E79: Referral | F79: D_002 | G79: Learning & Development Specialist | H79: Full-Time | I79: MGR102 | J79: 640000 | K79: 58000 | L79: =SUM(J79:K79) -> 698000 | M79: 6 | N79: 4.1 | O79: 96.1 | P79: 2 | Q79: Yes | R79: Low | S79: NA | T79: Active | U79: =VLOOKUP(A79,Emp_Info!$B$1:$G$101,3,0) -> smita | V79: =_xlfn.XLOOKUP(A79,Emp_Info!$B$2:$B$101,Emp_Info!$A$2:$A$101,,0) -> joshi | W79: =PROPER(_xlfn.CONCAT(U79," ",V79)) -> Smita Joshi | X79: =UPPER(_xlfn.CONCAT(LEFT(U79),LEFT(V79),RIGHT(A79,3))) -> SJ070 | Y79: =HLOOKUP(F79,Dept_Info!$A$2:$I$3,2,0) -> HR | Z79: =IF(Y79="Sales",L79+(L79*$AG$6),L79) -> 698000 | AA79: =IF(J79<700000,"Low",IF(AND(J79>700000,J79<900000),"Medium","High")) -> Low | AB79: Female | AC79: =INDEX(Emp_Info!$B$1:$G$101,MATCH(HR_Data!$A43,Emp_Info!$B$2:$B$101,0),MATCH(HR_Data!AC$1,Emp_Info!$B$1:$G$1,0)) -> Bachelor | AD79: =INDEX(Emp_Info!$A$1:$G$101,MATCH(HR_Data!$A79,Emp_Info!$B$1:$B$101,0),MATCH(HR_Data!AD$1,Emp_Info!$A$1:$G$1,0)) -> Mumbai | AE79: =INDEX(Emp_Info!$A$1:$G$101,MATCH(HR_Data!$A79,Emp_Info!$B$1:$B$101,0),MATCH(HR_Data!AE$1,Emp_Info!$A$1:$G$1,0)) -> West | AF79: =IF(AND(P79>=3,M79>6),"Eligible","Not Eligible") -> Not Eligible
A80: EMP020 | B80: 33395 | C80: 33 | D80: 43788 | E80: LinkedIn | F80: D_003 | G80: Sales Executive | H80: Full-Time | I80: MGR106 | J80: 620000 | K80: 58000 | L80: =SUM(J80:K80) -> 678000 | M80: 8 | N80: 3.9 | O80: 94.7 | P80: 1 | Q80: Yes | R80: Medium | S80: NA | T80: Active | U80: =VLOOKUP(A80,Emp_Info!$B$1:$G$101,3,0) -> divya | V80: =_xlfn.XLOOKUP(A80,Emp_Info!$B$2:$B$101,Emp_Info!$A$2:$A$101,,0) -> menon | W80: =PROPER(_xlfn.CONCAT(U80," ",V80)) -> Divya Menon | X80: =UPPER(_xlfn.CONCAT(LEFT(U80),LEFT(V80),RIGHT(A80,3))) -> DM020 | Y80: =HLOOKUP(F80,Dept_Info!$A$2:$I$3,2,0) -> Sales | Z80: =IF(Y80="Sales",L80+(L80*$AG$6),L80) -> 779700 | AA80: =IF(J80<700000,"Low",IF(AND(J80>700000,J80<900000),"Medium","High")) -> Low | AB80: F | AC80: =INDEX(Emp_Info!$B$1:$G$101,MATCH(HR_Data!$A99,Emp_Info!$B$2:$B$101,0),MATCH(HR_Data!AC$1,Emp_Info!$B$1:$G$1,0)) -> Master | AD80: =INDEX(Emp_Info!$A$1:$G$101,MATCH(HR_Data!$A80,Emp_Info!$B$1:$B$101,0),MATCH(HR_Data!AD$1,Emp_Info!$A$1:$G$1,0)) -> Bangalore | AE80: =INDEX(Emp_Info!$A$1:$G$101,MATCH(HR_Data!$A80,Emp_Info!$B$1:$B$101,0),MATCH(HR_Data!AE$1,Emp_Info!$A$1:$G$1,0)) -> South | AF80: =IF(AND(P80>=3,M80>6),"Eligible","Not Eligible") -> Not Eligible
A81: EMP026 | B81: 34091 | C81: 31 | D81: 44391 | E81: Freelance | F81: D_002 | G81: Compensation Analyst | H81: Full-Time | I81: MGR102 | J81: 620000 | K81: 55000 | L81: =SUM(J81:K81) -> 675000 | M81: 6 | N81: 3.9 | O81: 94.5 | P81: 1 | Q81: Yes | R81: Medium | S81: NA | T81: Active | U81: =VLOOKUP(A81,Emp_Info!$B$1:$G$101,3,0) -> nisha | V81: =_xlfn.XLOOKUP(A81,Emp_Info!$B$2:$B$101,Emp_Info!$A$2:$A$101,,0) -> yadav | W81: =PROPER(_xlfn.CONCAT(U81," ",V81)) -> Nisha Yadav | X81: =UPPER(_xlfn.CONCAT(LEFT(U81),LEFT(V81),RIGHT(A81,3))) -> NY026 | Y81: =HLOOKUP(F81,Dept_Info!$A$2:$I$3,2,0) -> HR | Z81: =IF(Y81="Sales",L81+(L81*$AG$6),L81) -> 675000 | AA81: =IF(J81<700000,"Low",IF(AND(J81>700000,J81<900000),"Medium","High")) -> Low | AB81: Female | AC81: =INDEX(Emp_Info!$B$1:$G$101,MATCH(HR_Data!$A41,Emp_Info!$B$2:$B$101,0),MATCH(HR_Data!AC$1,Emp_Info!$B$1:$G$1,0)) -> Master | AD81: =INDEX(Emp_Info!$A$1:$G$101,MATCH(HR_Data!$A81,Emp_Info!$B$1:$B$101,0),MATCH(HR_Data!AD$1,Emp_Info!$A$1:$G$1,0)) -> Noida | AE81: =INDEX(Emp_Info!$A$1:$G$101,MATCH(HR_Data!$A81,Emp_Info!$B$1:$B$101,0),MATCH(HR_Data!AE$1,Emp_Info!$A$1:$G$1,0)) -> North | AF81: =IF(AND(P81>=3,M81>6),"Eligible","Not Eligible") -> Not Eligible
A82: EMP100 | B82: 34785 | C82: 29 | D82: 44950 | E82: Referral | F82: D_001 | G82: Frontend Developer | H82: Full-Time | I82: MGR101 | J82: 620000 | K82: 55000 | L82: =SUM(J82:K82) -> 675000 | M82: 4 | N82: 3.9 | O82: 94.3 | P82: 2 | Q82: Yes | R82: Medium | S82: NA | T82: Active | U82: =VLOOKUP(A82,Emp_Info!$B$1:$G$101,3,0) -> prachi | V82: =_xlfn.XLOOKUP(A82,Emp_Info!$B$2:$B$101,Emp_Info!$A$2:$A$101,,0) -> kulkarni | W82: =PROPER(_xlfn.CONCAT(U82," ",V82)) -> Prachi Kulkarni | X82: =UPPER(_xlfn.CONCAT(LEFT(U82),LEFT(V82),RIGHT(A82,3))) -> PK100 | Y82: =HLOOKUP(F82,Dept_Info!$A$2:$I$3,2,0) -> IT | Z82: =IF(Y82="Sales",L82+(L82*$AG$6),L82) -> 675000 | AA82: =IF(J82<700000,"Low",IF(AND(J82>700000,J82<900000),"Medium","High")) -> Low | AB82: Female | AC82: =INDEX(Emp_Info!$B$1:$G$101,MATCH(HR_Data!$A69,Emp_Info!$B$2:$B$101,0),MATCH(HR_Data!AC$1,Emp_Info!$B$1:$G$1,0)) -> Master | AD82: =INDEX(Emp_Info!$A$1:$G$101,MATCH(HR_Data!$A82,Emp_Info!$B$1:$B$101,0),MATCH(HR_Data!AD$1,Emp_Info!$A$1:$G$1,0)) -> Mumbai | AE82: =INDEX(Emp_Info!$A$1:$G$101,MATCH(HR_Data!$A82,Emp_Info!$B$1:$B$101,0),MATCH(HR_Data!AE$1,Emp_Info!$A$1:$G$1,0)) -> West | AF82: =IF(AND(P82>=3,M82>6),"Eligible","Not Eligible") -> Not Eligible
A83: EMP062 | B83: 34068 | C83: 31 | D83: 44585 | E83: Job Portal | F83: D_002 | G83: Benefits Administrator | H83: Full-Time | I83: MGR102 | J83: 590000 | K83: 52000 | L83: =SUM(J83:K83) -> 642000 | M83: 6 | N83: 3.9 | O83: 94.6 | P83: 1 | Q83: Yes | R83: Medium | S83: NA | T83: Active | U83: =VLOOKUP(A83,Emp_Info!$B$1:$G$101,3,0) -> poornima | V83: =_xlfn.XLOOKUP(A83,Emp_Info!$B$2:$B$101,Emp_Info!$A$2:$A$101,,0) -> rao | W83: =PROPER(_xlfn.CONCAT(U83," ",V83)) -> Poornima Rao | X83: =UPPER(_xlfn.CONCAT(LEFT(U83),LEFT(V83),RIGHT(A83,3))) -> PR062 | Y83: =HLOOKUP(F83,Dept_Info!$A$2:$I$3,2,0) -> HR | Z83: =IF(Y83="Sales",L83+(L83*$AG$6),L83) -> 642000 | AA83: =IF(J83<700000,"Low",IF(AND(J83>700000,J83<900000),"Medium","High")) -> Low | AB83: Female | AC83: =INDEX(Emp_Info!$B$1:$G$101,MATCH(HR_Data!$A42,Emp_Info!$B$2:$B$101,0),MATCH(HR_Data!AC$1,Emp_Info!$B$1:$G$1,0)) -> Bachelor | AD83: =INDEX(Emp_Info!$A$1:$G$101,MATCH(HR_Data!$A83,Emp_Info!$B$1:$B$101,0),MATCH(HR_Data!AD$1,Emp_Info!$A$1:$G$1,0)) -> Bangalore | AE83: =INDEX(Emp_Info!$A$1:$G$101,MATCH(HR_Data!$A83,Emp_Info!$B$1:$B$101,0),MATCH(HR_Data!AE$1,Emp_Info!$A$1:$G$1,0)) -> South | AF83: =IF(AND(P83>=3,M83>6),"Eligible","Not Eligible") -> Not Eligible
A84: EMP022 | B84: 34631 | C84: 30 | D84: 44820 | E84: Job Portal | F84: D_001 | G84: QA Engineer | H84: Full-Time | I84: MGR101 | J84: 590000 | K84: 52000 | L84: =SUM(J84:K84) -> 642000 | M84: 5 | N84: 4 | O84: 95.3 | P84: 2 | Q84: Yes | R84: Low | S84: NA | T84: Active | U84: =VLOOKUP(A84,Emp_Info!$B$1:$G$101,3,0) -> swati | V84: =_xlfn.XLOOKUP(A84,Emp_Info!$B$2:$B$101,Emp_Info!$A$2:$A$101,,0) -> kulkarni | W84: =PROPER(_xlfn.CONCAT(U84," ",V84)) -> Swati Kulkarni | X84: =UPPER(_xlfn.CONCAT(LEFT(U84),LEFT(V84),RIGHT(A84,3))) -> SK022 | Y84: =HLOOKUP(F84,Dept_Info!$A$2:$I$3,2,0) -> IT | Z84: =IF(Y84="Sales",L84+(L84*$AG$6),L84) -> 642000 | AA84: =IF(J84<700000,"Low",IF(AND(J84>700000,J84<900000),"Medium","High")) -> Low | AB84: Female | AC84: =INDEX(Emp_Info!$B$1:$G$101,MATCH(HR_Data!$A64,Emp_Info!$B$2:$B$101,0),MATCH(HR_Data!AC$1,Emp_Info!$B$1:$G$1,0)) -> Bachelor | AD84: =INDEX(Emp_Info!$A$1:$G$101,MATCH(HR_Data!$A84,Emp_Info!$B$1:$B$101,0),MATCH(HR_Data!AD$1,Emp_Info!$A$1:$G$1,0)) -> Pune | AE84: =INDEX(Emp_Info!$A$1:$G$101,MATCH(HR_Data!$A84,Emp_Info!$B$1:$B$101,0),MATCH(HR_Data!AE$1,Emp_Info!$A$1:$G$1,0)) -> West | AF84: =IF(AND(P84>=3,M84>6),"Eligible","Not Eligible") -> Not Eligible
A85: EMP056 | B85: 33620 | C85: 32 | D85: 44040 | E85: Referral | F85: D_003 | G85: Sales Coordinator | H85: Full-Time | I85: MGR106 | J85: 580000 | K85: 52000 | L85: =SUM(J85:K85) -> 632000 | M85: 8 | N85: 3.8 | O85: 93.9 | P85: 1 | Q85: Yes | R85: Medium | S85: NA | T85: Active | U85: =VLOOKUP(A85,Emp_Info!$B$1:$G$101,3,0) -> ananya | V85: =_xlfn.XLOOKUP(A85,Emp_Info!$B$2:$B$101,Emp_Info!$A$2:$A$101,,0) -> desai | W85: =PROPER(_xlfn.CONCAT(U85," ",V85)) -> Ananya Desai | X85: =UPPER(_xlfn.CONCAT(LEFT(U85),LEFT(V85),RIGHT(A85,3))) -> AD056 | Y85: =HLOOKUP(F85,Dept_Info!$A$2:$I$3,2,0) -> Sales | Z85: =IF(Y85="Sales",L85+(L85*$AG$6),L85) -> 726800 | AA85: =IF(J85<700000,"Low",IF(AND(J85>700000,J85<900000),"Medium","High")) -> Low | AB85: Female | AC85: =INDEX(Emp_Info!$B$1:$G$101,MATCH(HR_Data!$A100,Emp_Info!$B$2:$B$101,0),MATCH(HR_Data!AC$1,Emp_Info!$B$1:$G$1,0)) -> Master | AD85: =INDEX(Emp_Info!$A$1:$G$101,MATCH(HR_Data!$A85,Emp_Info!$B$1:$B$101,0),MATCH(HR_Data!AD$1,Emp_Info!$A$1:$G$1,0)) -> Bangalore | AE85: =INDEX(Emp_Info!$A$1:$G$101,MATCH(HR_Data!$A85,Emp_Info!$B$1:$B$101,0),MATCH(HR_Data!AE$1,Emp_Info!$A$1:$G$1,0)) -> South | AF85: =IF(AND(P85>=3,M85>6),"Eligible","Not Eligible") -> Not Eligible
A86: EMP016 | B86: 33959 | C86: 32 | D86: 44000 | E86: Freelance | F86: D_002 | G86: Training Coordinator | H86: Full-Time | I86: MGR102 | J86: 580000 | K86: 50000 | L86: =SUM(J86:K86) -> 630000 | M86: 7 | N86: 4.1 | O86: 97.5 | P86: 2 | Q86: Yes | R86: Low | S86: NA | T86: Active | U86: =VLOOKUP(A86,Emp_Info!$B$1:$G$101,3,0) -> ritu | V86: =_xlfn.XLOOKUP(A86,Emp_Info!$B$2:$B$101,Emp_Info!$A$2:$A$101,,0) -> saxena | W86: =PROPER(_xlfn.CONCAT(U86," ",V86)) -> Ritu Saxena | X86: =UPPER(_xlfn.CONCAT(LEFT(U86),LEFT(V86),RIGHT(A86,3))) -> RS016 | Y86: =HLOOKUP(F86,Dept_Info!$A$2:$I$3,2,0) -> HR | Z86: =IF(Y86="Sales",L86+(L86*$AG$6),L86) -> 630000 | AA86: =IF(J86<700000,"Low",IF(AND(J86>700000,J86<900000),"Medium","High")) -> Low | AB86: F | AC86: =INDEX(Emp_Info!$B$1:$G$101,MATCH(HR_Data!$A39,Emp_Info!$B$2:$B$101,0),MATCH(HR_Data!AC$1,Emp_Info!$B$1:$G$1,0)) -> Bachelor | AD86: =INDEX(Emp_Info!$A$1:$G$101,MATCH(HR_Data!$A86,Emp_Info!$B$1:$B$101,0),MATCH(HR_Data!AD$1,Emp_Info!$A$1:$G$1,0)) -> Mumbai | AE86: =INDEX(Emp_Info!$A$1:$G$101,MATCH(HR_Data!$A86,Emp_Info!$B$1:$B$101,0),MATCH(HR_Data!AE$1,Emp_Info!$A$1:$G$1,0)) -> West | AF86: =IF(AND(P86>=3,M86>6),"Eligible","Not Eligible") -> Not Eligible
A87: EMP042 | B87: 34553 | C87: 30 | D87: 44741 | E87: Job Portal | F87: D_004 | G87: Market Research Analyst | H87: Full-Time | I87: MGR104 | J87: 580000 | K87: 50000 | L87: =SUM(J87:K87) -> 630000 | M87: 5 | N87: 4 | O87: 95.5 | P87: 1 | Q87: Yes | R87: Low | S87: NA | T87: Active | U87: =VLOOKUP(A87,Emp_Info!$B$1:$G$101,3,0) -> sonali | V87: =_xlfn.XLOOKUP(A87,Emp_Info!$B$2:$B$101,Emp_Info!$A$2:$A$101,,0) -> patil | W87: =PROPER(_xlfn.CONCAT(U87," ",V87)) -> Sonali Patil | X87: =UPPER(_xlfn.CONCAT(LEFT(U87),LEFT(V87),RIGHT(A87,3))) -> SP042 | Y87: =HLOOKUP(F87,Dept_Info!$A$2:$I$3,2,0) -> Admin | Z87: =IF(Y87="Sales",L87+(L87*$AG$6),L87) -> 630000 | AA87: =IF(J87<700000,"Low",IF(AND(J87>700000,J87<900000),"Medium","High")) -> Low | AB87: Female | AC87: =INDEX(Emp_Info!$B$1:$G$101,MATCH(HR_Data!$A14,Emp_Info!$B$2:$B$101,0),MATCH(HR_Data!AC$1,Emp_Info!$B$1:$G$1,0)) -> Bachelor | AD87: =INDEX(Emp_Info!$A$1:$G$101,MATCH(HR_Data!$A87,Emp_Info!$B$1:$B$101,0),MATCH(HR_Data!AD$1,Emp_Info!$A$1:$G$1,0)) -> Pune | AE87: =INDEX(Emp_Info!$A$1:$G$101,MATCH(HR_Data!$A87,Emp_Info!$B$1:$B$101,0),MATCH(HR_Data!AE$1,Emp_Info!$A$1:$G$1,0)) -> West | AF87: =IF(AND(P87>=3,M87>6),"Eligible","Not Eligible") -> Not Eligible
A88: EMP010 | B88: 34619 | C88: 30 | D88: 44793 | E88: Job Portal | F88: D_004 | G88: Digital Marketing Specialist | H88: Full-Time | I88: MGR104 | J88: 580000 | K88: 48000 | L88: =SUM(J88:K88) -> 628000 | M88: 5 | N88: 4 | O88: 96.2 | P88: 2 | Q88: Yes | R88: Low | S88: NA | T88: Active | U88: =VLOOKUP(A88,Emp_Info!$B$1:$G$101,3,0) -> deepa | V88: =_xlfn.XLOOKUP(A88,Emp_Info!$B$2:$B$101,Emp_Info!$A$2:$A$101,,0) -> iyer | W88: =PROPER(_xlfn.CONCAT(U88," ",V88)) -> Deepa Iyer | X88: =UPPER(_xlfn.CONCAT(LEFT(U88),LEFT(V88),RIGHT(A88,3))) -> DI010 | Y88: =HLOOKUP(F88,Dept_Info!$A$2:$I$3,2,0) -> Admin | Z88: =IF(Y88="Sales",L88+(L88*$AG$6),L88) -> 628000 | AA88: =IF(J88<700000,"Low",IF(AND(J88>700000,J88<900000),"Medium","High")) -> Low | AB88: Female | AC88: =INDEX(Emp_Info!$B$1:$G$101,MATCH(HR_Data!$A13,Emp_Info!$B$2:$B$101,0),MATCH(HR_Data!AC$1,Emp_Info!$B$1:$G$1,0)) -> Master | AD88: =INDEX(Emp_Info!$A$1:$G$101,MATCH(HR_Data!$A88,Emp_Info!$B$1:$B$101,0),MATCH(HR_Data!AD$1,Emp_Info!$A$1:$G$1,0)) -> Mumbai | AE88: =INDEX(Emp_Info!$A$1:$G$101,MATCH(HR_Data!$A88,Emp_Info!$B$1:$B$101,0),MATCH(HR_Data!AE$1,Emp_Info!$A$1:$G$1,0)) -> West | AF88: =IF(AND(P88>=3,M88>6),"Eligible","Not Eligible") -> Not Eligible
A89: EMP054 | B89: 34447 | C89: 30 | D89: 44829 | E89: Referral | F89: D_004 | G89: SEO Specialist | H89: Full-Time | I89: MGR104 | J89: 560000 | K89: 48000 | L89: =SUM(J89:K89) -> 608000 | M89: 5 | N89: 3.9 | O89: 94.2 | P89: 2 | Q89: Yes | R89: Medium | S89: NA | T89: Active | U89: =VLOOKUP(A89,Emp_Info!$B$1:$G$101,3,0) -> seema | V89: =_xlfn.XLOOKUP(A89,Emp_Info!$B$2:$B$101,Emp_Info!$A$2:$A$101,,0) -> chopra | W89: =PROPER(_xlfn.CONCAT(U89," ",V89)) -> Seema Chopra | X89: =UPPER(_xlfn.CONCAT(LEFT(U89),LEFT(V89),RIGHT(A89,3))) -> SC054 | Y89: =HLOOKUP(F89,Dept_Info!$A$2:$I$3,2,0) -> Admin | Z89: =IF(Y89="Sales",L89+(L89*$AG$6),L89) -> 608000 | AA89: =IF(J89<700000,"Low",IF(AND(J89>700000,J89<900000),"Medium","High")) -> Low | AB89: Female | AC89: =INDEX(Emp_Info!$B$1:$G$101,MATCH(HR_Data!$A15,Emp_Info!$B$2:$B$101,0),MATCH(HR_Data!AC$1,Emp_Info!$B$1:$G$1,0)) -> Bachelor | AD89: =INDEX(Emp_Info!$A$1:$G$101,MATCH(HR_Data!$A89,Emp_Info!$B$1:$B$101,0),MATCH(HR_Data!AD$1,Emp_Info!$A$1:$G$1,0)) -> Pune | AE89: =INDEX(Emp_Info!$A$1:$G$101,MATCH(HR_Data!$A89,Emp_Info!$B$1:$B$101,0),MATCH(HR_Data!AE$1,Emp_Info!$A$1:$G$1,0)) -> West | AF89: =IF(AND(P89>=3,M89>6),"Eligible","Not Eligible") -> Not Eligible
A90: EMP034 | B90: 34339 | C90: 30 | D90: 44800 | E90: Job Portal | F90: D_002 | G90: Employee Relations Specialist | H90: Full-Time | I90: MGR102 | J90: 560000 | K90: 48000 | L90: =SUM(J90:K90) -> 608000 | M90: 5 | N90: 3.9 | O90: 94.8 | P90: 1 | Q90: Yes | R90: Medium | S90: NA | T90: Active | U90: =VLOOKUP(A90,Emp_Info!$B$1:$G$101,3,0) -> isha | V90: =_xlfn.XLOOKUP(A90,Emp_Info!$B$2:$B$101,Emp_Info!$A$2:$A$101,,0) -> khanna | W90: =PROPER(_xlfn.CONCAT(U90," ",V90)) -> Isha Khanna | X90: =UPPER(_xlfn.CONCAT(LEFT(U90),LEFT(V90),RIGHT(A90,3))) -> IK034 | Y90: =HLOOKUP(F90,Dept_Info!$A$2:$I$3,2,0) -> HR | Z90: =IF(Y90="Sales",L90+(L90*$AG$6),L90) -> 608000 | AA90: =IF(J90<700000,"Low",IF(AND(J90>700000,J90<900000),"Medium","High")) -> Low | AB90: Female | AC90: =INDEX(Emp_Info!$B$1:$G$101,MATCH(HR_Data!$A45,Emp_Info!$B$2:$B$101,0),MATCH(HR_Data!AC$1,Emp_Info!$B$1:$G$1,0)) -> Bachelor | AD90: =INDEX(Emp_Info!$A$1:$G$101,MATCH(HR_Data!$A90,Emp_Info!$B$1:$B$101,0),MATCH(HR_Data!AD$1,Emp_Info!$A$1:$G$1,0)) -> Noida | AE90: =INDEX(Emp_Info!$A$1:$G$101,MATCH(HR_Data!$A90,Emp_Info!$B$1:$B$101,0),MATCH(HR_Data!AE$1,Emp_Info!$A$1:$G$1,0)) -> North | AF90: =IF(AND(P90>=3,M90>6),"Eligible","Not Eligible") -> Not Eligible
A91: EMP066 | B91: 34482 | C91: 30 | D91: 44763 | E91: Freelance | F91: D_004 | G91: Graphic Designer | H91: Full-Time | I91: MGR104 | J91: 550000 | K91: 46000 | L91: =SUM(J91:K91) -> 596000 | M91: 5 | N91: 3.8 | O91: 93.8 | P91: 1 | Q91: Yes | R91: Medium | S91: NA | T91: Active | U91: =VLOOKUP(A91,Emp_Info!$B$1:$G$101,3,0) -> lakshmi | V91: =_xlfn.XLOOKUP(A91,Emp_Info!$B$2:$B$101,Emp_Info!$A$2:$A$101,,0) -> menon | W91: =PROPER(_xlfn.CONCAT(U91," ",V91)) -> Lakshmi Menon | X91: =UPPER(_xlfn.CONCAT(LEFT(U91),LEFT(V91),RIGHT(A91,3))) -> LM066 | Y91: =HLOOKUP(F91,Dept_Info!$A$2:$I$3,2,0) -> Admin | Z91: =IF(Y91="Sales",L91+(L91*$AG$6),L91) -> 596000 | AA91: =IF(J91<700000,"Low",IF(AND(J91>700000,J91<900000),"Medium","High")) -> Low | AB91: Female | AC91: =INDEX(Emp_Info!$B$1:$G$101,MATCH(HR_Data!$A16,Emp_Info!$B$2:$B$101,0),MATCH(HR_Data!AC$1,Emp_Info!$B$1:$G$1,0)) -> Bachelor | AD91: =INDEX(Emp_Info!$A$1:$G$101,MATCH(HR_Data!$A91,Emp_Info!$B$1:$B$101,0),MATCH(HR_Data!AD$1,Emp_Info!$A$1:$G$1,0)) -> Chennai | AE91: =INDEX(Emp_Info!$A$1:$G$101,MATCH(HR_Data!$A91,Emp_Info!$B$1:$B$101,0),MATCH(HR_Data!AE$1,Emp_Info!$A$1:$G$1,0)) -> South | AF91: =IF(AND(P91>=3,M91>6),"Eligible","Not Eligible") -> Not Eligible
A92: EMP030 | B92: 34931 | C92: 29 | D92: 44969 | E92: LinkedIn | F92: D_004 | G92: Social Media Manager | H92: Full-Time | I92: MGR104 | J92: 550000 | K92: 45000 | L92: =SUM(J92:K92) -> 595000 | M92: 4 | N92: 3.8 | O92: 93.2 | P92: 1 | Q92: Yes | R92: Medium | S92: NA | T92: Active | U92: =VLOOKUP(A92,Emp_Info!$B$1:$G$101,3,0) -> shweta | V92: =_xlfn.XLOOKUP(A92,Emp_Info!$B$2:$B$101,Emp_Info!$A$2:$A$101,,0) -> bhatt | W92: =PROPER(_xlfn.CONCAT(U92," ",V92)) -> Shweta Bhatt | X92: =UPPER(_xlfn.CONCAT(LEFT(U92),LEFT(V92),RIGHT(A92,3))) -> SB030 | Y92: =HLOOKUP(F92,Dept_Info!$A$2:$I$3,2,0) -> Admin | Z92: =IF(Y92="Sales",L92+(L92*$AG$6),L92) -> 595000 | AA92: =IF(J92<700000,"Low",IF(AND(J92>700000,J92<900000),"Medium","High")) -> Low | AB92: Female | AC92: =INDEX(Emp_Info!$B$1:$G$101,MATCH(HR_Data!$A17,Emp_Info!$B$2:$B$101,0),MATCH(HR_Data!AC$1,Emp_Info!$B$1:$G$1,0)) -> Education_Level | AD92: =INDEX(Emp_Info!$A$1:$G$101,MATCH(HR_Data!$A92,Emp_Info!$B$1:$B$101,0),MATCH(HR_Data!AD$1,Emp_Info!$A$1:$G$1,0)) -> Delhi | AE92: =INDEX(Emp_Info!$A$1:$G$101,MATCH(HR_Data!$A92,Emp_Info!$B$1:$B$101,0),MATCH(HR_Data!AE$1,Emp_Info!$A$1:$G$1,0)) -> North | AF92: =IF(AND(P92>=3,M92>6),"Eligible","Not Eligible") -> Not Eligible
A93: EMP046 | B93: 34875 | C93: 29 | D93: 44939 | E93: Campus | F93: D_001 | G93: UI/UX Designer | H93: Full-Time | I93: MGR101 | J93: 540000 | K93: 42000 | L93: =SUM(J93:K93) -> 582000 | M93: 4 | N93: 3.8 | O93: 93.7 | P93: 1 | Q93: Yes | R93: Medium | S93: NA | T93: Active | U93: =VLOOKUP(A93,Emp_Info!$B$1:$G$101,3,0) -> shruti | V93: =_xlfn.XLOOKUP(A93,Emp_Info!$B$2:$B$101,Emp_Info!$A$2:$A$101,,0) -> rao | W93: =PROPER(_xlfn.CONCAT(U93," ",V93)) -> Shruti Rao | X93: =UPPER(_xlfn.CONCAT(LEFT(U93),LEFT(V93),RIGHT(A93,3))) -> SR046 | Y93: =HLOOKUP(F93,Dept_Info!$A$2:$I$3,2,0) -> IT | Z93: =IF(Y93="Sales",L93+(L93*$AG$6),L93) -> 582000 | AA93: =IF(J93<700000,"Low",IF(AND(J93>700000,J93<900000),"Medium","High")) -> Low | AB93: Female | AC93: =INDEX(Emp_Info!$B$1:$G$101,MATCH(HR_Data!$A67,Emp_Info!$B$2:$B$101,0),MATCH(HR_Data!AC$1,Emp_Info!$B$1:$G$1,0)) -> Master | AD93: =INDEX(Emp_Info!$A$1:$G$101,MATCH(HR_Data!$A93,Emp_Info!$B$1:$B$101,0),MATCH(HR_Data!AD$1,Emp_Info!$A$1:$G$1,0)) -> Delhi | AE93: =INDEX(Emp_Info!$A$1:$G$101,MATCH(HR_Data!$A93,Emp_Info!$B$1:$B$101,0),MATCH(HR_Data!AE$1,Emp_Info!$A$1:$G$1,0)) -> North | AF93: =IF(AND(P93>=3,M93>6),"Eligible","Not Eligible") -> Not Eligible
A94: EMP072 | B94: 33827 | C94: 32 | D94: 43970 | E94: LinkedIn | F94: D_004 | G94: Event Manager | H94: Contract | I94: MGR104 | J94: 520000 | K94: 42000 | L94: =SUM(J94:K94) -> 562000 | M94: 7 | N94: 3.7 | O94: 92.7 | P94: 1 | Q94: No | R94: High | S94: NA | T94: Active | U94: =VLOOKUP(A94,Emp_Info!$B$1:$G$101,3,0) -> vidya | V94: =_xlfn.XLOOKUP(A94,Emp_Info!$B$2:$B$101,Emp_Info!$A$2:$A$101,,0) -> mishra | W94: =PROPER(_xlfn.CONCAT(U94," ",V94)) -> Vidya Mishra | X94: =UPPER(_xlfn.CONCAT(LEFT(U94),LEFT(V94),RIGHT(A94,3))) -> VM072 | Y94: =HLOOKUP(F94,Dept_Info!$A$2:$I$3,2,0) -> Admin | Z94: =IF(Y94="Sales",L94+(L94*$AG$6),L94) -> 562000 | AA94: =IF(J94<700000,"Low",IF(AND(J94>700000,J94<900000),"Medium","High")) -> Low | AB94: Female | AC94: =INDEX(Emp_Info!$B$1:$G$101,MATCH(HR_Data!$A9,Emp_Info!$B$2:$B$101,0),MATCH(HR_Data!AC$1,Emp_Info!$B$1:$G$1,0)) -> Master | AD94: =INDEX(Emp_Info!$A$1:$G$101,MATCH(HR_Data!$A94,Emp_Info!$B$1:$B$101,0),MATCH(HR_Data!AD$1,Emp_Info!$A$1:$G$1,0)) -> Pune | AE94: =INDEX(Emp_Info!$A$1:$G$101,MATCH(HR_Data!$A94,Emp_Info!$B$1:$B$101,0),MATCH(HR_Data!AE$1,Emp_Info!$A$1:$G$1,0)) -> West | AF94: =IF(AND(P94>=3,M94>6),"Eligible","Not Eligible") -> Not Eligible
A95: EMP014 | B95: 34774 | C95: 29 | D95: 44940 | E95: Linkedin | F95: D_001 | G95: Junior Developer | H95: Full-Time | I95: MGR101 | J95: 520000 | K95: 40000 | L95: =SUM(J95:K95) -> 560000 | M95: 4 | N95: 3.8 | O95: 94 | P95: 1 | Q95: Yes | R95: Medium | S95: NA | T95: Active | U95: =VLOOKUP(A95,Emp_Info!$B$1:$G$101,3,0) -> neha | V95: =_xlfn.XLOOKUP(A95,Emp_Info!$B$2:$B$101,Emp_Info!$A$2:$A$101,,0) -> verma | W95: =PROPER(_xlfn.CONCAT(U95," ",V95)) -> Neha Verma | X95: =UPPER(_xlfn.CONCAT(LEFT(U95),LEFT(V95),RIGHT(A95,3))) -> NV014 | Y95: =HLOOKUP(F95,Dept_Info!$A$2:$I$3,2,0) -> IT | Z95: =IF(Y95="Sales",L95+(L95*$AG$6),L95) -> 560000 | AA95: =IF(J95<700000,"Low",IF(AND(J95>700000,J95<900000),"Medium","High")) -> Low | AB95: Female | AC95: =INDEX(Emp_Info!$B$1:$G$101,MATCH(HR_Data!$A66,Emp_Info!$B$2:$B$101,0),MATCH(HR_Data!AC$1,Emp_Info!$B$1:$G$1,0)) -> Master | AD95: =INDEX(Emp_Info!$A$1:$G$101,MATCH(HR_Data!$A95,Emp_Info!$B$1:$B$101,0),MATCH(HR_Data!AD$1,Emp_Info!$A$1:$G$1,0)) -> Bangalore | AE95: =INDEX(Emp_Info!$A$1:$G$101,MATCH(HR_Data!$A95,Emp_Info!$B$1:$B$101,0),MATCH(HR_Data!AE$1,Emp_Info!$A$1:$G$1,0)) -> South | AF95: =IF(AND(P95>=3,M95>6),"Eligible","Not Eligible") -> Not Eligible
A96: EMP038 | B96: 34284 | C96: 31 | D96: 44457 | E96: Campus | F96: D_003 | G96: Inside Sales Representative | H96: Contract | I96: MGR106 | J96: 490000 | K96: 38000 | L96: =SUM(J96:K96) -> 528000 | M96: 6 | N96: 3.7 | O96: 92.5 | P96: 1 | Q96: No | R96: High | S96: NA | T96: Active | U96: =VLOOKUP(A96,Emp_Info!$B$1:$G$101,3,0) -> rekha | V96: =_xlfn.XLOOKUP(A96,Emp_Info!$B$2:$B$101,Emp_Info!$A$2:$A$101,,0) -> pillai | W96: =PROPER(_xlfn.CONCAT(U96," ",V96)) -> Rekha Pillai | X96: =UPPER(_xlfn.CONCAT(LEFT(U96),LEFT(V96),RIGHT(A96,3))) -> RP038 | Y96: =HLOOKUP(F96,Dept_Info!$A$2:$I$3,2,0) -> Sales | Z96: =IF(Y96="Sales",L96+(L96*$AG$6),L96) -> 607200 | AA96: =IF(J96<700000,"Low",IF(AND(J96>700000,J96<900000),"Medium","High")) -> Low | AB96: Female | AC96: =INDEX(Emp_Info!$B$1:$G$101,MATCH(HR_Data!$A101,Emp_Info!$B$2:$B$101,0),MATCH(HR_Data!AC$1,Emp_Info!$B$1:$G$1,0)) -> Bachelor | AD96: =INDEX(Emp_Info!$A$1:$G$101,MATCH(HR_Data!$A96,Emp_Info!$B$1:$B$101,0),MATCH(HR_Data!AD$1,Emp_Info!$A$1:$G$1,0)) -> Mumbai | AE96: =INDEX(Emp_Info!$A$1:$G$101,MATCH(HR_Data!$A96,Emp_Info!$B$1:$B$101,0),MATCH(HR_Data!AE$1,Emp_Info!$A$1:$G$1,0)) -> West | AF96: =IF(AND(P96>=3,M96>6),"Eligible","Not Eligible") -> Not Eligible
A97: EMP058 | B97: 35023 | C97: 29 | D97: 44976 | E97: Referral | F97: D_001 | G97: Technical Writer | H97: Contract | I97: MGR101 | J97: 480000 | K97: 36000 | L97: =SUM(J97:K97) -> 516000 | M97: 4 | N97: 3.7 | O97: 92.3 | P97: 1 | Q97: No | R97: High | S97: NA | T97: Active | U97: =VLOOKUP(A97,Emp_Info!$B$1:$G$101,3,0) -> ritika | V97: =_xlfn.XLOOKUP(A97,Emp_Info!$B$2:$B$101,Emp_Info!$A$2:$A$101,,0) -> bhatt | W97: =PROPER(_xlfn.CONCAT(U97," ",V97)) -> Ritika Bhatt | X97: =UPPER(_xlfn.CONCAT(LEFT(U97),LEFT(V97),RIGHT(A97,3))) -> RB058 | Y97: =HLOOKUP(F97,Dept_Info!$A$2:$I$3,2,0) -> IT | Z97: =IF(Y97="Sales",L97+(L97*$AG$6),L97) -> 516000 | AA97: =IF(J97<700000,"Low",IF(AND(J97>700000,J97<900000),"Medium","High")) -> Low | AB97: Female | AC97: =INDEX(Emp_Info!$B$1:$G$101,MATCH(HR_Data!$A68,Emp_Info!$B$2:$B$101,0),MATCH(HR_Data!AC$1,Emp_Info!$B$1:$G$1,0)) -> Master | AD97: =INDEX(Emp_Info!$A$1:$G$101,MATCH(HR_Data!$A97,Emp_Info!$B$1:$B$101,0),MATCH(HR_Data!AD$1,Emp_Info!$A$1:$G$1,0)) -> Noida | AE97: =INDEX(Emp_Info!$A$1:$G$101,MATCH(HR_Data!$A97,Emp_Info!$B$1:$B$101,0),MATCH(HR_Data!AE$1,Emp_Info!$A$1:$G$1,0)) -> North | AF97: =IF(AND(P97>=3,M97>6),"Eligible","Not Eligible") -> Not Eligible
A98: EMP008 | B98: 34008 | D98: 44333 | E98: Freelance | F98: D_002 | G98: Recruiter | H98: Contract | I98: MGR102 | J98: 480000 | K98: 35000 | L98: =SUM(J98:K98) -> 515000 | M98: 6 | N98: 3.9 | O98: 93.5 | P98: 1 | Q98: No | R98: High | S98: NA | T98: Active | U98: =VLOOKUP(A98,Emp_Info!$B$1:$G$101,3,0) -> kavita | V98: =_xlfn.XLOOKUP(A98,Emp_Info!$B$2:$B$101,Emp_Info!$A$2:$A$101,,0) -> joshi | W98: =PROPER(_xlfn.CONCAT(U98," ",V98)) -> Kavita Joshi | X98: =UPPER(_xlfn.CONCAT(LEFT(U98),LEFT(V98),RIGHT(A98,3))) -> KJ008 | Y98: =HLOOKUP(F98,Dept_Info!$A$2:$I$3,2,0) -> HR | Z98: =IF(Y98="Sales",L98+(L98*$AG$6),L98) -> 515000 | AA98: =IF(J98<700000,"Low",IF(AND(J98>700000,J98<900000),"Medium","High")) -> Low | AB98: Female | AC98: =INDEX(Emp_Info!$B$1:$G$101,MATCH(HR_Data!$A40,Emp_Info!$B$2:$B$101,0),MATCH(HR_Data!AC$1,Emp_Info!$B$1:$G$1,0)) -> Bachelor | AD98: =INDEX(Emp_Info!$A$1:$G$101,MATCH(HR_Data!$A98,Emp_Info!$B$1:$B$101,0),MATCH(HR_Data!AD$1,Emp_Info!$A$1:$G$1,0)) -> Bangalore | AE98: =INDEX(Emp_Info!$A$1:$G$101,MATCH(HR_Data!$A98,Emp_Info!$B$1:$B$101,0),MATCH(HR_Data!AE$1,Emp_Info!$A$1:$G$1,0)) -> South | AF98: =IF(AND(P98>=3,M98>6),"Eligible","Not Eligible") -> Not Eligible
A99: EMP048 | B99: 33803 | C99: 32 | D99: 44181 | E99: Job Portal | F99: D_004 | G99: Email Marketing Specialist | H99: Contract | I99: MGR104 | J99: 470000 | K99: 35000 | L99: =SUM(J99:K99) -> 505000 | M99: 7 | N99: 3.6 | O99: 91.8 | P99: 1 | Q99: No | R99: High | S99: NA | T99: Active | U99: =VLOOKUP(A99,Emp_Info!$B$1:$G$101,3,0) -> geeta | V99: =_xlfn.XLOOKUP(A99,Emp_Info!$B$2:$B$101,Emp_Info!$A$2:$A$101,,0) -> saxena | W99: =PROPER(_xlfn.CONCAT(U99," ",V99)) -> Geeta Saxena | X99: =UPPER(_xlfn.CONCAT(LEFT(U99),LEFT(V99),RIGHT(A99,3))) -> GS048 | Y99: =HLOOKUP(F99,Dept_Info!$A$2:$I$3,2,0) -> Admin | Z99: =IF(Y99="Sales",L99+(L99*$AG$6),L99) -> 505000 | AA99: =IF(J99<700000,"Low",IF(AND(J99>700000,J99<900000),"Medium","High")) -> Low | AB99: Female | AC99: =INDEX(Emp_Info!$B$1:$G$101,MATCH(HR_Data!$A8,Emp_Info!$B$2:$B$101,0),MATCH(HR_Data!AC$1,Emp_Info!$B$1:$G$1,0)) -> Bachelor | AD99: =INDEX(Emp_Info!$A$1:$G$101,MATCH(HR_Data!$A99,Emp_Info!$B$1:$B$101,0),MATCH(HR_Data!AD$1,Emp_Info!$A$1:$G$1,0)) -> Hyderabad | AE99: =INDEX(Emp_Info!$A$1:$G$101,MATCH(HR_Data!$A99,Emp_Info!$B$1:$B$101,0),MATCH(HR_Data!AE$1,Emp_Info!$A$1:$G$1,0)) -> South | AF99: =IF(AND(P99>=3,M99>6),"Eligible","Not Eligible") -> Not Eligible
A100: EMP088 | B100: 34971 | C100: 29 | D100: 44979 | E100: Referral | F100: D_002 | G100: HR Coordinator | H100: Contract | I100: MGR102 | J100: 460000 | K100: 34000 | L100: =SUM(J100:K100) -> 494000 | M100: 4 | N100: 3.6 | O100: 91.5 | P100: 1 | Q100: No | R100: High | S100: NA | T100: Active | U100: =VLOOKUP(A100,Emp_Info!$B$1:$G$101,3,0) -> sonal | V100: =_xlfn.XLOOKUP(A100,Emp_Info!$B$2:$B$101,Emp_Info!$A$2:$A$101,,0) -> kapoor | W100: =PROPER(_xlfn.CONCAT(U100," ",V100)) -> Sonal Kapoor | X100: =UPPER(_xlfn.CONCAT(LEFT(U100),LEFT(V100),RIGHT(A100,3))) -> SK088 | Y100: =HLOOKUP(F100,Dept_Info!$A$2:$I$3,2,0) -> HR | Z100: =IF(Y100="Sales",L100+(L100*$AG$6),L100) -> 494000 | AA100: =IF(J100<700000,"Low",IF(AND(J100>700000,J100<900000),"Medium","High")) -> Low | AB100: Female | AC100: =INDEX(Emp_Info!$B$1:$G$101,MATCH(HR_Data!$A46,Emp_Info!$B$2:$B$101,0),MATCH(HR_Data!AC$1,Emp_Info!$B$1:$G$1,0)) -> Bachelor | AD100: =INDEX(Emp_Info!$A$1:$G$101,MATCH(HR_Data!$A100,Emp_Info!$B$1:$B$101,0),MATCH(HR_Data!AD$1,Emp_Info!$A$1:$G$1,0)) -> Mumbai | AE100: =INDEX(Emp_Info!$A$1:$G$101,MATCH(HR_Data!$A100,Emp_Info!$B$1:$B$101,0),MATCH(HR_Data!AE$1,Emp_Info!$A$1:$G$1,0)) -> West | AF100: =IF(AND(P100>=3,M100>6),"Eligible","Not Eligible") -> Not Eligible
...

Sheet Dept_Info
A1: HOD | B1: Shantanu Roy | C1: Vibha Kaur | D1: Nikhil Chopra | E1: Mohanty Sahoo | F1: Akash Wadhwa | G1: Ankush Patel | H1: Pankaj Singh | I1: Martyn John
A2: Dept_ID | B2: D_001 | C2: D_002 | D2: D_003 | E2: D_004 | F2: D_005 | G2: D_006 | H2: D_007 | I2: D_008
A3: Dept_Name | B3: IT | C3: HR | D3: Sales | E3: Admin | F3: Marketing | G3: Finance | H3: Operations | I3: R&D

Sheet Emp_Info
A1: Last_Name | B1: Emp_ID | C1: Gender | D1: First_Name | E1: Education_Level | F1: Location | G1: Region
A2: gupta | B2: EMP011 | C2: Male | D2: manoj | E2: Bachelor | F2: Noida | G2: North
A3: kapoor | B3: EMP012 | C3: Female | D3: pooja | E3: Bachelor | F3: Pune | G3: West
A4: rao | B4: EMP013 | C4: Male | D4: arjun | E4: Master | F4: Hyderabad | G4: South
A5: verma | B5: EMP014 | C5: Female | D5: neha | E5: Bachelor | F5: Bangalore | G5: South
A6: malhotra | B6: EMP015 | C6: Male | D6: karan | E6: Master | F6: Delhi | G6: North
A7: saxena | B7: EMP016 | C7: F | D7: ritu | E7: Bachelor | F7: Mumbai | G7: West
A8: pillai | B8: EMP017 | C8: Male | D8: sanjay | E8: Bachelor | F8: Chennai | G8: South
A9: bhat | B9: EMP018 | C9: Female | D9: meera | E9: Bachelor | F9: Pune | G9: West
A10: chopra | B10: EMP019 | C10: Male | D10: anil | E10: Master | F10: Noida | G10: North
A11: menon | B11: EMP020 | C11: F | D11: divya | E11: Bachelor | F11: Bangalore | G11: South
A12: kumar | B12: EMP001 | C12: Male | D12: rajesh | E12: Bachelor | F12: Mumbai | G12: West
... A101: pillai | B101: EMP092 | C101: Female | D101: kavita | E101: Master | F101: Bangalore | G101: South

Sheet Class_3_File
A1: Emp_ID | B1: Date_of_Birth | C1: Age | D1: Hire_Date | E1: Hiring Source | F1: Dept_ID | G1: Job_Title | H1: Employment_Type | I1: Manager_ID | J1: Base_Salary | K1: Bonus | L1: Total_Salary | M1: Years_of_Experience | N1: Performance_Rating | O1: Attendance_Percentage | P1: Certifications | Q1: Promotion_Eligible | R1: Attrition_Risk | S1: Last_Promotion_Date | T1: Employee_Status | U1: First_Name | V1: Last_Name | W1: Full_Name | X1: ID_Card_Details | Y1: Dept_Name | Z1: Diwali_Month_Salary | AA1: Salary_Seg | AB1: Gender | AC1: Education_Level | AD1: Location | AE1: Region | AF1: Advanced_Cert_Bonus
A2: EMP075 | B2: 31339 | C2: 39 | D2: 41983 | E2: Referral | F2: D_006 | G2: VP Finance | H2: Full-Time | I2: MGR103 | J2: 1450000 | K2: 165000 | L2: 1615000 | M2: 19 | N2: 4.8 | O2: 99.1 | P2: 4 | Q2: No | R2: Low | S2: 43819 | T2: Active | U2: vinay | V2: reddy | W2: Vinay Reddy | X2: VR075 | Y2: Finance | Z2: 1615000 | AA2: High | AB2: Male | AC2: Bachelor | AD2: Chennai | AE2: South | AF2: Eligible
A3: EMP019 | B3: 31301 | C3: 39 | D3: 42070 | E3: Job Portal | F3: D_001 | G3: IT Manager | H3: Full-Time | I3: MGR101 | J3: 1450000 | K3: 165000 | L3: 1615000 | M3: 17 | N3: 4.8 | O3: 99.2 | P3: 5 | Q3: No | R3: Low | S3: 43905 | T3: Active | U3: anil | V3: chopra | W3: Anil Chopra | X3: AC019 | Y3: IT | Z3: 1615000 | AA3: High | AB3: Male | AC3: Master | AD3: Noida | AE3: North | AF3: Eligible
A4: EMP097 | B4: 31462 | D4: 42137 | E4: Referral | F4: D_003 | G4: VP Sales | H4: Full-Time | I4: MGR106 | J4: 1380000 | K4: 158000 | L4: 1538000 | M4: 18 | N4: 4.8 | O4: 99 | P4: 4 | Q4: No | R4: Low | S4: 43971 | T4: Active | U4: rohit | V4: agarwal | W4: Rohit Agarwal | X4: RA097 | Y4: Sales | Z4: 1768700 | AA4: High | AB4: Male | AC4: Master | AD4: Bangalore | AE4: South | AF4: Eligible
A5: EMP005 | B5: 32129 | C5: 37 | D5: 42559 | E5: Campus | F5: D_005 | G5: Operations Manager | H5: Full-Time | I5: MGR105 | J5: 1100000 | K5: 120000 | L5: 1220000 | M5: 15 | N5: 4.7 | O5: 99 | P5: 4 | Q5: No | R5: Low | S5: 44397 | T5: Active | U5: vikram | V5: singh | W5: Vikram Singh | X5: VS005 | Y5: Marketing | Z5: 1220000 | AA5: High | AB5: Male | AC5: Bachelor | AD5: Pune | AE5: West | AF5: Eligible
A6: EMP047 | B6: 31355 | C6: 39 | D6: 42115 | E6: LinkedIn | F6: D_005 | G6: Plant Manager | H6: Full-Time | I6: MGR105 | J6: 1080000 | K6: 115000 | L6: 1195000 | M6: 18 | N6: 4.6 | O6: 98.6 | P6: 4 | Q6: No | R6: Low | S6: 43931 | T6: Active | U6: rajeev | V6: bose | W6: Rajeev Bose | X6: RB047 | Y6: Marketing | Z6: 1195000 | AA6: High | AB6: Male | AC6: Bachelor | AD6: Pune | AE6: West | AF6: Eligible
A7: EMP041 | B7: 33015 | C7: 34 | D7: 43419 | E7: Freelance | F7: D_001 | G7: Cloud Architect | H7: Full-Time | I7: MGR101 | J7: 1050000 | K7: 110000 | L7: 1160000 | M7: 11 | N7: 4.7 | O7: 98.9 | P7: 5 | Q7: Yes | R7: Low | S7: 44885 | T7: Active | U7: varun | V7: kapoor | W7: Varun Kapoor | X7: VK041 | Y7: IT | Z7: 1160000 | AA7: High | AB7: Male | AC7: Bachelor | AD7: Noida | AE7: North | AF7: Eligible
A8: EMP009 | B8: 31654 | C8: 38 | D8: 42040 | E8: Referral | F8: D_006 | G8: Finance Manager | H8: Full-Time | I8: MGR103 | J8: 1050000 | K8: 105000 | L8: 1155000 | M8: 16 | N8: 4.6 | O8: 98.5 | P8: 3 | Q8: No | R8: Low | S8: 43871 | T8: Active | U8: suresh | V8: nair | W8: Suresh Nair | X8: SN009 | Y8: Finance | Z8: 1155000 | AA8: High | AB8: Male | AC8: Master | AD8: Chennai | AE8: South | AF8: Eligible
A9: EMP079 | B9: 32516 | C9: 35 | D9: 43329 | E9: Job Portal | F9: D_003 | G9: National Sales Manager | H9: Full-Time | I9: MGR106 | J9: 1020000 | K9: 125000 | L9: 1145000 | M9: 12 | N9: 4.7 | O9: 98.6 | P9: 3 | Q9: Yes | R9: Low | S9: 45163 | T9: Active | U9: nikhil | V9: chopra | W9: Nikhil Chopra | X9: NC079 | Y9: Sales | Z9: 1316750 | AA9: High | AB9: Male | AC9: Master | AD9: Hyderabad | AE9: South | AF9: Eligible
A10: EMP051 | B10: 31537 | C10: 38 | D10: 42383 | E10: Freelance | F10: D_006 | G10: Controller | H10: Full-Time | I10: MGR103 | J10: 980000 | K10: 98000 | L10: 1078000 | M10: 16 | N10: 4.5 | O10: 98.2 | P10: 3 | Q10: No | R10: Low | S10: 44216 | T10: Active | U10: ramesh | V10: pillai | W10: Ramesh Pillai | X10: RP051 | Y10: Finance | Z10: 1078000 | AA10: High | AB10: Male | AC10: Master | AD10: Chennai | AE10: South | AF10: Eligible
A11: EMP077 | B11: 32276 | C11: 36 | D11: 43053 | E11: LinkedIn | F11: D_001 | G11: Solutions Architect | H11: Full-Time | I11: MGR101 | J11: 980000 | K11: 98000 | L11: 1078000 | M11: 13 | N11: 4.6 | O11: 98.4 | P11: 4 | Q11: Yes | R11: Low | S11: 44885 | T11: Active | U11: rajat | V11: verma | W11: Rajat Verma | X11: RV077 | Y11: IT | Z11: 1078000 | AA11: High | AB11: Male | AC11: Master | AD11: Delhi | AE11: North | AF11: Eligible
A12: EMP025 | B12: 33206 | C12: 34 | D12: 43544 | E12: Job Portal | F12: D_003 | G12: Regional Sales Manager | H12: Full-Time | I12: MGR106 | J12: 950000 | K12: 115000 | L12: 1065000 | M12: 10 | N12: 4.5 | O12: 97.8 | P12: 2 | Q12: Yes | R12: Low | S12: 44995 | T12: Active | U12: gaurav | V12: pandey | W12: Gaurav Pandey | X12: GP025 | Y12: Sales | Z12: 1224750 | AA12: High | AB12: Male | AC12: Master | AD12: Hyderabad | AE12: South | AF12: Not Eligible
A13: EMP061 | B13: 32504 | C13: 36 | D13: 42954 | E13: Referral | F13: D_003 | G13: Enterprise Sales Manager | H13: Full-Time | I13: MGR106 | J13: 940000 | K13: 112000 | L13: 1052000 | M13: 13 | N13: 4.5 | O13: 98.1 | P13: 3 | Q13: Yes | R13: Low | S13: 44788 | T13: Active | U13: siddharth | V13: mehta | W13: Siddharth Mehta | X13: SM061 | Y13: Sales | Z13: 1209800 | AA13: High | AB13: Male | AC13: Bachelor | AD13: Delhi | AE13: North | AF13: Eligible
A14: EMP002 | B14: 33076 | C14: 34 | D14: 43631 | E14: LinkedIn | F14: D_002 | G14: HR Manager | H14: Full-Time | I14: MGR102 | J14: 950000 | K14: 95000 | L14: 1045000 | M14: 10 | N14: 4.3 | O14: 98.2 | P14: 2 | Q14: Yes | R14: Low | S14: 45087 | T14: Active | U14: priya | V14: sharma | W14: Priya Sharma | X14: PS002 | Y14: HR | Z14: 1045000 | AA14: High | AB14: Female | AC14: Bachelor | AD14: Delhi | AE14: North | AF14: Not Eligible
A15: EMP092 | B15: 34168 | C15: 31 | D15: 44462 | E15: Job Portal | F15: D_001 | G15: Machine Learning Engineer | H15: Full-Time | I15: MGR101 | J15: 950000 | K15: 95000 | L15: 1045000 | M15: 6 | N15: 4.6 | O15: 98.3 | P15: 4 | Q15: Yes | R15: Low | S15: NA | T15: Active | U15: kavita | V15: pillai | W15: Kavita Pillai | X15: KP092 | Y15: IT | Z15: 1045000 | AA15: High | AB15: Female | AC15: Bachelor | AD15: Bangalore | AE15: South | AF15: Not Eligible
A16: EMP036 | B16: 33490 | C16: 33 | D16: 43851 | E16: Referral | F16: D_004 | G16: Product Manager | H16: Full-Time | I16: MGR104 | J16: 920000 | K16: 95000 | L16: 1015000 | M16: 9 | N16: 4.6 | O16: 98.7 | P16: 3 | Q16: Yes | R16: Low | S16: NA | T16: Active | U16: pallavi | V16: nambiar | W16: Pallavi Nambiar | X16: PN036 | Y16: Admin | Z16: 1015000 | AA16: High | AB16: Female | AC16: Bachelor | AD16: Pune | AE16: West | AF16: Eligible
A17: EMP011 | B17: 30684 | C17: 40 | D17: 41988 | E17: Freelance | F17: D_001 | G17: Senior Developer | H17: Full-Time | I17: MGR101 | J17: 920000 | K17: 92000 | L17: 1012000 | M17: 18 | N17: 4.4 | O17: 97.3 | P17: 4 | Q17: No | R17: Low | S17: 43819 | T17: Active | U17: manoj | V17: gupta | W17: Manoj Gupta | X17: MG011 | Y17: IT | Z17: 1012000 | AA17: High | AB17: Male | AC17: Bachelor | AD17: Noida | AE17: North | AF17: Eligible
A18: EMP059 | B18: 31479 | C18: 38 | D18: 42300 | E18: Job Portal | F18: D_005 | G18: Production Manager | H18: Full-Time | I18: MGR105 | J18: 920000 | K18: 92000 | L18: 1012000 | M18: 17 | N18: 4.4 | O18: 97.9 | P18: 3 | Q18: No | R18: Low | S18: 44119 | T18: Active | U18: alok | V18: sinha | W18: Alok Sinha | X18: AS059 | Y18: Marketing | Z18: 1012000 | AA18: High | AB18: Male | AC18: Master | AD18: Chennai | AE18: South | AF18: Eligible
A19: EMP093 | B19: 32080 | C19: 37 | D19: 42531 | E19: Freelance | F19: D_006 | G19: Financial Planning Manager | H19: Full-Time | I19: MGR103 | J19: 920000 | K19: 92000 | L19: 1012000 | M19: 15 | N19: 4.5 | O19: 98 | P19: 3 | Q19: Yes | R19: Low | S19: 44367 | T19: Active | U19: dinesh | V19: reddy | W19: Dinesh Reddy | X19: DR093 | Y19: Finance | Z19: 1012000 | AA19: High | AB19: Male | AC19: Master | AD19: Delhi | AE19: North | AF19: Eligible
A20: EMP096 | B20: 33579 | C20: 33 | D20: 43758 | E20: Freelance | F20: D_001 | G20: Technical Lead | H20: Full-Time | I20: MGR101 | J20: 920000 | K20: 92000 | L20: 1012000 | M20: 9 | N20: 4.5 | O20: 98.1 | P20: 4 | Q20: Yes | R20: Low | S20: 45214 | T20: Active | U20: anjana | V20: nair | W20: Anjana Nair | X20: AN096 | Y20: IT | Z20: 1012000 | AA20: High | AB20: Female | AC20: Master | AD20: Noida | AE20: North | AF20: Eligible
A21: EMP082 | B21: 34530 | C21: 30 | D21: 44862 | E21: Job Portal | F21: D_001 | G21: Data Scientist | H21: Full-Time | I21: MGR101 | J21: 920000 | K21: 92000 | L21: 1012000 | M21: 5 | N21: 4.5 | O21: 97.8 | P21: 3 | Q21: Yes | R21: Low | S21: NA | T21: Active | U21: namita | V21: rao | W21: Namita Rao | X21: NR082 | Y21: IT | Z21: 1012000 | AA21: High | AB21: Female | AC21: Master | AD21: Noida | AE21: North | AF21: Not Eligible
A22: EMP049 | B22: 32199 | C22: 36 | D22: 42622 | E22: Freelance | F22: D_003 | G22: Channel Sales Manager | H22: Full-Time | I22: MGR106 | J22: 890000 | K22: 105000 | L22: 995000 | M22: 14 | N22: 4.4 | O22: 97.5 | P22: 3 | Q22: Yes | R22: Low | S22: 44459 | T22: Active | U22: sunil | V22: agarwal | W22: Sunil Agarwal | X22: SA049 | Y22: Sales | Z22: 1144250 | AA22: Medium | AB22: Male | AC22: Bachelor | AD22: Bangalore | AE22: South | AF22: Eligible
A23: EMP007 | B23: 32673 | C23: 35 | D23: 43434 | E23: Job Portal | F23: D_003 | G23: Sales Manager | H23: Full-Time | I23: MGR106 | J23: 880000 | K23: 110000 | L23: 990000 | M23: 11 | N23: 4.3 | O23: 96.7 | P23: 1 | Q23: Yes | R23: Medium | S23: 44880 | T23: Active | U23: rahul | V23: mehta | W23: Rahul Mehta | X23: RM007 | Y23: Sales | Z23: 1138500 | AA23: Medium | AB23: Male | AC23: Bachelor | AD23: Delhi | AE23: North | AF23: Not Eligible
A24: EMP099 | B24: 32308 | C24: 36 | D24: 43048 | E24: Referral | F24: D_006 | G24: Mergers & Acquisitions Analyst | H24: Full-Time | I24: MGR103 | J24: 890000 | K24: 88000 | L24: 978000 | M24: 13 | N24: 4.4 | O24: 97.6 | P24: 3 | Q24: Yes | R24: Low | S24: 44885 | T24: Active | U24: vikas | V24: sharma | W24: Vikas Sharma | X24: VS099 | Y24: Finance | Z24: 978000 | AA24: Medium | AB24: Male | AC24: Master | AD24: Pune | AE24: West | AF24: Eligible
A25: EMP029 | B25: 32485 | D25: 42903 | E25: LinkedIn | F25: D_005 | G25: Process Manager | H25: Full-Time | I25: MGR105 | J25: 890000 | K25: 88000 | L25: 978000 | M25: 13 | N25: 4.3 | O25: 98 | P25: 3 | Q25: Yes | R25: Low | S25: 44732 | T25: Active | U25: nitin | V25: jain | W25: Nitin Jain | X25: NJ029 | Y25: Marketing | Z25: 978000 | AA25: Medium | AB25: Male | AC25: Bachelor | AD25: Pune | AE25: West | AF25: Eligible
A26: EMP091 | B26: 32514 | C26: 35 | D26: 43084 | E26: LinkedIn | F26: D_003 | G26: Direct Sales Manager | H26: Full-Time | I26: MGR106 | J26: 870000 | K26: 98000 | L26: 968000 | M26: 12 | N26: 4.4 | O26: 97.4 | P26: 2 | Q26: Yes | R26: Low | S26: 44915 | T26: Active | U26: sameer | V26: bansal | W26: Sameer Bansal | X26: SB091 | Y26: Sales | Z26: 1113200 | AA26: Medium | AB26: Male | AC26: Master | AD26: Pune | AE26: West | AF26: Not Eligible
A27: EMP037 | B27: 31471 | C27: 38 | D27: 42342 | E27: Job Portal | F27: D_001 | G27: DevOps Engineer | H27: Full-Time | I27: MGR101 | J27: 880000 | K27: 85000 | L27: 965000 | M27: 16 | N27: 4.4 | O27: 97.4 | P27: 4 | Q27: No | R27: Low | S27: 44180 | T27: Active | U27: ajay | V27: sharma | W27: Ajay Sharma | X27: AS037 | Y27: IT | Z27: 965000 | AA27: Medium | AB27: Male | AC27: Bachelor | AD27: Bangalore | AE27: South | AF27: Eligible
A28: EMP086 | B28: 33453 | C28: 33 | D28: 43795 | E28: Job Portal | F28: D_001 | G28: Product Owner | H28: Full-Time | I28: MGR101 | J28: 880000 | K28: 85000 | L28: 965000 | M28: 9 | N28: 4.4 | O28: 97.6 | P28: 3 | Q28: Yes | R28: Low | S28: NA | T28: Active | U28: preeti | V28: menon | W28: Preeti Menon | X28: PM086 | Y28: IT | Z28: 965000 | AA28: Medium | AB28: Female | AC28: Bachelor | AD28: Bangalore | AE28: South | AF28: Eligible
A29: EMP031 | B29: 31837 | C29: 37 | D29: 42680 | E29: Job Portal | F29: D_003 | G29: Key Account Manager | H29: Full-Time | I29: MGR106 | J29: 860000 | K29: 98000 | L29: 958000 | M29: 14 | N29: 4.4 | O29: 96.9 | P29: 2 | Q29: Yes | R29: Low | S29: 44515 | T29: Active | U29: ravi | V29: shetty | W29: Ravi Shetty | X29: RS031 | Y29: Sales | Z29: 1101700 | AA29: Medium | AB29: Male | AC29: Bachelor | AD29: Bangalore | AE29: South | AF29: Not Eligible
A30: EMP017 | B30: 31871 | C30: 37 | D30: 42655 | E30: Referral | F30: D_005 | G30: Logistics Manager | H30: Full-Time | I30: MGR105 | J30: 870000 | K30: 85000 | L30: 955000 | M30: 14 | N30: 4.3 | O30: 98.1 | P30: 3 | Q30: Yes | R30: Low | S30: 44489 | T30: Active | U30: sanjay | V30: pillai | W30: Sanjay Pillai | X30: SP017 | Y30: Marketing | Z30: 955000 | AA30: Medium | AB30: Male | AC30: Bachelor | AD30: Chennai | AE30: South | AF30: Eligible
A31: EMP081 | B31: 31718 | C31: 38 | D31: 42515 | E31: LinkedIn | F31: D_006 | G31: Compliance Officer | H31: Full-Time | I31: MGR103 | J31: 860000 | K31: 82000 | L31: 942000 | M31: 16 | N31: 4.3 | O31: 97.1 | P31: 3 | Q31: No | R31: Low | S31: 44326 | T31: Active | U31: sachin | V31: desai | W31: Sachin Desai | X31: SD081 | Y31: Finance | Z31: 942000 | AA31: Medium | AB31: Male | AC31: Bachelor | AD31: Mumbai | AE31: West | AF31: Eligible
A32: EMP001 | B32: 31121 | C32: 39 | D32: 43191 | E32: Job Portal | F32: D_001 | G32: Software Engineer | H32: Full-Time | I32: MGR101 | J32: 850000 | K32: 85000 | L32: 935000 | M32: 12 | N32: 4.2 | O32: 96.5 | P32: 3 | Q32: Yes | R32: Low | S32: 44666 | T32: Active | U32: rajesh | V32: kumar | W32: Rajesh Kumar | X32: RK001 | Y32: IT | Z32: 935000 | AA32: Medium | AB32: Male | AC32: Bachelor | AD32: Mumbai | AE32: West | AF32: Eligible
A33: EMP089 | B33: 31727 | C33: 38 | D33: 42464 | E33: Job Portal | F33: D_005 | G33: Distribution Manager | H33: Full-Time | I33: MGR105 | J33: 850000 | K33: 82000 | L33: 932000 | M33: 16 | N33: 4.3 | O33: 97.7 | P33: 3 | Q33: No | R33: Low | S33: 44301 | T33: Active | U33: akash | V33: yadav | W33: Akash Yadav | X33: AY089 | Y33: Marketing | Z33: 932000 | AA33: Medium | AB33: Male | AC33: Bachelor | AD33: Noida | AE33: North | AF33: Eligible
A34: EMP035 | B34: 32706 | C34: 35 | D34: 43233 | E34: LinkedIn | F34: D_005 | G34: Quality Manager | H34: Full-Time | I34: MGR105 | J34: 850000 | K34: 82000 | L34: 932000 | M34: 12 | N34: 4.3 | O34: 97.6 | P34: 3 | Q34: Yes | R34: Low | S34: 45066 | T34: Active | U34: manish | V34: goyal | W34: Manish Goyal | X34: MG035 | Y34: Marketing | Z34: 932000 | AA34: Medium | AB34: Male | AC34: Bachelor | AD34: Chennai | AE34: South | AF34: Eligible
A35: EMP095 | B35: 33110 | C35: 34 | D35: 43538 | E35: Job Portal | F35: D_004 | G35: Growth Marketing Manager | H35: Full-Time | I35: MGR104 | J35: 850000 | K35: 82000 | L35: 932000 | M35: 10 | N35: 4.4 | O35: 97.8 | P35: 3 | Q35: Yes | R35: Low | S35: NA | T35: Active | U35: puneet | V35: mehta | W35: Puneet Mehta | X35: PM095 | Y35: Admin | Z35: 932000 | AA35: Medium | AB35: Male | AC35: Bachelor | AD35: Hyderabad | AE35: South | AF35: Eligible
A36: EMP052 | B36: 33479 | C36: 33 | D36: 43636 | E36: Job Portal | F36: D_002 | G36: Talent Acquisition Manager | H36: Full-Time | I36: MGR102 | J36: 850000 | K36: 82000 | L36: 932000 | M36: 9 | N36: 4.4 | O36: 97.8 | P36: 2 | Q36: Yes | R36: Low | S36: 45092 | T36: Active | U36: aditi | V36: malhotra | W36: Aditi Malhotra | X36: AM052 | Y36: HR | Z36: 932000 | AA36: Medium | AB36: Female | AC36: Bachelor | AD36: Mumbai | AE36: West | AF36: Not Eligible
A37: EMP068 | B37: 33441 | C37: 33 | D37: 43756 | E37: Job Portal | F37: D_001 | G37: Scrum Master | H37: Full-Time | I37: MGR101 | J37: 850000 | K37: 82000 | L37: 932000 | M37: 9 | N37: 4.4 | O37: 97.7 | P37: 3 | Q37: Yes | R37: Low | S37: NA | T37: Active | U37: rashmi | V37: kapoor | W37: Rashmi Kapoor | X37: RK068 | Y37: IT | Z37: 932000 | AA37: Medium | AB37: Female | AC37: Bachelor | AD37: Bangalore | AE37: South | AF37: Eligible
A38: EMP085 | B38: 33045 | C38: 34 | D38: 43476 | E38: Job Portal | F38: D_003 | G38: Partner Manager | H38: Full-Time | I38: MGR106 | J38: 840000 | K38: 88000 | L38: 928000 | M38: 10 | N38: 4.3 | O38: 97 | P38: 2 | Q38: Yes | R38: Low | S38: 44946 | T38: Active | U38: anuj | V38: sinha | W38: Anuj Sinha | X38: AS085 | Y38: Sales | Z38: 1067200 | AA38: Medium | AB38: Male | AC38: Bachelor | AD38: Delhi | AE38: North | AF38: Not Eligible
A39: EMP043 | B39: 31796 | C39: 37 | D39: 42408 | E39: LinkedIn | F39: D_003 | G39: Territory Manager | H39: Full-Time | I39: MGR106 | J39: 830000 | K39: 92000 | L39: 922000 | M39: 15 | N39: 4.3 | O39: 97.1 | P39: 2 | Q39: Yes | R39: Low | S39: 44242 | T39: Active | U39: harish | V39: menon | W39: Harish Menon | X39: HM043 | Y39: Sales | Z39: 1060300 | AA39: Medium | AB39: Male | AC39: Master | AD39: Chennai | AE39: South | AF39: Not Eligible
A40: EMP013 | B40: 33204 | C40: 34 | D40: 43306 | E40: Job Portal | F40: D_003 | G40: Business Development Manager | H40: Full-Time | I40: MGR106 | J40: 810000 | K40: 95000 | L40: 905000 | M40: 10 | N40: 4.2 | O40: 95.5 | P40: 2 | Q40: Yes | R40: Medium | S40: NA | T40: Active | U40: arjun | V40: rao | W40: Arjun Rao | X40: AR013 | Y40: Sales | Z40: 1040750 | AA40: Medium | AB40: Male | AC40: Bachelor | AD40: Hyderabad | AE40: South | AF40: Not Eligible
A41: EMP033 | B41: 31343 | C41: 39 | D41: 42277 | E41: Referral | F41: D_006 | G41: Senior Accountant | H41: Full-Time | I41: MGR103 | J41: 820000 | K41: 78000 | L41: 898000 | M41: 17 | N41: 4.1 | O41: 96.1 | P41: 2 | Q41: No | R41: Low | S41: 44084 | T41: Active | U41: prakash | V41: reddy | W41: Prakash Reddy | X41: PR033 | Y41: Finance | Z41: 898000 | AA41: Medium | AB41: Male | AC41: Master | AD41: Hyderabad | AE41: South | AF41: Not Eligible
A42: EMP055 | B42: 31964 | C42: 37 | D42: 42686 | E42: Referral | F42: D_001 | G42: Database Administrator | H42: Full-Time | I42: MGR101 | J42: 820000 | K42: 78000 | L42: 898000 | M42: 15 | N42: 4.2 | O42: 96.8 | P42: 3 | Q42: Yes | R42: Low | S42: 44525 | T42: Active | U42: karthik | V42: reddy | W42: Karthik Reddy | X42: KR055 | Y42: IT | Z42: 898000 | AA42: Medium | AB42: Male | AC42: Bachelor | AD42: Hyderabad | AE42: South | AF42: Eligible
A43: EMP023 | B43: 31419 | C43: 38 | D43: 42593 | E43: Campus | F43: D_005 | G43: Warehouse Manager | H43: Full-Time | I43: MGR105 | J43: 820000 | K43: 78000 | L43: 898000 | M43: 15 | N43: 4.2 | O43: 97 | P43: 2 | Q43: Yes | R43: Low | S43: 44433 | T43: Active | U43: vishal | V43: tiwari | W43: Vishal Tiwari | X43: VT023 | Y43: Marketing | Z43: 898000 | AA43: Medium | AB43: Male | AC43: Bachelor | AD43: Delhi | AE43: North | AF43: Not Eligible
A44: EMP080 | B44: 33714 | C44: 32 | D44: 44267 | E44: Campus | F44: D_002 | G44: Diversity & Inclusion Manager | H44: Full-Time | I44: MGR102 | J44: 820000 | K44: 78000 | L44: 898000 | M44: 8 | N44: 4.4 | O44: 97.9 | P44: 3 | Q44: Yes | R44: Low | S44: NA | T44: Active | U44: shilpa | V44: kulkarni | W44: Shilpa Kulkarni | X44: SK080 | Y44: HR | Z44: 898000 | AA44: Medium | AB44: Female | AC44: Bachelor | AD44: Bangalore | AE44: South | AF44: Eligible
A45: EMP067 | B45: 31726 | C45: 38 | D45: 42434 | E45: Referral | F45: D_003 | G45: Sales Trainer | H45: Full-Time | I45: MGR106 | J45: 810000 | K45: 78000 | L45: 888000 | M45: 16 | N45: 4.3 | O45: 97.4 | P45: 2 | Q45: No | R45: Low | S45: 44270 | T45: Active | U45: naveen | V45: gupta | W45: Naveen Gupta | X45: NG067 | Y45: Sales | Z45: 1021200 | AA45: Medium | AB45: Male | AC45: Master | AD45: Pune | AE45: West | AF45: Not Eligible
A46: EMP060 | B46: 33403 | C46: 33 | D46: 43932 | E46: LinkedIn | F46: D_004 | G46: Communications Manager | H46: Full-Time | I46: MGR104 | J46: 810000 | K46: 78000 | L46: 888000 | M46: 9 | N46: 4.3 | O46: 97.3 | P46: 2 | Q46: Yes | R46: Low | S46: NA | T46: Active | U46: nidhi | V46: kulkarni | W46: Nidhi Kulkarni | X46: NK060 | Y46: Admin | Z46: 888000 | AA46: Medium | AB46: Female | AC46: Bachelor | AD46: Pune | AE46: West | AF46: Not Eligible
A47: EMP071 | B47: 31865 | C47: 37 | D47: 42573 | E47: Job Portal | F47: D_005 | G47: Safety Manager | H47: Full-Time | I47: MGR105 | J47: 800000 | K47: 76000 | L47: 876000 | M47: 15 | N47: 4.2 | O47: 97.2 | P47: 3 | Q47: Yes | R47: Low | S47: 44407 | T47: Active | U47: tarun | V47: shetty | W47: Tarun Shetty | X47: TS071 | Y47: Marketing | Z47: 876000 | AA47: Medium | AB47: Male | AC47: Bachelor | AD47: Hyderabad | AE47: South | AF47: Eligible
A48: EMP063 | B48: 32010 | C48: 37 | D48: 42537 | E48: Campus | F48: D_001 | G48: Network Engineer | H48: Full-Time | I48: MGR101 | J48: 790000 | K48: 75000 | L48: 865000 | M48: 15 | N48: 4.2 | O48: 96.9 | P48: 3 | Q48: Yes | R48: Low | S48: 44367 | T48: Active | U48: abhishek | V48: pandey | W48: Abhishek Pandey | X48: AP063 | Y48: IT | Z48: 865000 | AA48: Medium | AB48: Male | AC48: Master | AD48: Mumbai | AE48: West | AF48: Eligible
A49: EMP083 | B49: 31835 | C49: 37 | D49: 42632 | E49: Freelance | F49: D_005 | G49: Maintenance Manager | H49: Full-Time | I49: MGR105 | J49: 790000 | K49: 75000 | L49: 865000 | M49: 15 | N49: 4.1 | O49: 96.3 | P49: 2 | Q49: Yes | R49: Low | S49: 44464 | T49: Active | U49: yogesh | V49: pandey | W49: Yogesh Pandey | X49: YP083 | Y49: Marketing | Z49: 865000 | AA49: Medium | AB49: Male | AC49: Master | AD49: Chennai | AE49: South | AF49: Not Eligible
A50: EMP039 | B50: 32236 | C50: 36 | D50: 42942 | E50: LinkedIn | F50: D_006 | G50: Investment Analyst | H50: Full-Time | I50: MGR103 | J50: 790000 | K50: 72000 | L50: 862000 | M50: 13 | N50: 4.2 | O50: 96.5 | P50: 2 | Q50: Yes | R50: Low | S50: 44752 | T50: Active | U50: sandeep | V50: rana | W50: Sandeep Rana | X50: SR039 | Y50: Finance | Z50: 862000 | AA50: Medium | AB50: Male | AC50: Bachelor | AD50: Delhi | AE50: North | AF50: Not Eligible
A51: EMP073 | B51: 33231 | C51: 34 | D51: 43512 | E51: Job Portal | F51: D_003 | G51: Customer Success Manager | H51: Full-Time | I51: MGR106 | J51: 780000 | K51: 75000 | L51: 855000 | M51: 10 | N51: 4.2 | O51: 96.6 | P51: 2 | Q51: Yes | R51: Medium | S51: NA | T51: Active | U51: ashish | V51: pillai | W51: Ashish Pillai | X51: AP073 | Y51: Sales | Z51: 983250 | AA51: Medium | AB51: Male | AC51: Master | AD51: Bangalore | AE51: South | AF51: Not Eligible
A52: EMP027 | B52: 30940 | C52: 40 | D52: 42013 | E52: Referral | F52: D_001 | G52: System Administrator | H52: Full-Time | I52: MGR101 | J52: 780000 | K52: 72000 | L52: 852000 | M52: 19 | N52: 4.1 | O52: 96.4 | P52: 3 | Q52: No | R52: Low | S52: 43845 | T52: Active | U52: ashok | V52: bansal | W52: Ashok Bansal | X52: AB027 | Y52: IT | Z52: 852000 | AA52: Medium | AB52: Male | AC52: Bachelor | AD52: Mumbai | AE52: West | AF52: Eligible
A53: EMP076 | B53: 33270 | C53: 33 | D53: 43735 | E53: Job Portal | F53: D_005 | G53: Customer Service Manager | H53: Full-Time | I53: MGR105 | J53: 780000 | K53: 72000 | L53: 852000 | M53: 9 | N53: 4.3 | O53: 97.5 | P53: 2 | Q53: Yes | R53: Low | S53: 45184 | T53: Active | U53: sunita | V53: nair | W53: Sunita Nair | X53: SN076 | Y53: Marketing | Z53: 852000 | AA53: Medium | AB53: Female | AC53: Bachelor | AD53: Mumbai | AE53: West | AF53: Not Eligible
A54: EMP024 | B54: 33803 | C54: 32 | D54: 44170 | E54: LinkedIn | F54: D_004 | G54: Brand Manager | H54: Full-Time | I54: MGR104 | J54: 780000 | K54: 72000 | L54: 852000 | M54: 8 | N54: 4.4 | O54: 98.3 | P54: 3 | Q54: Yes | R54: Low | S54: NA | T54: Active | U54: anjali | V54: sinha | W54: Anjali Sinha | X54: AS024 | Y54: Admin | Z54: 852000 | AA54: Medium | AB54: Female | AC54: Bachelor | AD54: Bangalore | AE54: South | AF54: Eligible
A55: EMP050 | B55: 34255 | C55: 31 | D55: 44338 | E55: Job Portal | F55: D_001 | G55: Cybersecurity Analyst | H55: Full-Time | I55: MGR101 | J55: 780000 | K55: 72000 | L55: 852000 | M55: 6 | N55: 4.2 | O55: 96.7 | P55: 3 | Q55: Yes | R55: Low | S55: NA | T55: Active | U55: kavya | V55: iyer | W55: Kavya Iyer | X55: KI050 | Y55: IT | Z55: 852000 | AA55: Medium | AB55: Female | AC55: Bachelor | AD55: Noida | AE55: North | AF55: Not Eligible
A56: EMP003 | B56: 32457 | C56: 36 | D56: 42755 | E56: Referral | F56: D_006 | G56: Financial Analyst | H56: Full-Time | I56: MGR103 | J56: 780000 | K56: 70000 | L56: 850000 | M56: 14 | N56: 3.8 | O56: 94.3 | P56: 1 | Q56: No | R56: Medium | S56: NA | T56: Active | U56: amit | V56: patel | W56: Amit Patel | X56: AP003 | Y56: Finance | Z56: 850000 | AA56: Medium | AB56: Male | AC56: Master | AD56: Bangalore | AE56: South | AF56: Not Eligible
A57: EMP087 | B57: 32218 | C57: 36 | D57: 42924 | E57: LinkedIn | F57: D_006 | G57: Internal Auditor | H57: Full-Time | I57: MGR103 | J57: 770000 | K57: 72000 | L57: 842000 | M57: 13 | N57: 4.1 | O57: 96.5 | P57: 2 | Q57: Yes | R57: Low | S57: 44757 | T57: Active | U57: hemant | V57: gupta | W57: Hemant Gupta | X57: HG087 | Y57: Finance | Z57: 842000 | AA57: Medium | AB57: Male | AC57: Bachelor | AD57: Hyderabad | AE57: South | AF57: Not Eligible
A58: EMP057 | B58: 32753 | C58: 35 | D58: 43235 | E58: Referral | F58: D_006 | G58: Risk Analyst | H58: Full-Time | I58: MGR103 | J58: 770000 | K58: 71000 | L58: 841000 | M58: 11 | N58: 4.1 | O58: 96.2 | P58: 2 | Q58: Yes | R58: Low | S58: 45066 | T58: Active | U58: mohit | V58: jain | W58: Mohit Jain | X58: MJ057 | Y58: Finance | Z58: 841000 | AA58: Medium | AB58: Male | AC58: Bachelor | AD58: Mumbai | AE58: West | AF58: Not Eligible
A59: EMP065 | B59: 32919 | C59: 34 | D59: 43356 | E59: Job Portal | F59: D_005 | G59: Inventory Manager | H59: Full-Time | I59: MGR105 | J59: 760000 | K59: 72000 | L59: 832000 | M59: 11 | N59: 4.1 | O59: 96.4 | P59: 2 | Q59: Yes | R59: Low | S59: 45189 | T59: Active | U59: pankaj | V59: bansal | W59: Pankaj Bansal | X59: PB065 | Y59: Marketing | Z59: 832000 | AA59: Medium | AB59: Male | AC59: Master | AD59: Noida | AE59: North | AF59: Not Eligible
A60: EMP090 | B60: 33748 | C60: 32 | D60: 44062 | E60: Campus | F60: D_004 | G60: Partnership Manager | H60: Full-Time | I60: MGR104 | J60: 760000 | K60: 72000 | L60: 832000 | M60: 8 | N60: 4.2 | O60: 96.9 | P60: 2 | Q60: Yes | R60: Low | S60: NA | T60: Active | U60: naina | V60: tiwari | W60: Naina Tiwari | X60: NT090 | Y60: Admin | Z60: 832000 | AA60: Medium | AB60: Female | AC60: Bachelor | AD60: Chennai | AE60: South | AF60: Not Eligible
A61: EMP045 | B61: 32579 | C61: 35 | D61: 42964 | E61: Job Portal | F61: D_006 | G61: Treasury Analyst | H61: Full-Time | I61: MGR103 | J61: 760000 | K61: 70000 | L61: 830000 | M61: 12 | N61: 4 | O61: 95.8 | P61: 2 | Q61: Yes | R61: Low | S61: 44798 | T61: Active | U61: aditya | V61: verma | W61: Aditya Verma | X61: AV045 | Y61: Finance | Z61: 830000 | AA61: Medium | AB61: Male | AC61: Bachelor | AD61: Mumbai | AE61: West | AF61: Not Eligible
A62: EMP015 | B62: 32333 | C62: 36 | D62: 42981 | E62: Job Portal | F62: D_006 | G62: Tax Consultant | H62: Full-Time | I62: MGR103 | J62: 750000 | K62: 68000 | L62: 818000 | M62: 12 | N62: 4 | O62: 96.8 | P62: 2 | Q62: Yes | R62: Low | S62: 44819 | T62: Active | U62: karan | V62: malhotra | W62: Karan Malhotra | X62: KM015 | Y62: Finance | Z62: 818000 | AA62: Medium | AB62: Male | AC62: Bachelor | AD62: Delhi | AE62: North | AF62: Not Eligible
A63: EMP069 | B63: 32512 | C63: 35 | D63: 43216 | E63: Freelance | F63: D_006 | G63: Credit Analyst | H63: Full-Time | I63: MGR103 | J63: 740000 | K63: 68000 | L63: 808000 | M63: 12 | N63: 4 | O63: 95.6 | P63: 2 | Q63: Yes | R63: Low | S63: 45026 | T63: Active | U63: deepak | V63: yadav | W63: Deepak Yadav | X63: DY069 | Y63: Finance | Z63: 808000 | AA63: Medium | AB63: Male | AC63: Bachelor | AD63: Delhi | AE63: North | AF63: Not Eligible
A64: EMP032 | B64: 33769 | C64: 32 | D64: 43940 | E64: Linkedin | F64: D_001 | G64: Business Analyst | H64: Full-Time | I64: MGR101 | J64: 740000 | K64: 68000 | L64: 808000 | M64: 8 | N64: 4.2 | O64: 97.2 | P64: 2 | Q64: Yes | R64: Low | S64: NA | T64: Active | U64: tanvi | V64: deshpande | W64: Tanvi Deshpande | X64: TD032 | Y64: IT | Z64: 808000 | AA64: Medium | AB64: Female | AC64: Bachelor | AD64: Mumbai | AE64: West | AF64: Not Eligible
A65: EMP064 | B65: 33880 | C65: 32 | D65: 44164 | E65: LinkedIn | F65: D_006 | G65: Payroll Manager | H65: Full-Time | I65: MGR103 | J65: 730000 | K65: 68000 | L65: 798000 | M65: 8 | N65: 4 | O65: 95.9 | P65: 2 | Q65: Yes | R65: Low | S65: NA | T65: Active | U65: megha | V65: tiwari | W65: Megha Tiwari | X65: MT064 | Y65: Finance | Z65: 798000 | AA65: Medium | AB65: Female | AC65: Bachelor | AD65: Hyderabad | AE65: South | AF65: Not Eligible
A66: EMP053 | B66: 33218 | C66: 34 | D66: 43542 | E66: LinkedIn | F66: D_005 | G66: Facilities Manager | H66: Full-Time | I66: MGR105 | J66: 720000 | K66: 68000 | L66: 788000 | M66: 10 | N66: 4 | O66: 95.4 | P66: 2 | Q66: Yes | R66: Medium | S66: NA | T66: Active | U66: vivek | V66: nair | W66: Vivek Nair | X66: VN053 | Y66: Marketing | Z66: 788000 | AA66: Medium | AB66: Male | AC66: Bachelor | AD66: Delhi | AE66: North | AF66: Not Eligible
A67: EMP078 | B67: 34238 | C67: 31 | D67: 44367 | E67: Referral | F67: D_004 | G67: Influencer Marketing Manager | H67: Full-Time | I67: MGR104 | J67: 720000 | K67: 68000 | L67: 788000 | M67: 6 | N67: 4.2 | O67: 96.8 | P67: 2 | Q67: Yes | R67: Low | S67: NA | T67: Active | U67: archana | V67: bhatt | W67: Archana Bhatt | X67: AB078 | Y67: Admin | Z67: 788000 | AA67: Medium | AB67: Female | AC67: Bachelor | AD67: Pune | AE67: West | AF67: Not Eligible
A68: EMP094 | B68: 34436 | C68: 30 | D68: 44892 | E68: Referral | F68: D_005 | G68: Quality Assurance Manager | H68: Full-Time | I68: MGR105 | J68: 720000 | K68: 68000 | L68: 788000 | M68: 5 | N68: 4 | O68: 95.7 | P68: 2 | Q68: Yes | R68: Medium | S68: NA | T68: Active | U68: shraddha | V68: joshi | W68: Shraddha Joshi | X68: SJ094 | Y68: Marketing | Z68: 788000 | AA68: Medium | AB68: Female | AC68: Bachelor | AD68: Mumbai | AE68: West | AF68: Not Eligible
A69: EMP006 | B69: 33353 | C69: 33 | D69: 43730 | E69: LinkedIn | F69: D_001 | G69: Data Analyst | H69: Full-Time | I69: MGR101 | J69: 720000 | K69: 65000 | L69: 785000 | M69: 9 | N69: 4.1 | O69: 95.8 | P69: 2 | Q69: Yes | R69: Low | S69: NA | T69: Active | U69: anita | V69: desai | W69: Anita Desai | X69: AD006 | Y69: IT | Z69: 785000 | AA69: Medium | AB69: Female | AC69: Bachelor | AD69: Mumbai | AE69: West | AF69: Not Eligible
A70: EMP028 | B70: 33354 | C70: 33 | D70: 43761 | E70: Job Portal | F70: D_006 | G70: Budget Analyst | H70: Full-Time | I70: MGR103 | J70: 710000 | K70: 65000 | L70: 775000 | M70: 9 | N70: 4 | O70: 95.7 | P70: 2 | Q70: Yes | R70: Low | S70: NA | T70: Active | U70: preeti | V70: mishra | W70: Preeti Mishra | X70: PM028 | Y70: Finance | Z70: 775000 | AA70: Medium | AB70: Female | AC70: Bachelor | AD70: Chennai | AE70: South | AF70: Not Eligible
A71: EMP098 | B71: 34213 | C71: 31 | D71: 44393 | E71: Job Portal | F71: D_002 | G71: Organizational Development Specialist | H71: Full-Time | I71: MGR102 | J71: 690000 | K71: 64000 | L71: 754000 | M71: 6 | N71: 4.1 | O71: 96.4 | P71: 2 | Q71: Yes | R71: Low | S71: NA | T71: Active | U71: tara | V71: desai | W71: Tara Desai | X71: TD098 | Y71: HR | Z71: 754000 | AA71: Low | AB71: Female | AC71: Master | AD71: Chennai | AE71: South | AF71: Not Eligible
A72: EMP044 | B72: 33511 | C72: 33 | D72: 43762 | E72: Referral | F72: D_002 | G72: HRIS Specialist | H72: Full-Time | I72: MGR102 | J72: 690000 | K72: 62000 | L72: 752000 | M72: 9 | N72: 4.1 | O72: 96.3 | P72: 2 | Q72: Yes | R72: Low | S72: NA | T72: Active | U72: priyanka | V72: gupta | W72: Priyanka Gupta | X72: PG044 | Y72: HR | Z72: 752000 | AA72: Low | AB72: Female | AC72: Master | AD72: Bangalore | AE72: South | AF72: Not Eligible
A73: EMP012 | B73: 33377 | C73: 33 | D73: 43565 | E73: Referral | F73: D_005 | G73: Supply Chain Analyst | H73: Full-Time | I73: MGR105 | J73: 690000 | K73: 62000 | L73: 752000 | M73: 9 | N73: 3.7 | O73: 92.8 | P73: 1 | Q73: No | R73: High | S73: NA | T73: Active | U73: pooja | V73: kapoor | W73: Pooja Kapoor | X73: PK012 | Y73: Marketing | Z73: 752000 | AA73: Low | AB73: Female | AC73: Master | AD73: Pune | AE73: West | AF73: Not Eligible
A74: EMP074 | B74: 34492 | C74: 30 | D74: 44796 | E74: Freelance | F74: D_001 | G74: Mobile App Developer | H74: Full-Time | I74: MGR101 | J74: 680000 | K74: 62000 | L74: 742000 | M74: 5 | N74: 4 | O74: 95.2 | P74: 2 | Q74: Yes | R74: Low | S74: NA | T74: Active | U74: jyoti | V74: agarwal | W74: Jyoti Agarwal | X74: JA074 | Y74: IT | Z74: 742000 | AA74: Low | AB74: Female | AC74: Bachelor | AD74: Noida | AE74: North | AF74: Not Eligible
A75: EMP021 | B75: 32552 | C75: 35 | D75: 43248 | E75: Referral | F75: D_006 | G75: Accountant | H75: Full-Time | I75: MGR103 | J75: 680000 | K75: 60000 | L75: 740000 | M75: 11 | N75: 3.8 | O75: 93.9 | P75: 1 | Q75: No | R75: Medium | S75: NA | T75: Active | U75: rohit | V75: agarwal | W75: Rohit Agarwal | X75: RA021 | Y75: Finance | Z75: 740000 | AA75: Low | AB75: Male | AC75: Master | AD75: Mumbai | AE75: West | AF75: Not Eligible
... A97: EMP058 | B97: 35023 | C97: 29 | D97: 44976 | E97: Referral | F97: D_001 | G97: Technical Writer | H97: Contract | I97: MGR101 | J97: 480000 | K97: 36000 | L97: 516000 | M97: 4 | N97: 3.7 | O97: 92.3 | P97: 1 | Q97: No | R97: High | S97: NA | T97: Active | U97: ritika | V97: bhatt | W97: Ritika Bhatt | X97: RB058 | Y97: IT | Z97: 516000 | AA97: Low | AB97: Female | AC97: Master | AD97: Noida | AE97: North | AF97: Not Eligible
A98: EMP008 | B98: 34008 | D98: 44333 | E98: Freelance | F98: D_002 | G98: Recruiter | H98: Contract | I98: MGR102 | J98: 480000 | K98: 35000 | L98: 515000 | M98: 6 | N98: 3.9 | O98: 93.5 | P98: 1 | Q98: No | R98: High | S98: NA | T98: Active | U98: kavita | V98: joshi | W98: Kavita Joshi | X98: KJ008 | Y98: HR | Z98: 515000 | AA98: Low | AB98: Female | AC98: Bachelor | AD98: Bangalore | AE98: South | AF98: Not Eligible
A99: EMP048 | B99: 33803 | C99: 32 | D99: 44181 | E99: Job Portal | F99: D_004 | G99: Email Marketing Specialist | H99: Contract | I99: MGR104 | J99: 470000 | K99: 35000 | L99: 505000 | M99: 7 | N99: 3.6 | O99: 91.8 | P99: 1 | Q99: No | R99: High | S99: NA | T99: Active | U99: geeta | V99: saxena | W99: Geeta Saxena | X99: GS048 | Y99: Admin | Z99: 505000 | AA99: Low | AB99: Female | AC99: Bachelor | AD99: Hyderabad | AE99: South | AF99: Not Eligible
A100: EMP088 | B100: 34971 | C100: 29 | D100: 44979 | E100: Referral | F100: D_002 | G100: HR Coordinator | H100: Contract | I100: MGR102 | J100: 460000 | K100: 34000 | L100: 494000 | M100: 4 | N100: 3.6 | O100: 91.5 | P100: 1 | Q100: No | R100: High | S100: NA | T100: Active | U100: sonal | V100: kapoor | W100: Sonal Kapoor | X100: SK088 | Y100: HR | Z100: 494000 | AA100: Low | AB100: Female | AC100: Bachelor | AD100: Mumbai | AE100: West | AF100: Not Eligible
A101: EMP018 | B101: 34209 | C101: 31 | D101: 44249 | E101: Job Portal | F101: D_004 | G101: Content Writer | H101: Contract | I101: MGR104 | J101: 450000 | K101: 32000 | L101: 482000 | M101: 6 | N101: 3.6 | O101: 91.2 | P101: 1 | Q101: No | R101: High | S101: NA | T101: Active | U101: meera | V101: bhat | W101: Meera Bhat | X101: MB018 | Y101: Admin | Z101: 482000 | AA101: Low | AB101: Female | AC101: Master | AD101: Pune | AE101: West | AF101: Not Eligible
B114: Row Labels | C114: Sum of Total_Salary
B115: Admin | C115: 11326000
B116: Finance | C116: 15842000
B117: HR | C117: 8643000
B118: IT | C118: 20508000
B119: Marketing | C119: 14605000
B120: Sales | C120: 15047000
B121: Grand Total | C121: 85971000
B149: Row Labels | C149: Count of Emp_ID
B150: Bangalore | C150: 17
B151: Chennai | C151: 12
B152: Delhi | C152: 13
B153: Hyderabad | C153: 12
B154: Mumbai | C154: 18
B155: Noida | C155: 12
B156: Pune | C156: 16
B157: Grand Total | C157: 100
B163: Region | C163: Location | D163: Count of Emp_ID
B164: North | C164: Delhi | D164: 13
C165: Noida | D165: 11
...

Sheet Dashboard
A1: HR Data Analysis
